Workbook

Sheet Stock y price
A1: PRODUCTO (A) | B1: PRECIO (B) | C1: (C) | D1: STOCK (D) | E1: (E) | F1: MARCA (F) | G1: CATEGORIA (G) | H1: COSTO | J1: COMISION | L1: Costo Aereo | M1: Aereo+costo | N1: Total costo | O1: PESO
A2: Peak Pro 3DXL - Onyx | B2: 380 | C2: C | D2: 0 | F2: PUFFCO | G2: VAPORIZADOR | H2: 317.43177 | I2: =(B2/H2)-1 -> 0.19710765 | J2: =(B2-H2)/2 -> 31.284115 | L2: =(O2*38) -> 30.058 | M2: =L2+268 -> 298.058 | N2: =M2*1.065 -> 317.43177 | O2: 0.791 | Q2: =H2*D2 -> 0
A3: Peak Pro 3DXL - Pearl | B3: 380 | C3: C | D3: 0 | F3: PUFFCO | G3: VAPORIZADOR | H3: 317.43177 | I3: =(B3/H3)-1 -> 0.19710765 | J3: =(B3-H3)/2 -> 31.284115 | L3: =(O3*38) -> 30.058 | M3: =L3+268 -> 298.058 | N3: =M3*1.065 -> 317.43177 | O3: 0.791 | Q3: =H3*D3 -> 0
A4: Peak Pro 3DXL - PLASMA | B4: 380 | C4: C | D4: 0 | F4: PUFFCO | G4: VAPORIZADOR | H4: 317.43177 | I4: =(B4/H4)-1 -> 0.19710765 | J4: =(B4-H4)/2 -> 31.284115 | L4: =(O4*38) -> 30.058 | M4: =L4+268 -> 298.058 | N4: =M4*1.065 -> 317.43177 | O4: 0.791 | Q4: =H4*D4 -> 0
A5: Proxy - Haze | B5: 230 | C5: C | D5: 9 | F5: PUFFCO | G5: VAPORIZADOR | H5: 190.11102 | I5: =(B5/H5)-1 -> 0.2098194 | J5: =(B5-H5)/2 -> 19.94449 | L5: =(O5*38) -> 21.508 | M5: =L5+157 -> 178.508 | N5: =M5*1.065 -> 190.11102 | O5: 0.566 | Q5: =H5*D5 -> 1710.9992
A6: Proxy - Onyx | B6: 230 | C6: C | D6: 0 | F6: PUFFCO | G6: VAPORIZADOR | H6: 190.11102 | I6: =(B6/H6)-1 -> 0.2098194 | J6: =(B6-H6)/2 -> 19.94449 | L6: =(O6*38) -> 21.508 | M6: =L6+157 -> 178.508 | N6: =M6*1.065 -> 190.11102 | O6: 0.566 | Q6: =H6*D6 -> 0
A7: Proxy Core PINE | B7: 210 | C7: C | D7: 2 | F7: PUFFCO | G7: VAPORIZADOR | H7: 173.78031 | I7: =(B7/H7)-1 -> 0.20842229 | J7: =(B7-H7)/2 -> 18.109845 | L7: =(O7*38) -> 14.174 | M7: =L7+149 -> 163.174 | N7: =M7*1.065 -> 173.78031 | O7: 0.373 | Q7: =H7*D7 -> 347.56062
A8: Proxy Core ONIX | B8: 210 | C8: C | D8: 0 | F8: PUFFCO | G8: VAPORIZADOR | H8: 173.78031 | I8: =(B8/H8)-1 -> 0.20842229 | J8: =(B8-H8)/2 -> 18.109845 | L8: =(O8*38) -> 14.174 | M8: =L8+149 -> 163.174 | N8: =M8*1.065 -> 173.78031 | O8: 0.373 | Q8: =H8*D8 -> 0
A9: Proxy Core silicona ONIX | B9: 50 | C9: C | D9: 3 | F9: PUFFCO | G9: ACCESORIO | H9: 32.802 | I9: =(B9/H9)-1 -> 0.5242973 | J9: =(B9-H9)/2 -> 8.599 | L9: =(O9*38) -> 3.8 | M9: =L9+27 -> 30.8 | N9: =M9*1.065 -> 32.802 | O9: 0.1 | Q9: =H9*D9 -> 98.406
A10: Proxy Core silicona HAZE | B10: 50 | C10: C | D10: 6 | F10: PUFFCO | G10: ACCESORIO | H10: 32.802 | I10: =(B10/H10)-1 -> 0.5242973 | J10: =(B10-H10)/2 -> 8.599 | L10: =(O10*38) -> 3.8 | M10: =L10+27 -> 30.8 | N10: =M10*1.065 -> 32.802 | O10: 0.1 | Q10: =H10*D10 -> 196.812
A11: Pivot - Storm | B11: 120 | C11: C | D11: 1 | F11: PUFFCO | G11: VAPORIZADOR | H11: 98.7681 | I11: =(B11/H11)-1 -> 0.21496718 | J11: =(B11-H11)/2 -> 10.61595 | L11: =(O11*38) -> 8.74 | M11: =L11+84 -> 92.74 | N11: =M11*1.065 -> 98.7681 | O11: 0.23 | Q11: =H11*D11 -> 98.7681
A12: Pivot - Onyx | B12: 120 | C12: C | D12: 3 | F12: PUFFCO | G12: VAPORIZADOR | H12: 98.7681 | I12: =(B12/H12)-1 -> 0.21496718 | J12: =(B12-H12)/2 -> 10.61595 | L12: =(O12*38) -> 8.74 | M12: =L12+84 -> 92.74 | N12: =M12*1.065 -> 98.7681 | O12: 0.23 | Q12: =H12*D12 -> 296.3043
A13: Peak - Amarillo | B13: 215 | C13: C | D13: 3 | F13: PUFFCO | G13: VAPORIZADOR | H13: 185.1396 | I13: =(B13/H13)-1 -> 0.16128586 | J13: =(B13-H13)/2 -> 14.9302 | L13: =(O13*38) -> 25.84 | M13: =L13+148 -> 173.84 | N13: =M13*1.065 -> 185.1396 | O13: 0.68 | Q13: =H13*D13 -> 555.4188
A14: Peak - Storm | B14: 215 | C14: C | D14: 0 | F14: PUFFCO | G14: VAPORIZADOR | H14: 185.1396 | I14: =(B14/H14)-1 -> 0.16128586 | J14: =(B14-H14)/2 -> 14.9302 | L14: =(O14*38) -> 25.84 | M14: =L14+148 -> 173.84 | N14: =M14*1.065 -> 185.1396 | O14: 0.68 | Q14: =H14*D14 -> 0
A15: Peak - Onyx | B15: 215 | C15: C | D15: 0 | F15: PUFFCO | G15: VAPORIZADOR | H15: 185.1396 | I15: =(B15/H15)-1 -> 0.16128586 | J15: =(B15-H15)/2 -> 14.9302 | L15: =(O15*38) -> 25.688 | M15: =L15+148 -> 173.688 | N15: =M15*1.065 -> 184.97772 | O15: 0.676 | Q15: =H15*D15 -> 0
A16: Proxy Bub - Haze | B16: 90 | C16: C | D16: 4 | F16: PUFFCO | G16: ACCESORIO | H16: 70.65636 | I16: =(B16/H16)-1 -> 0.27377068 | J16: =(B16-H16)/2 -> 9.67182 | L16: =(O16*38) -> 12.844 | M16: =L16+53.5 -> 66.344 | N16: =M16*1.065 -> 70.65636 | O16: 0.338 | Q16: =H16*D16 -> 282.62544
A17: Proxy Bub - Onyx | B17: 90 | C17: C | D17: 0 | F17: PUFFCO | G17: ACCESORIO | H17: 70.65636 | I17: =(B17/H17)-1 -> 0.27377068 | J17: =(B17-H17)/2 -> 9.67182 | L17: =(O17*38) -> 12.844 | M17: =L17+53.5 -> 66.344 | N17: =M17*1.065 -> 70.65636 | O17: 0.338 | Q17: =H17*D17 -> 0
A18: Proxy Bub Wizard - Haze | B18: 90 | C18: C | D18: 0 | F18: PUFFCO | G18: ACCESORIO | H18: 71.02059 | I18: =(B18/H18)-1 -> 0.26723813 | J18: =(B18-H18)/2 -> 9.489705 | L18: =(O18*38) -> 13.186 | M18: =L18+53.5 -> 66.686 | N18: =M18*1.065 -> 71.02059 | O18: 0.347 | Q18: =H18*D18 -> 0
A19: Proxy Bub Wizard - Onyx | B19: 90 | C19: C | D19: 2 | F19: PUFFCO | G19: ACCESORIO | H19: 71.02059 | I19: =(B19/H19)-1 -> 0.26723813 | J19: =(B19-H19)/2 -> 9.489705 | L19: =(O19*38) -> 13.186 | M19: =L19+53.5 -> 66.686 | N19: =M19*1.065 -> 71.02059 | O19: 0.347 | Q19: =H19*D19 -> 142.04118
A20: Proxy Bub viejo - Onyx | B20: 90 | C20: C | D20: 0 | F20: PUFFCO | G20: ACCESORIO | H20: 71.142 | I20: =(B20/H20)-1 -> 0.26507548 | J20: =(B20-H20)/2 -> 9.429 | L20: =(O20*38) -> 13.3 | M20: =L20+53.5 -> 66.8 | N20: =M20*1.065 -> 71.142 | O20: 0.35 | Q20: =H20*D20 -> 0
A21: Proxy wizard - marron | B21: 100 | C21: C | D21: 0 | F21: PUFFCO | G21: ACCESORIO | H21: 73 | I21: =(B21/H21)-1 -> 0.36986301 | J21: =(B21-H21)/2 -> 13.5 | L21: =(O21*38) -> 13.3 | M21: =L21+55 -> 68.3 | N21: =M21*1.065 -> 72.7395 | O21: 0.35 | Q21: =H21*D21 -> 0
A22: Peak Pro 3DXL Chamber clasico | B22: 80 | C22: C | D22: 0 | F22: PUFFCO | G22: REPUESTO | H22: 57.297 | I22: =(B22/H22)-1 -> 0.39623366 | J22: =(B22-H22)/2 -> 11.3515 | L22: =(O22*38) -> 3.8 | M22: =L22+50 -> 53.8 | N22: =M22*1.065 -> 57.297 | O22: 0.1 | Q22: =H22*D22 -> 0
A23: Peak Pro 3DXL Chamber - PLASMA | B23: 80 | C23: C | D23: 17 | F23: PUFFCO | G23: REPUESTO | H23: 57.297 | I23: =(B23/H23)-1 -> 0.39623366 | J23: =(B23-H23)/2 -> 11.3515 | L23: =(O23*38) -> 3.8 | M23: =L23+50 -> 53.8 | N23: =M23*1.065 -> 57.297 | O23: 0.1 | Q23: =H23*D23 -> 974.049
A24: Hot knife NEW NEGRO | B24: 60 | C24: C | D24: 3 | F24: PUFFCO | G24: ACCESORIO | H24: 46.647 | I24: =(B24/H24)-1 -> 0.28625635 | J24: =(B24-H24)/2 -> 6.6765 | L24: =(O24*38) -> 3.8 | M24: =L24+40 -> 43.8 | N24: =M24*1.065 -> 46.647 | O24: 0.1 | Q24: =H24*D24 -> 139.941
A25: Hot knife NEW PEARL | B25: 60 | C25: C | D25: 2 | F25: PUFFCO | G25: ACCESORIO | H25: 46.647 | I25: =(B25/H25)-1 -> 0.28625635 | J25: =(B25-H25)/2 -> 6.6765 | L25: =(O25*38) -> 3.8 | M25: =L25+40 -> 43.8 | N25: =M25*1.065 -> 46.647 | O25: 0.1 | Q25: =H25*D25 -> 93.294
A26: Hot Knife NEW PINE | B26: 60 | C26: C | D26: 3 | F26: PUFFCO | G26: ACCESORIO | H26: 46.647 | I26: =(B26/H26)-1 -> 0.28625635 | J26: =(B26-H26)/2 -> 6.6765 | L26: =(O26*38) -> 3.8 | M26: =L26+40 -> 43.8 | N26: =M26*1.065 -> 46.647 | O26: 0.1 | Q26: =H26*D26 -> 139.941
A27: Hot Knife NEW PLASMA | B27: 60 | C27: C | D27: 0 | F27: PUFFCO | G27: ACCESORIO | H27: 46.647 | I27: =(B27/H27)-1 -> 0.28625635 | J27: =(B27-H27)/2 -> 6.6765 | L27: =(O27*38) -> 3.8 | M27: =L27+40 -> 43.8 | N27: =M27*1.065 -> 46.647 | O27: 0.1 | Q27: =H27*D27 -> 0
A28: BAG PEAK PRO | B28: 50 | C28: C | D28: 0 | F28: PUFFCO | G28: ACCESORIO | H28: 39.34 | I28: =(B28/H28)-1 -> 0.27097102 | J28: =(B28-H28)/2 -> 5.33 | L28: =(O28*38) -> #N/A | M28: =L28+250 -> #N/A | N28: =M28*1.065 -> #N/A | O28: #N/A | Q28: =H28*D28 -> 0
A29: Peak Pro 3D Chamber | B29: 70 | C29: C | D29: 0 | F29: PUFFCO | G29: REPUESTO | H29: 52.3767 | I29: =(B29/H29)-1 -> 0.33647213 | J29: =(B29-H29)/2 -> 8.81165 | L29: =(O29*38) -> 4.18 | M29: =L29+45 -> 49.18 | N29: =M29*1.065 -> 52.3767 | O29: 0.11 | Q29: =H29*D29 -> 0
A30: Peak Pro TRAVEL GLASS SHADOW | B30: 85 | C30: C | D30: 0 | F30: PUFFCO | G30: ACCESORIO | H30: 57.946 | I30: =(B30/H30)-1 -> 0.46688296 | J30: =(B30-H30)/2 -> 13.527 | L30: =(O30*38) -> #N/A | M30: =L30+61 -> #N/A | N30: =M30*1.065 -> #N/A | O30: #N/A | Q30: =H30*D30 -> 0
A31: Peak Pro TRAVEL GLASS | B31: 85 | C31: C | D31: 0 | F31: PUFFCO | G31: ACCESORIO | H31: 57.946 | I31: =(B31/H31)-1 -> 0.46688296 | J31: =(B31-H31)/2 -> 13.527 | L31: =(O31*38) -> #N/A | M31: =L31+61 -> #N/A | N31: =M31*1.065 -> #N/A | O31: #N/A | Q31: =H31*D31 -> 0
A32: Peak Pro Glass 2.0 | B32: 75 | C32: C | D32: 5 | F32: PUFFCO | G32: ACCESORIO | H32: 57.946 | I32: =(B32/H32)-1 -> 0.29430849 | J32: =(B32-H32)/2 -> 8.527 | L32: =(O32*38) -> #N/A | M32: =L32+53.5 -> #N/A | N32: =M32*1.065 -> #N/A | O32: #N/A | Q32: =H32*D32 -> 289.73
A33: Proxy 3D Chamber - Onyx | B33: 37 | C33: C | D33: 14 | F33: PUFFCO | G33: REPUESTO | H33: 29.80722 | I33: =(B33/H33)-1 -> 0.24130999 | J33: =(B33-H33)/2 -> 3.59639 | L33: =(O33*38) -> 0.988 | M33: =L33+27 -> 27.988 | N33: =M33*1.065 -> 29.80722 | O33: 0.026 | Q33: =H33*D33 -> 417.30108
A34: Peak 3D Chamber - Onyx | B34: 45 | C34: C | D34: 49 | F34: PUFFCO | G34: REPUESTO | H34: 36.97893 | I34: =(B34/H34)-1 -> 0.2169092 | J34: =(B34-H34)/2 -> 4.010535 | L34: =(O34*38) -> 0.722 | M34: =L34+34 -> 34.722 | N34: =M34*1.065 -> 36.97893 | O34: 0.019 | Q34: =H34*D34 -> 1811.9676
A35: Pivot 3D Chamber 2-Pack - Onyx | B35: 55 | C35: C | D35: 24 | F35: PUFFCO | G35: REPUESTO | H35: 37.45179 | I35: =(B35/H35)-1 -> 0.46855464 | J35: =(B35-H35)/2 -> 8.774105 | L35: =(O35*38) -> 2.166 | M35: =L35+33 -> 35.166 | N35: =M35*1.065 -> 37.45179 | O35: 0.057 | Q35: =H35*D35 -> 898.84296
A36: Pivot Glass Adapter with 3D Chamber - Onyx | B36: 60 | C36: C | D36: 6 | F36: PUFFCO | G36: ACCESORIO | H36: 43.15593 | I36: =(B36/H36)-1 -> 0.3903072 | J36: =(B36-H36)/2 -> 8.422035 | L36: =(O36*38) -> 4.522 | M36: =L36+36 -> 40.522 | N36: =M36*1.065 -> 43.15593 | O36: 0.119 | Q36: =H36*D36 -> 258.93558
A37: Plus Dark Pack | B37: 10 | C37: C | D37: 0 | F37: PUFFCO | G37: ACCESORIO | H37: 5.06 | I37: =(B37/H37)-1 -> 0.97628459 | J37: =(B37-H37)/2 -> 2.47 | L37: =(O37*38) -> #N/A | M37: =L37+250 -> #N/A | N37: =M37*1.065 -> #N/A | O37: #N/A | Q37: =H37*D37 -> 0
A38: Plus Supercharger | B38: 4 | C38: C | D38: 0 | F38: PUFFCO | G38: ACCESORIO | H38: 5.06 | I38: =(B38/H38)-1 -> -0.20948617 | J38: =(B38-H38)/2 -> -0.53 | L38: =(O38*38) -> #N/A | M38: =L38+250 -> #N/A | N38: =M38*1.065 -> #N/A | O38: #N/A | Q38: =H38*D38 -> 0
A39: Plus Battery - Pearl | B39: 25 | C39: C | D39: 0 | F39: PUFFCO | G39: REPUESTO | H39: 32.492 | I39: =(B39/H39)-1 -> -0.23057984 | J39: =(B39-H39)/2 -> -3.746 | L39: =(O39*38) -> 6.992 | M39: =L39+250 -> 256.992 | N39: =M39*1.065 -> 273.69648 | O39: 0.184 | Q39: =H39*D39 -> 0
A40: Chamber Plus - Pearl | B40: 15 | C40: C | D40: 0 | F40: PUFFCO | G40: REPUESTO | H40: 11 | I40: =(B40/H40)-1 -> 0.36363636 | J40: =(B40-H40)/2 -> 2 | L40: =(O40*38) -> #N/A | M40: =L40+250 -> #N/A | N40: =M40*1.065 -> #N/A | O40: #N/A | Q40: =H40*D40 -> 0
A41: Pivot Mouthpiece 2-Pack pine | B41: 15 | C41: C | D41: 6 | F41: PUFFCO | G41: REPUESTO | H41: 11.28 | I41: =(B41/H41)-1 -> 0.32978723 | J41: =(B41-H41)/2 -> 1.86 | L41: =(O41*38) -> #N/A | M41: =L41+250 -> #N/A | N41: =M41*1.065 -> #N/A | O41: #N/A | Q41: =H41*D41 -> 67.68
A42: Pivot Mouthpiece 2-Pack moca | B42: 15 | C42: C | D42: 6 | F42: PUFFCO | G42: REPUESTO | H42: 11.28 | I42: =(B42/H42)-1 -> 0.32978723 | J42: =(B42-H42)/2 -> 1.86 | L42: =(O42*38) -> #N/A | M42: =L42+250 -> #N/A | N42: =M42*1.065 -> #N/A | O42: #N/A | Q42: =H42*D42 -> 67.68
A43: Pivot Mouthpiece 2-Pack slate | B43: 15 | C43: C | D43: 6 | F43: PUFFCO | G43: REPUESTO | H43: 11.28 | I43: =(B43/H43)-1 -> 0.32978723 | J43: =(B43-H43)/2 -> 1.86 | L43: =(O43*38) -> #N/A | M43: =L43+250 -> #N/A | N43: =M43*1.065 -> #N/A | O43: #N/A | Q43: =H43*D43 -> 67.68
A44: Peak Atomizer | B44: 28 | C44: C | D44: 18 | F44: PUFFCO | G44: REPUESTO | H44: 21.832 | I44: =(B44/H44)-1 -> 0.28252107 | J44: =(B44-H44)/2 -> 3.084 | L44: =(O44*38) -> 4.332 | M44: =L44+250 -> 254.332 | N44: =M44*1.065 -> 270.86358 | O44: 0.114 | Q44: =H44*D44 -> 392.976
A45: Joystick cap Peak New | B45: 18 | C45: C | D45: 0 | F45: PUFFCO | G45: REPUESTO | L45: =(O45*38) -> #N/A | M45: =L45+250 -> #N/A | N45: =M45*1.065 -> #N/A | O45: #N/A | Q45: =H45*D45 -> 0
A46: Adaptador Peak Pro Link | B46: 120 | C46: C | D46: 1 | F46: PUFFCO | G46: ACCESORIO | H46: 89.162 | I46: =(B46/H46)-1 -> 0.34586483 | J46: =(B46-H46)/2 -> 15.419 | L46: =(O46*38) -> 15.162 | M46: =L46+250 -> 265.162 | N46: =M46*1.065 -> 282.39753 | O46: 0.399 | Q46: =H46*D46 -> 89.162
A47: PUFFCO TRAVEL CASE ROJO | B47: 60 | C47: C | D47: 0 | F47: PUFFCO | G47: ACCESORIO | I47: =(B47/H47)-1 -> #DIV/0! | J47: =(B47-H47)/2 -> 30 | L47: =(O47*38) -> 19 | M47: =L47+30 -> 49 | N47: =M47*1.065 -> 52.185 | O47: 0.5 | Q47: =H47*D47 -> 0
A48: PUFFCO TRAVEL CASE STORM | B48: 60 | C48: C | D48: 0 | F48: PUFFCO | G48: REPUESTO | I48: =(B48/H48)-1 -> #DIV/0! | J48: =(B48-H48)/2 -> 30 | L48: =(O48*38) -> 19 | M48: =L48+30 -> 49 | N48: =M48*1.065 -> 52.185 | O48: 0.5 | Q48: =H48*D48 -> 0
A49: PUFFCO TRAVEL CASE PLATEADO | B49: 60 | C49: C | D49: 8 | F49: PUFFCO | G49: REPUESTO | I49: =(B49/H49)-1 -> #DIV/0! | J49: =(B49-H49)/2 -> 30 | L49: =(O49*38) -> 19 | M49: =L49+30 -> 49 | N49: =M49*1.065 -> 52.185 | O49: 0.5 | Q49: =H49*D49 -> 0
A50: BigFun! Puffco Pivot Tops - Drei | B50: 30 | C50: C | D50: 0 | F50: BigFun | G50: ACCESORIO | H50: 15.95 | I50: =(B50/H50)-1 -> 0.88087774 | J50: =(B50-H50)/2 -> 7.025 | L50: =(O50*38) -> 0.95 | M50: =L50+7.2 -> 8.15 | N50: =M50*1.065 -> 8.67975 | O50: 0.025 | Q50: =H50*D50 -> 0
A51: BigFun! Puffco Pivot Tops - LIL' Frosty | B51: 40 | C51: C | D51: 3 | F51: BigFun | G51: ACCESORIO | H51: 18.76 | I51: =(B51/H51)-1 -> 1.1321962 | J51: =(B51-H51)/2 -> 10.62 | L51: =(O51*38) -> 0.76 | M51: =L51+250 -> 250.76 | N51: =M51*1.065 -> 267.0594 | O51: 0.02 | Q51: =H51*D51 -> 56.28
A52: BigFun! Puffco Pivot Tops - LIL' X | B52: 36 | C52: C | D52: 4 | F52: BigFun | G52: ACCESORIO | H52: 22.178 | I52: =(B52/H52)-1 -> 0.62323023 | J52: =(B52-H52)/2 -> 6.911 | L52: =(O52*38) -> 1.178 | M52: =L52+250 -> 251.178 | N52: =M52*1.065 -> 267.50457 | O52: 0.031 | Q52: =H52*D52 -> 88.712
A53: Bubble Pivot Top - Iridescent | B53: 30 | C53: C | D53: 0 | F53: BigFun | G53: ACCESORIO | H53: 18.76 | I53: =(B53/H53)-1 -> 0.59914712 | J53: =(B53-H53)/2 -> 5.62 | L53: =(O53*38) -> #N/A | M53: =L53+250 -> #N/A | N53: =M53*1.065 -> #N/A | O53: #N/A | Q53: =H53*D53 -> 0
A54: Bubble Peak Top - Iridescent | B54: 50 | C54: C | D54: 0 | F54: BigFun | G54: ACCESORIO | H54: 22.178 | I54: =(B54/H54)-1 -> 1.2544864 | J54: =(B54-H54)/2 -> 13.911 | L54: =(O54*38) -> #N/A | M54: =L54+250 -> #N/A | N54: =M54*1.065 -> #N/A | O54: #N/A | Q54: =H54*D54 -> 0
A55: BigFun! Puffco Peak Tops - Big X pinito | B55: 65 | C55: C | D55: 2 | F55: BigFun | G55: ACCESORIO | H55: 40 | I55: =(B55/H55)-1 -> 0.625 | J55: =(B55-H55)/2 -> 12.5 | L55: =(O55*38) -> #N/A | M55: =L55+250 -> #N/A | N55: =M55*1.065 -> #N/A | O55: #N/A | Q55: =H55*D55 -> 80
A56: BigFun! Puffco Peak Tops - Big Frosty muñeco nieve | B56: 60 | C56: C | D56: 2 | F56: BigFun | G56: ACCESORIO | H56: 34 | I56: =(B56/H56)-1 -> 0.76470588 | J56: =(B56-H56)/2 -> 13 | L56: =(O56*38) -> #N/A | M56: =L56+250 -> #N/A | N56: =M56*1.065 -> #N/A | O56: #N/A | Q56: =H56*D56 -> 68
A57: Tricolor Peak Tops - Canopy | B57: 40 | C57: C | D57: 3 | F57: BigFun | G57: ACCESORIOS | H57: 21.32 | I57: =(B57/H57)-1 -> 0.87617261 | J57: =(B57-H57)/2 -> 9.34 | L57: =(O57*38) -> #N/A | M57: =L57+250 -> #N/A | N57: =M57*1.065 -> #N/A | O57: #N/A | Q57: =H57*D57 -> 63.96
A58: Tricolor Peak Tops - Sorbet | B58: 40 | C58: C | D58: 5 | F58: BigFun | G58: ACCESORIOS | H58: 21.32 | I58: =(B58/H58)-1 -> 0.87617261 | J58: =(B58-H58)/2 -> 9.34 | L58: =(O58*38) -> #N/A | M58: =L58+250 -> #N/A | N58: =M58*1.065 -> #N/A | O58: #N/A | Q58: =H58*D58 -> 106.6
A59: Tricolor Pivot Tops - Canopy | B59: 20 | C59: C | D59: 9 | E59: =D59 + SUMIF('Hoja 33'!A:A, A59, 'Hoja 33'!B:B) -> #N/A | F59: BigFun | G59: ACCESORIOS | H59: 8.98 | I59: =(B59/H59)-1 -> 1.2271715 | J59: =(B59-H59)/2 -> 5.51 | L59: =(O59*38) -> #N/A | M59: =L59+250 -> #N/A | N59: =M59*1.065 -> #N/A | O59: #N/A | Q59: =H59*D59 -> 80.82
A60: Tricolor Pivot Tops - Sorbet | B60: 20 | C60: C | D60: 10 | E60: =D60 + SUMIF('Hoja 33'!A:A, A60, 'Hoja 33'!B:B) -> #N/A | F60: BigFun | G60: ACCESORIOS | H60: 8.98 | I60: =(B60/H60)-1 -> 1.2271715 | J60: =(B60-H60)/2 -> 5.51 | L60: =(O60*38) -> #N/A | M60: =L60+250 -> #N/A | N60: =M60*1.065 -> #N/A | O60: #N/A | Q60: =H60*D60 -> 89.8
A61: Empire Glassworks Puffco Peak Tops - Renew the Redwood | B61: 170 | C61: C | D61: 4 | E61: =D61 + SUMIF('Hoja 33'!A:A, A61, 'Hoja 33'!B:B) -> #N/A | F61: Empire Glass | G61: ACCESORIO | H61: 115 | I61: =(B61/H61)-1 -> 0.47826087 | J61: =(B61-H61)/2 -> 27.5 | L61: =(O61*38) -> #N/A | M61: =L61+250 -> #N/A | N61: =M61*1.065 -> #N/A | O61: #N/A | Q61: =H61*D61 -> 460
A62: Empire Glassworks Puffco Peak Tops - Rocket Ship | B62: 170 | C62: C | D62: 4 | E62: =D62 + SUMIF('Hoja 33'!A:A, A62, 'Hoja 33'!B:B) -> #N/A | F62: Empire Glass | G62: ACCESORIO | H62: 115 | I62: =(B62/H62)-1 -> 0.47826087 | J62: =(B62-H62)/2 -> 27.5 | L62: =(O62*38) -> #N/A | M62: =L62+250 -> #N/A | N62: =M62*1.065 -> #N/A | O62: #N/A | Q62: =H62*D62 -> 460
A63: Empire Glassworks Puffco Peak Tops - Save the Bees | B63: 170 | C63: C | D63: 0 | E63: =D63 + SUMIF('Hoja 33'!A:A, A63, 'Hoja 33'!B:B) -> #N/A | F63: Empire Glass | G63: ACCESORIO | H63: 115 | I63: =(B63/H63)-1 -> 0.47826087 | J63: =(B63-H63)/2 -> 27.5 | L63: =(O63*38) -> #N/A | M63: =L63+250 -> #N/A | N63: =M63*1.065 -> #N/A | O63: #N/A | Q63: =H63*D63 -> 0
A64: Empire Glassworks Puffco Peak Tops - Save the Seas | B64: 170 | C64: C | D64: 0 | E64: =D64 + SUMIF('Hoja 33'!A:A, A64, 'Hoja 33'!B:B) -> #N/A | F64: Empire Glass | G64: ACCESORIO | H64: 115 | I64: =(B64/H64)-1 -> 0.47826087 | J64: =(B64-H64)/2 -> 27.5 | L64: =(O64*38) -> #N/A | M64: =L64+250 -> #N/A | N64: =M64*1.065 -> #N/A | O64: #N/A | Q64: =H64*D64 -> 0
A65: Peak Pro 3DXL Joystick Caps - Black Nebula | B65: 16 | C65: C | D65: 0 | E65: =D65 + SUMIF('Hoja 33'!A:A, A65, 'Hoja 33'!B:B) -> #N/A | F65: Human Grade | G65: ACCESORIO | H65: 11.0547 | I65: =(B65/H65)-1 -> 0.44734819 | J65: =(B65-H65)/2 -> 2.47265 | L65: =(O65*38) -> 0.38 | M65: =L65+10 -> 10.38 | N65: =M65*1.065 -> 11.0547 | O65: 0.01 | Q65: =H65*D65 -> 0
A66: Peak Pro 3DXL Joystick Caps Blue Lagoon | B66: 16 | C66: C | D66: 0 | E66: =D66 + SUMIF('Hoja 33'!A:A, A66, 'Hoja 33'!B:B) -> #N/A | F66: Human Grade | G66: ACCESORIO | H66: 11.0547 | I66: =(B66/H66)-1 -> 0.44734819 | J66: =(B66-H66)/2 -> 2.47265 | L66: =(O66*38) -> 0.38 | M66: =L66+10 -> 10.38 | N66: =M66*1.065 -> 11.0547 | O66: 0.01 | Q66: =H66*D66 -> 0
A67: Peak Pro 3DXL Joystick Caps - Clear | B67: 16 | C67: C | D67: 1 | E67: =D67 + SUMIF('Hoja 33'!A:A, A67, 'Hoja 33'!B:B) -> #N/A | F67: Human Grade | G67: ACCESORIO | H67: 11.0547 | I67: =(B67/H67)-1 -> 0.44734819 | J67: =(B67-H67)/2 -> 2.47265 | L67: =(O67*38) -> 0.38 | M67: =L67+10 -> 10.38 | N67: =M67*1.065 -> 11.0547 | O67: 0.01 | Q67: =H67*D67 -> 11.0547
A68: Peak Pro 3DXL Joystick Caps - Eclipse | B68: 16 | C68: C | D68: 1 | E68: =D68 + SUMIF('Hoja 33'!A:A, A68, 'Hoja 33'!B:B) -> #N/A | F68: Human Grade | G68: ACCESORIO | H68: 11.0547 | I68: =(B68/H68)-1 -> 0.44734819 | J68: =(B68-H68)/2 -> 2.47265 | L68: =(O68*38) -> 0.38 | M68: =L68+10 -> 10.38 | N68: =M68*1.065 -> 11.0547 | O68: 0.01 | Q68: =H68*D68 -> 11.0547
A69: Peak Pro 3DXL Joystick Caps - Firestone Red | B69: 16 | C69: C | D69: 1 | E69: =D69 + SUMIF('Hoja 33'!A:A, A69, 'Hoja 33'!B:B) -> #N/A | F69: Human Grade | G69: ACCESORIO | H69: 11.0547 | I69: =(B69/H69)-1 -> 0.44734819 | J69: =(B69-H69)/2 -> 2.47265 | L69: =(O69*38) -> 0.38 | M69: =L69+10 -> 10.38 | N69: =M69*1.065 -> 11.0547 | O69: 0.01 | Q69: =H69*D69 -> 11.0547
A70: Peak Pro 3DXL Joystick Caps Glow in the Dark | B70: 16 | C70: C | D70: 2 | E70: =D70 + SUMIF('Hoja 33'!A:A, A70, 'Hoja 33'!B:B) -> #N/A | F70: Human Grade | G70: ACCESORIO | H70: 11.0547 | I70: =(B70/H70)-1 -> 0.44734819 | J70: =(B70-H70)/2 -> 2.47265 | L70: =(O70*38) -> 0.38 | M70: =L70+10 -> 10.38 | N70: =M70*1.065 -> 11.0547 | O70: 0.01 | Q70: =H70*D70 -> 22.1094
A71: Peak Pro 3DXL Joystick Caps - Orange | B71: 16 | C71: C | D71: 1 | E71: =D71 + SUMIF('Hoja 33'!A:A, A71, 'Hoja 33'!B:B) -> #N/A | F71: Human Grade | G71: ACCESORIO | H71: 11.0547 | I71: =(B71/H71)-1 -> 0.44734819 | J71: =(B71-H71)/2 -> 2.47265 | L71: =(O71*38) -> 0.38 | M71: =L71+10 -> 10.38 | N71: =M71*1.065 -> 11.0547 | O71: 0.01 | Q71: =H71*D71 -> 11.0547
A72: Peak Pro 3DXL Joystick Caps - Pink UV | B72: 16 | C72: C | D72: 2 | E72: =D72 + SUMIF('Hoja 33'!A:A, A72, 'Hoja 33'!B:B) -> #N/A | F72: Human Grade | G72: ACCESORIO | H72: 11.0547 | I72: =(B72/H72)-1 -> 0.44734819 | J72: =(B72-H72)/2 -> 2.47265 | L72: =(O72*38) -> 0.38 | M72: =L72+10 -> 10.38 | N72: =M72*1.065 -> 11.0547 | O72: 0.01 | Q72: =H72*D72 -> 22.1094
A73: Peak Pro 3DXL Joystick Caps - Slime | B73: 16 | C73: C | D73: 2 | E73: =D73 + SUMIF('Hoja 33'!A:A, A73, 'Hoja 33'!B:B) -> #N/A | F73: Human Grade | G73: ACCESORIO | H73: 11.0547 | I73: =(B73/H73)-1 -> 0.44734819 | J73: =(B73-H73)/2 -> 2.47265 | L73: =(O73*38) -> 0.38 | M73: =L73+10 -> 10.38 | N73: =M73*1.065 -> 11.0547 | O73: 0.01 | Q73: =H73*D73 -> 22.1094
A74: Peak Pro 3DXL Joystick Caps - Sunrise | B74: 16 | C74: C | D74: 0 | E74: =D74 + SUMIF('Hoja 33'!A:A, A74, 'Hoja 33'!B:B) -> #N/A | F74: Human Grade | G74: ACCESORIO | H74: 11.0547 | I74: =(B74/H74)-1 -> 0.44734819 | J74: =(B74-H74)/2 -> 2.47265 | L74: =(O74*38) -> 0.38 | M74: =L74+10 -> 10.38 | N74: =M74*1.065 -> 11.0547 | O74: 0.01 | Q74: =H74*D74 -> 0
A75: Peak Pro 3DXL Joystick Caps - Transparent Red | B75: 16 | C75: C | D75: 3 | E75: =D75 + SUMIF('Hoja 33'!A:A, A75, 'Hoja 33'!B:B) -> #N/A | F75: Human Grade | G75: ACCESORIO | H75: 11.0547 | I75: =(B75/H75)-1 -> 0.44734819 | J75: =(B75-H75)/2 -> 2.47265 | L75: =(O75*38) -> 0.38 | M75: =L75+10 -> 10.38 | N75: =M75*1.065 -> 11.0547 | O75: 0.01 | Q75: =H75*D75 -> 33.1641
A76: Peak Pro 3DXL Joystick Caps - Vintage | B76: 16 | C76: C | D76: 3 | E76: =D76 + SUMIF('Hoja 33'!A:A, A76, 'Hoja 33'!B:B) -> #N/A | F76: Human Grade | G76: ACCESORIO | H76: 11.0547 | I76: =(B76/H76)-1 -> 0.44734819 | J76: =(B76-H76)/2 -> 2.47265 | L76: =(O76*38) -> 0.38 | M76: =L76+10 -> 10.38 | N76: =M76*1.065 -> 11.0547 | O76: 0.01 | Q76: =H76*D76 -> 33.1641
A77: Peak Pro 3DXL Joystick Caps - Yellow | B77: 16 | C77: C | D77: 3 | E77: =D77 + SUMIF('Hoja 33'!A:A, A77, 'Hoja 33'!B:B) -> #N/A | F77: Human Grade | G77: ACCESORIO | H77: 11.0547 | I77: =(B77/H77)-1 -> 0.44734819 | J77: =(B77-H77)/2 -> 2.47265 | L77: =(O77*38) -> 0.38 | M77: =L77+10 -> 10.38 | N77: =M77*1.065 -> 11.0547 | O77: 0.01 | Q77: =H77*D77 -> 33.1641
A78: Pivot Tops Display - V1 (18) | B78: 30 | C78: C | D78: 12 | E78: =D78 + SUMIF('Hoja 33'!A:A, A78, 'Hoja 33'!B:B) -> #N/A | F78: Empire Glass | G78: ACCESORIO | H78: 16.9 | I78: =(B78/H78)-1 -> 0.77514793 | J78: =(B78-H78)/2 -> 6.55 | L78: =(O78*38) -> 1.9 | M78: =L78+250 -> 251.9 | N78: =M78*1.065 -> 268.2735 | O78: 0.05 | Q78: =H78*D78 -> 202.8
A79: Pivot Tops Display - V2 (18) | B79: 30 | C79: C | D79: 12 | E79: =D79 + SUMIF('Hoja 33'!A:A, A79, 'Hoja 33'!B:B) -> #N/A | F79: Empire Glass | G79: ACCESORIO | H79: 12.5 | I79: =(B79/H79)-1 -> 1.4 | J79: =(B79-H79)/2 -> 8.75 | L79: =(O79*38) -> 31.464 | M79: =L79+250 -> 281.464 | N79: =M79*1.065 -> 299.75916 | O79: 0.828 | Q79: =H79*D79 -> 150
A80: Chili Pepper Green (Red Hat) | B80: 12 | C80: C | D80: 1 | E80: =D80 + SUMIF('Hoja 33'!A:A, A80, 'Hoja 33'!B:B) -> #N/A | F80: Human Grade | G80: ACCESORIO | H80: 6.95 | I80: =(B80/H80)-1 -> 0.72661871 | J80: =(B80-H80)/2 -> 2.525 | L80: =(O80*38) -> 0.95 | M80: =L80+250 -> 250.95 | N80: =M80*1.065 -> 267.26175 | O80: 0.025 | Q80: =H80*D80 -> 6.95
A81: Chili Pepper - Orange (Milky Yellow Hat) | B81: 12 | C81: C | D81: 2 | E81: =D81 + SUMIF('Hoja 33'!A:A, A81, 'Hoja 33'!B:B) -> #N/A | F81: Human Grade | G81: ACCESORIO | H81: 6.95 | I81: =(B81/H81)-1 -> 0.72661871 | J81: =(B81-H81)/2 -> 2.525 | L81: =(O81*38) -> 0.95 | M81: =L81+250 -> 250.95 | N81: =M81*1.065 -> 267.26175 | O81: 0.025 | Q81: =H81*D81 -> 13.9
A82: Chili Pepper Red (Yellow Hat) | B82: 12 | C82: C | D82: 3 | E82: =D82 + SUMIF('Hoja 33'!A:A, A82, 'Hoja 33'!B:B) -> #N/A | F82: Human Grade | G82: ACCESORIO | H82: 6.95 | I82: =(B82/H82)-1 -> 0.72661871 | J82: =(B82-H82)/2 -> 2.525 | L82: =(O82*38) -> 0.95 | M82: =L82+250 -> 250.95 | N82: =M82*1.065 -> 267.26175 | O82: 0.025 | Q82: =H82*D82 -> 20.85
A83: Frog Green (Blue Base) | B83: 12 | C83: C | D83: 1 | E83: =D83 + SUMIF('Hoja 33'!A:A, A83, 'Hoja 33'!B:B) -> #N/A | F83: Human Grade | G83: ACCESORIO | H83: 7.52 | I83: =(B83/H83)-1 -> 0.59574468 | J83: =(B83-H83)/2 -> 2.24 | L83: =(O83*38) -> 1.52 | M83: =L83+250 -> 251.52 | N83: =M83*1.065 -> 267.8688 | O83: 0.04 | Q83: =H83*D83 -> 7.52
A84: Frog Lake Green (Blue Base) | B84: 12 | C84: C | D84: 1 | E84: =D84 + SUMIF('Hoja 33'!A:A, A84, 'Hoja 33'!B:B) -> #N/A | F84: Human Grade | G84: ACCESORIO | H84: 7.02 | I84: =(B84/H84)-1 -> 0.70940171 | J84: =(B84-H84)/2 -> 2.49 | L84: =(O84*38) -> 1.52 | M84: =L84+250 -> 251.52 | N84: =M84*1.065 -> 267.8688 | O84: 0.04 | Q84: =H84*D84 -> 7.02
A85: Frog Light Yellow (Blue Base) | B85: 12 | C85: C | D85: 2 | E85: =D85 + SUMIF('Hoja 33'!A:A, A85, 'Hoja 33'!B:B) -> #N/A | F85: Human Grade | G85: ACCESORIO | H85: 7.02 | I85: =(B85/H85)-1 -> 0.70940171 | J85: =(B85-H85)/2 -> 2.49 | L85: =(O85*38) -> 1.52 | M85: =L85+250 -> 251.52 | N85: =M85*1.065 -> 267.8688 | O85: 0.04 | Q85: =H85*D85 -> 14.04
A86: Frog - Matrix Green (Blue Base) | B86: 12 | C86: C | D86: 3 | E86: =D86 + SUMIF('Hoja 33'!A:A, A86, 'Hoja 33'!B:B) -> #N/A | F86: Human Grade | G86: ACCESORIO | H86: 8.02 | I86: =(B86/H86)-1 -> 0.49625935 | J86: =(B86-H86)/2 -> 1.99 | L86: =(O86*38) -> 1.52 | M86: =L86+250 -> 251.52 | N86: =M86*1.065 -> 267.8688 | O86: 0.04 | Q86: =H86*D86 -> 24.06
A87: Ghost Amber | B87: 12 | C87: C | D87: 0 | E87: =D87 + SUMIF('Hoja 33'!A:A, A87, 'Hoja 33'!B:B) -> #N/A | F87: Human Grade | G87: ACCESORIO | H87: 6.77 | I87: =(B87/H87)-1 -> 0.77252585 | J87: =(B87-H87)/2 -> 2.615 | L87: =(O87*38) -> 1.52 | M87: =L87+250 -> 251.52 | N87: =M87*1.065 -> 267.8688 | O87: 0.04 | Q87: =H87*D87 -> 0
A88: Ghost - Green | B88: 12 | C88: C | D88: 0 | E88: =D88 + SUMIF('Hoja 33'!A:A, A88, 'Hoja 33'!B:B) -> #N/A | F88: Human Grade | G88: ACCESORIO | H88: 6.77 | I88: =(B88/H88)-1 -> 0.77252585 | J88: =(B88-H88)/2 -> 2.615 | L88: =(O88*38) -> 1.52 | M88: =L88+250 -> 251.52 | N88: =M88*1.065 -> 267.8688 | O88: 0.04 | Q88: =H88*D88 -> 0
A89: Ghost - Lavender | B89: 12 | C89: C | D89: 0 | E89: =D89 + SUMIF('Hoja 33'!A:A, A89, 'Hoja 33'!B:B) -> #N/A | F89: Human Grade | G89: ACCESORIO | H89: 6.77 | I89: =(B89/H89)-1 -> 0.77252585 | J89: =(B89-H89)/2 -> 2.615 | L89: =(O89*38) -> 1.52 | M89: =L89+250 -> 251.52 | N89: =M89*1.065 -> 267.8688 | O89: 0.04 | Q89: =H89*D89 -> 0
... A102: Pig - Milky Pink (Clear Base) | B102: 12 | C102: C | D102: 0 | E102: =D102 + SUMIF('Hoja 33'!A:A, A102, 'Hoja 33'!B:B) -> #N/A | F102: Human Grade | G102: ACCESORIO | H102: 6.27 | I102: =(B102/H102)-1 -> 0.9138756 | J102: =(B102-H102)/2 -> 2.865 | L102: =(O102*38) -> 1.52 | M102: =L102+250 -> 251.52 | N102: =M102*1.065 -> 267.8688 | O102: 0.04 | Q102: =H102*D102 -> 0
A103: Spinner 3 - Blue | B103: 12 | C103: C | D103: 0 | E103: =D103 + SUMIF('Hoja 33'!A:A, A103, 'Hoja 33'!B:B) -> #N/A | F103: Human Grade | G103: ACCESORIO | H103: 6.52 | I103: =(B103/H103)-1 -> 0.8404908 | J103: =(B103-H103)/2 -> 2.74 | L103: =(O103*38) -> #N/A | M103: =L103+250 -> #N/A | N103: =M103*1.065 -> #N/A | O103: #N/A | Q103: =H103*D103 -> 0
A104: Spinner 3 Green | B104: 12 | C104: C | D104: 0 | E104: =D104 + SUMIF('Hoja 33'!A:A, A104, 'Hoja 33'!B:B) -> #N/A | F104: Human Grade | G104: ACCESORIO | H104: 6.52 | I104: =(B104/H104)-1 -> 0.8404908 | J104: =(B104-H104)/2 -> 2.74 | L104: =(O104*38) -> #N/A | M104: =L104+250 -> #N/A | N104: =M104*1.065 -> #N/A | O104: #N/A | Q104: =H104*D104 -> 0
A105: Spinner 3 - Smoke | B105: 12 | C105: C | D105: 0 | E105: =D105 + SUMIF('Hoja 33'!A:A, A105, 'Hoja 33'!B:B) -> #N/A | F105: Human Grade | G105: ACCESORIO | H105: 6.52 | I105: =(B105/H105)-1 -> 0.8404908 | J105: =(B105-H105)/2 -> 2.74 | L105: =(O105*38) -> #N/A | M105: =L105+250 -> #N/A | N105: =M105*1.065 -> #N/A | O105: #N/A | Q105: =H105*D105 -> 0
A106: Spinner 3 - Lake Green | B106: 12 | C106: C | D106: 0 | E106: =D106 + SUMIF('Hoja 33'!A:A, A106, 'Hoja 33'!B:B) -> #N/A | F106: Human Grade | G106: ACCESORIO | H106: 6.52 | I106: =(B106/H106)-1 -> 0.8404908 | J106: =(B106-H106)/2 -> 2.74 | L106: =(O106*38) -> #N/A | M106: =L106+250 -> #N/A | N106: =M106*1.065 -> #N/A | O106: #N/A | Q106: =H106*D106 -> 0
A107: Spinner 3 Matrix Green | B107: 12 | C107: C | D107: 1 | E107: =D107 + SUMIF('Hoja 33'!A:A, A107, 'Hoja 33'!B:B) -> #N/A | F107: Human Grade | G107: ACCESORIO | H107: 6.52 | I107: =(B107/H107)-1 -> 0.8404908 | J107: =(B107-H107)/2 -> 2.74 | L107: =(O107*38) -> 1.52 | M107: =L107+250 -> 251.52 | N107: =M107*1.065 -> 267.8688 | O107: 0.04 | Q107: =H107*D107 -> 6.52
A108: Spinner 3 - Pink | B108: 12 | C108: C | D108: 1 | E108: =D108 + SUMIF('Hoja 33'!A:A, A108, 'Hoja 33'!B:B) -> #N/A | F108: Human Grade | G108: ACCESORIO | H108: 6.52 | I108: =(B108/H108)-1 -> 0.8404908 | J108: =(B108-H108)/2 -> 2.74 | L108: =(O108*38) -> 1.52 | M108: =L108+250 -> 251.52 | N108: =M108*1.065 -> 267.8688 | O108: 0.04 | Q108: =H108*D108 -> 6.52
A109: Spinner 3 Purple | B109: 12 | C109: C | D109: 1 | E109: =D109 + SUMIF('Hoja 33'!A:A, A109, 'Hoja 33'!B:B) -> #N/A | F109: Human Grade | G109: ACCESORIO | H109: 6.52 | I109: =(B109/H109)-1 -> 0.8404908 | J109: =(B109-H109)/2 -> 2.74 | L109: =(O109*38) -> 1.52 | M109: =L109+250 -> 251.52 | N109: =M109*1.065 -> 267.8688 | O109: 0.04 | Q109: =H109*D109 -> 6.52
A110: Turtle - Dark Red (Amber Shell) | B110: 12 | C110: C | D110: 0 | E110: =D110 + SUMIF('Hoja 33'!A:A, A110, 'Hoja 33'!B:B) -> #N/A | F110: Human Grade | G110: ACCESORIO | H110: 7.52 | I110: =(B110/H110)-1 -> 0.59574468 | J110: =(B110-H110)/2 -> 2.24 | L110: =(O110*38) -> 1.52 | M110: =L110+250 -> 251.52 | N110: =M110*1.065 -> 267.8688 | O110: 0.04 | Q110: =H110*D110 -> 0
A111: Turtle - Green (Amber Shell) | B111: 12 | C111: C | D111: 0 | E111: =D111 + SUMIF('Hoja 33'!A:A, A111, 'Hoja 33'!B:B) -> #N/A | F111: Human Grade | G111: ACCESORIO | H111: 7.52 | I111: =(B111/H111)-1 -> 0.59574468 | J111: =(B111-H111)/2 -> 2.24 | L111: =(O111*38) -> 1.52 | M111: =L111+250 -> 251.52 | N111: =M111*1.065 -> 267.8688 | O111: 0.04 | Q111: =H111*D111 -> 0
A112: Turtle Lake Green (Amber Shell) | B112: 12 | C112: C | D112: 1 | E112: =D112 + SUMIF('Hoja 33'!A:A, A112, 'Hoja 33'!B:B) -> #N/A | F112: Human Grade | G112: ACCESORIO | H112: 7.52 | I112: =(B112/H112)-1 -> 0.59574468 | J112: =(B112-H112)/2 -> 2.24 | L112: =(O112*38) -> 1.52 | M112: =L112+250 -> 251.52 | N112: =M112*1.065 -> 267.8688 | O112: 0.04 | Q112: =H112*D112 -> 7.52
...

Sheet Resumen
A1: Cliente | B1: Saldo | E1: TOTAL DEUDA | F1: =SUM(B2:B982) -> 49255.195
A2: TIN UY | B2: =INDIRECT("'" & A2 & "'!I1") -> 10639.221 | J2: H1 | K2: 16999
A3: Facu Pisando | B3: =INDIRECT("'" & A3 & "'!I1") -> 7052.3677 | J3: H7 | K3: 16999
A4: Guille naesa | B4: =INDIRECT("'" & A4 & "'!I1") -> 2912.7268 | J4: H4 | K4: 22999
A5: FACU LP | B5: =INDIRECT("'" & A5 & "'!I1") -> 3477 | J5: A232-7A | K5: 169999
A6: Kanario | B6: =INDIRECT("'" & A6 & "'!I1") -> 2909.6785 | J6: RF-5020 | K6: 24999
A7: LT Grow | B7: =INDIRECT("'" & A7 & "'!I1") -> 1426.8722 | J7: ST-KIT08 | K7: 22999
A8: MARSHAL LEAN | B8: =INDIRECT("'" & A8 & "'!I1") -> 2551.5 | J8: ST-KIT04 | K8: 33999
A9: Alfredo Indajaus | B9: =INDIRECT("'" & A9 & "'!I1") -> 2480 | J9: ST-03 | K9: 6999
A10: vaporever | B10: =INDIRECT("'" & A10 & "'!I1") -> 2952.3634 | J10: ST-ISO45080 | K10: 6499
A11: The pot club | B11: =INDIRECT("'" & A11 & "'!I1") -> 1985 | J11: ST-CABPRO2V | K11: 36999
A12: Alto Vuelo | B12: =INDIRECT("'" & A12 & "'!I1") -> 1501
A13: Pedro | B13: =INDIRECT("'" & A13 & "'!I1") -> 1467.7487
A14: Leloir ONG | B14: =INDIRECT("'" & A14 & "'!I1") -> 1315
A15: Alan | B15: =INDIRECT("'" & A15 & "'!I1") -> 950.23259
A16: Nahu La comarca | B16: =INDIRECT("'" & A16 & "'!I1") -> 733
A17: Lean TEGRIDAD | B17: =INDIRECT("'" & A17 & "'!I1") -> 309.76288
A18: Ale Ong Cordoba | B18: =INDIRECT("'" & A18 & "'!I1") -> 482
A19: Tuki Grow | B19: =INDIRECT("'" & A19 & "'!I1") -> 430
A20: Coco Salta | B20: =INDIRECT("'" & A20 & "'!I1") -> 2083.0266
A21: Agus Honney | B21: =INDIRECT("'" & A21 & "'!I1") -> 68.659953
A22: High up OMG | B22: =INDIRECT("'" & A22 & "'!I1") -> 0
A23: OLD FARMERS | B23: =INDIRECT("'" & A23 & "'!I1") -> 1528.0369
A24: Charly Distri | B24: =INDIRECT("'" & A24 & "'!I1") -> -0.002455

Sheet LISTA Special distro
A1: PRODUCTO | B1: VENTA | C1: DISTRI
A2: {=IF('Stock y price'!A2:A1643="", "", 'Stock y price'!A2:A1643)} -> Peak Pro 3DXL - Onyx | B2: {=IF('Stock y price'!A2:A1643="", "", 'Stock y price'!B2:B1643)} -> 380 | C2: {=IF('Stock y price'!A2:A1643="", "", 'Stock y price'!H2:H1643 + ('Stock y price'!B2:B1643 - 'Stock y price'!H2:H1643) / 2)} -> 348.71589 | D2: =(B2/C2)-1 -> 0.089712331
A3: Peak Pro 3DXL - Pearl | B3: 380 | C3: 348.71588 | D3: =(B3/C3)-1 -> 0.089712331
A4: Peak Pro 3DXL - PLASMA | B4: 380 | C4: 348.71588 | D4: =(B4/C4)-1 -> 0.089712331
A5: Proxy - Haze | B5: 230 | C5: 210.05551 | D5: =(B5/C5)-1 -> 0.094948664
A6: Proxy - Onyx | B6: 230 | C6: 210.05551 | D6: =(B6/C6)-1 -> 0.094948664
A7: Proxy Core PINE | B7: 210 | C7: 191.89015 | D7: =(B7/C7)-1 -> 0.094376103
A8: Proxy Core ONIX | B8: 210 | C8: 191.89015 | D8: =(B8/C8)-1 -> 0.094376103
A9: Proxy Core silicona ONIX | B9: 50 | C9: 41.401 | D9: =(B9/C9)-1 -> 0.2077003
A10: Proxy Core silicona HAZE | B10: 50 | C10: 41.401 | D10: =(B10/C10)-1 -> 0.2077003
A11: Pivot - Storm | B11: 120 | C11: 109.38405 | D11: =(B11/C11)-1 -> 0.097052084
A12: Pivot - Onyx | B12: 120 | C12: 109.38405 | D12: =(B12/C12)-1 -> 0.097052084
A13: Peak - Amarillo | B13: 215 | C13: 200.0698 | D13: =(B13/C13)-1 -> 0.074624956
A14: Peak - Storm | B14: 215 | C14: 200.0698 | D14: =(B14/C14)-1 -> 0.074624956
... A298: MJ Arsenal Proxy Attachments - 14mm 45deg | B298: 20 | C298: 15.00337 | D298: =(B298/C298)-1 -> 0.33303385
A300: FORMULA 420 PYREX-GLASS-METAL-CERAMIC Al 12oz 24ct | B300: 9 | C300: 7.545
A301: Formula 710 Advanced Cleaner C 1_16oz_20ct | B301: 12 | C301: 9.945
A302: Formula 710 Instant Cleaner C2_12oz_24ct | B302: 9 | C302: 7.545
A303: Dab Rite GO | B303: 299 | C303: 267.502
A309: SLURPER MOPS (LIMPIEZA DE BONGS) | B309: 15 | C309: 7.5
A310: GLOB MOPS CLASICO | B310: 12 | C310: 6
A311: GLOB MOPS BENDABLE (SE DOBLA EL CABO DEL MOPS) | B311: 12 | C311: 6
A312: KIT HIBRIDO (incluye pad antideslizante, cap/dabber, controlador, resistencia, cazuela) | B312: 330 | C312: 165
A313: KIT CUARZO (incluye pad antideslizante, cap/dabber, controlador, resistencia, cazuela) | B313: 310 | C313: 155
A314: Deep Dish Quartz Hybrid Nail (cazuela hibrida para 14-18 mm) | B314: 110 | C314: 55
A315: Quartz deep dish (REPUESTO cazuela de cuarzo para banger híbrido x 2 u) | B315: 25 | C315: 12.5
A316: Quartz Ebanger 14 mm Macho | B316: 30 | C316: 23.675
... A363: TERP BALL 3mm x 3 unidades | B363: 10 | C363: 7.5

Sheet Pedidos
A1: fecha | B1: Clientes | C1: Inversion inicial | D1: PEDIDO | E1: GANANCIA | F1: Ganancia real | I1: PAGO | J1: DEBE | K1: OBSERVACIONES
A2: 46065.556 | B2: Alfredo Indajaus | C2: 1 x Peak - Canyon, 1 x Hot knife Negro | D2: 240 | E2: 55.972 | F2: =IFERROR(__xludf.DUMMYFUNCTION("ARRAYFORMULA(IF(B2:B292="""", """",IF(REGEXMATCH(LOWER(B2:B292),""tin uy|charly distri|agus honney""),E2:E292/2, E2:E292)))"),55.97200000000001) -> 55.972 | I2: 240
A3: 46065.559 | B3: Leloir ong | C3: 2 x Pivot - Onyx, 2 x Pivot Pine, 1 x Proxy - Haze, 1 x Peak - Canyon, 1 x Peak Pro 3DXL - Pearl, 1 x Peak Pro 3DXL Chamber - Black, 1 x Pivot 3D Chamber 2-Pack - Onyx | D3: 1315 | E3: 326.428 | F3: =IFERROR(__xludf.DUMMYFUNCTION("""COMPUTED_VALUE"""),326.42800000000005) -> 326.428 | I3: 1315
A4: 46065.566 | B4: tin uy | C4: 5 x Pivot Pine, 6 x Pivot - Onyx, 2 x Peak - Pine, 1 x Peak - Canyon, 1 x Peak - Onyx, 2 x Peak Pro 3DXL - Onyx, 1 x Peak Pro 3DXL - Pearl, 2 x Proxy - Onyx, 2 x Proxy - Haze, 3 x Peak Pro 3DXL Chamber - Black, 3 x Peak 3D Chamber - Onyx, 7 x Adaptador Peak Pro Link, 2 x Hot knife Pearl, 1 x Hot knife Negro | D4: 5185 | E4: 1260.006 | F4: =IFERROR(__xludf.DUMMYFUNCTION("""COMPUTED_VALUE"""),630.0029999999999) -> 630.003
A5: 46065.572 | B5: flavio VIERCOLES | C5: 1 x Peak Pro 3DXL - Pearl, 1 x Hot knife Pearl | D5: 400 | E5: 80.602 | F5: =IFERROR(__xludf.DUMMYFUNCTION("""COMPUTED_VALUE"""),80.602) -> 80.602 | I5: 100 | J5: 300 dls
A6: 46065.573 | B6: COCO Salta 420 | C6: 2 x Adaptador Peak Pro Link, 1 x Proxy - Haze | D6: 440 | E6: 105.168 | F6: =IFERROR(__xludf.DUMMYFUNCTION("""COMPUTED_VALUE"""),105.16799999999998) -> 105.168 | J6: 440 dls
A7: 46065.576 | B7: Dealer del OESTE NQN Franco | C7: 1 x Peak Pro 3DXL - Onyx, 1 x Peak - Canyon, 1 x Proxy - Haze, 1 x Proxy - Onyx, 2 x Peak Pro 3DXL Chamber - Black, 2 x Adaptador Peak Pro Link, 1 x Peak Pro 3DXL - Pearl | D7: 1690 | E7: 387.472 | F7: =IFERROR(__xludf.DUMMYFUNCTION("""COMPUTED_VALUE"""),387.472) -> 387.472 | I7: 350
A8: 46065.586 | B8: CHARLY DISTRI | C8: 5 x Pivot Pine, 5 x Pivot - Onyx, 4 x Pivot Glass Adapter with 3D Chamber - Onyx, 5 x Hot knife Pearl, 5 x Hot knife Negro, 3 x Peak - Pine, 2 x Peak - Canyon, 2 x Peak - Onyx, 4 x Peak 3D Chamber - Onyx, 2 x Proxy - Onyx, 2 x Proxy - Haze, 2 x Proxy 3D Chamber - Onyx, 2 x Peak Pro 3DXL - Onyx, 2 x Peak Pro 3DXL - Pearl, 4 x Peak Pro 3DXL Chamber clasico, 4 x Peak Pro 3DXL Chamber - Black, 2 x Peak Pro Glass 2.0, 1 x Adaptador Peak Pro Link | D8: 6534 | E8: 1600.578 | F8: =IFERROR(__xludf.DUMMYFUNCTION("""COMPUTED_VALUE"""),800.289) -> 800.289 | J8: 6534 | K8: es mas por cosas que tenia yo | L8: 7400 aprox
A9: 46065.589 | B9: BIG FACU COSTA ATLANTICA | C9: 1 x Pivot Pine, 1 x Pivot - Onyx, 1 x Pivot 3D Chamber 2-Pack - Onyx, 1 x Pivot Glass Adapter with 3D Chamber - Onyx, 1 x Hot knife Negro, 1 x Hot knife Pearl, 1 x Peak - Canyon, 1 x Peak - Pine, 1 x Proxy - Haze, 2 x Proxy - Onyx, 1 x Peak Pro 3DXL - Pearl, 1 x Peak Pro 3DXL Chamber - Black, 2 x Adaptador Peak Pro Link | D9: 2085 | E9: 500.678 | F9: =IFERROR(__xludf.DUMMYFUNCTION("""COMPUTED_VALUE"""),500.678) -> 500.678 | I9: 800 | J9: 2231 dls
A10: 46065.598 | B10: Planto Luego existo | C10: 2 x Pivot Pine, 2 x Pivot - Onyx, 2 x Pivot 3D Chamber 2-Pack - Onyx, 1 x Hot knife Negro, 1 x Hot knife Pearl, 2 x Peak - Pine, 1 x Peak - Onyx, 1 x Peak - Canyon, 1 x Peak Pro 3DXL - Onyx, 1 x Peak Pro 3DXL - Pearl, 1 x Proxy - Haze, 2 x Proxy - Onyx, 4 x Proxy 3D Chamber - Onyx, 2 x Adaptador Peak Pro Link, 2 x Peak Pro 3DXL Chamber - Black | D10: 3258 | E10: 784.976 | F10: =IFERROR(__xludf.DUMMYFUNCTION("""COMPUTED_VALUE"""),784.9759999999999) -> 784.976 | I10: 3258 | K10: 46094
A11: 46065.605 | B11: High up OMG | C11: 30 x Plus Battery - Pearl, 2 x Proxy - Onyx, 4 x Proxy 3D Chamber - Onyx, 2 x Peak Pro 3DXL - Pearl, 1 x Proxy - Haze, 2 x Pivot Pine, 2 x Hot knife Negro, 2 x Hot knife Pearl, 3 x Peak - Onyx, 1 x Peak - Canyon, 1 x Peak - Pine | D11: 3868 | E11: 711.368 | F11: =IFERROR(__xludf.DUMMYFUNCTION("""COMPUTED_VALUE"""),711.368) -> 711.368 | I11: 4384 | K11: cobrado 26/2/2026 x luke entrego al colo 2-3-26
A12: 46065.606 | B12: High up OMG | C12: 2 x Peak Pro 3DXL Chamber clasico | D12: 160 | E12: 53.616 | F12: =IFERROR(__xludf.DUMMYFUNCTION("""COMPUTED_VALUE"""),53.616) -> 53.616 | J12: -
A13: 46065.612 | B13: High up OMG | C13: 1 x Peak - Canyon | D13: 190 | E13: 45.312 | F13: =IFERROR(__xludf.DUMMYFUNCTION("""COMPUTED_VALUE"""),45.31200000000001) -> 45.312 | J13: -
A14: 46066.452 | B14: Facu LP | C14: 1 x Peak Pro 3DXL - Onyx, 1 x Peak Pro 3DXL - Pearl | D14: 700 | E14: 139.884 | F14: =IFERROR(__xludf.DUMMYFUNCTION("""COMPUTED_VALUE"""),139.88400000000001) -> 139.884 | J14: 700 dls
A15: 46066.475 | B15: Astro GRow LA PLATA | C15: 2 x Pivot - Onyx, 1 x Pivot Pine, 1 x Peak - Onyx, 3 x Peak Atomizer, 1 x Proxy - Onyx, 1 x Proxy - Haze, 1 x Peak Pro 3DXL Chamber - Black | D15: 1084 | E15: 268.388 | F15: =IFERROR(__xludf.DUMMYFUNCTION("""COMPUTED_VALUE"""),268.38800000000003) -> 268.388 | I15: 1084
A16: 46066.487 | B16: Facu LP | C16: 1 x Peak Pro 3D Chamber | D16: 70 | E16: 20.82 | F16: =IFERROR(__xludf.DUMMYFUNCTION("""COMPUTED_VALUE"""),20.82) -> 20.82 | I16: 70
A17: 46066.488 | B17: tin uy | C17: 2 x Pivot Pine, 1 x Pivot - Onyx, 1 x Hot knife Negro | D17: 380 | E17: 101.44 | F17: =IFERROR(__xludf.DUMMYFUNCTION("""COMPUTED_VALUE"""),50.720000000000006) -> 50.72
A18: 46066.489 | B18: tin uy | C18: 2 x Peak Pro 3D Chamber | D18: 140 | E18: 41.64 | F18: =IFERROR(__xludf.DUMMYFUNCTION("""COMPUTED_VALUE"""),20.82) -> 20.82
A19: 46066.691 | B19: MARSHAL LEAN | C19: 1 x Peak Pro 3DXL - Pearl, 1 x Pivot Pine, 1 x Pivot - Onyx, 2 x Proxy - Onyx, 2 x Proxy - Haze, 1 x Peak 3D Chamber - Onyx, 2 x Peak Pro Glass 2.0, 3 x Peak Pro 3DXL Chamber - Black, 1 x Hot knife Negro | D19: 1855 | E19: 440.9 | F19: =IFERROR(__xludf.DUMMYFUNCTION("""COMPUTED_VALUE"""),440.9) -> 440.9 | J19: 1855
A20: 46066.856 | B20: Jamrock | C20: 1 x Pivot Pine, 1 x Peak - Pine, 1 x Peak Pro Glass 2.0 | D20: 375 | E20: 92.626 | F20: =IFERROR(__xludf.DUMMYFUNCTION("""COMPUTED_VALUE"""),92.62600000000002) -> 92.626 | I20: 375
A21: 46066.875 | B21: El club de la alegría | C21: 1 x Pivot - Onyx | D21: 110 | E21: 30.26 | F21: =IFERROR(__xludf.DUMMYFUNCTION("""COMPUTED_VALUE"""),30.260000000000005) -> 30.26 | I21: 110
A22: 46071.321 | B22: tin uy | C22: 3 x Proxy - Onyx, 2 x Pivot 3D Chamber 2-Pack - Onyx | D22: 710 | E22: 170.144 | F22: =IFERROR(__xludf.DUMMYFUNCTION("""COMPUTED_VALUE"""),85.07199999999999) -> 85.072
A23: 46071.328 | B23: tin uy | C23: 1 x Pivot Pine | D23: 110 | E23: 30.26 | F23: =IFERROR(__xludf.DUMMYFUNCTION("""COMPUTED_VALUE"""),15.130000000000003) -> 15.13
A24: 46071.362 | B24: tin uy | C24: 1 x Pivot - Onyx | D24: 110 | E24: 30.26 | F24: =IFERROR(__xludf.DUMMYFUNCTION("""COMPUTED_VALUE"""),15.130000000000003) -> 15.13
A25: 46072.992 | B25: tin uy | C25: 1 x Peak Pro Glass 2.0 | D25: 75 | E25: 17.054 | F25: =IFERROR(__xludf.DUMMYFUNCTION("""COMPUTED_VALUE"""),8.527000000000001) -> 8.527
A26: 46073.357 | B26: Agus HONNEY | C26: 1 x Peak - Pine, 2 x GLOB MOPS CLASICO | D26: 214 | E26: 69.312 | F26: =IFERROR(__xludf.DUMMYFUNCTION("""COMPUTED_VALUE"""),34.656000000000006) -> 34.656 | I26: 214
A27: 46073 | B27: tin uy | C27: DEUDA ANTERIOR | D27: 154 | F27: =IFERROR(__xludf.DUMMYFUNCTION("""COMPUTED_VALUE"""),0.0) -> 0
A28: 46073.563 | B28: Facu LP | C28: 1 x Pivot Pine, 1 x Pivot 3D Chamber 2-Pack - Onyx, 1 x Peak Pro 3DXL Chamber clasico, 1 x Hot knife Pearl | D28: 295 | E28: 87.562 | F28: =IFERROR(__xludf.DUMMYFUNCTION("""COMPUTED_VALUE"""),87.56200000000001) -> 87.562 | J28: 295
A29: 46076.37 | B29: Tin UY | C29: 2 x PAPEL REYNOLS, 5 x GLOB MOPS CLASICO, 1 x Peak - Pine, 1 x Proxy - Haze, 1 x PUFFCO TRAVEL CASE ROJO, 1 x Joystick cap Peak New, 1 x Hot knife Negro, 1 x Hot knife Pearl | D29: 680 | E29: 257.604 | F29: =IFERROR(__xludf.DUMMYFUNCTION("""COMPUTED_VALUE"""),128.802) -> 128.802
A30: 46077.388 | B30: Jamrock | C30: 1 x Adaptador Peak Pro Link | D30: 120 | E30: 30.838 | F30: =IFERROR(__xludf.DUMMYFUNCTION("""COMPUTED_VALUE"""),30.837999999999994) -> 30.838 | I30: 120
A31: 46077.41 | B31: Tin UY | C31: 6 x Adaptador Peak Pro Link | D31: 720 | E31: 185.028 | F31: =IFERROR(__xludf.DUMMYFUNCTION("""COMPUTED_VALUE"""),92.51399999999998) -> 92.514
A32: 46077.424 | B32: FACU LP | C32: 1 x Proxy - Haze, 1 x Proxy - Onyx, 1 x Pivot - Onyx, 3 x Peak - Onyx, 1 x Peak - Canyon, 6 x Peak Pro 3DXL Chamber - Black | D32: 1750 | E32: 459.34 | F32: =IFERROR(__xludf.DUMMYFUNCTION("""COMPUTED_VALUE"""),459.34000000000003) -> 459.34 | J32: 1750
B33: FACU LP | C33: Deuda ANTERIOR | D33: 725
A34: 46077.647 | B34: MARSHAL LEAN | C34: 5 x Adaptador Peak Pro Link, 3 x MALLAS PARA BUBBLE HASH 20 LITROS PACK x 8 unidades | D34: 1410 | E34: 291.35 | F34: =IFERROR(__xludf.DUMMYFUNCTION("""COMPUTED_VALUE"""),291.34999999999997) -> 291.35 | J34: 1410
A35: 46078.006 | B35: Agus HONNEY | C35: 15 x ROSIN BAGS PACK X 25 UNIDADES ( 6 CM X 11 CM) MICRAJE 25 | D35: 300 | E35: 59.61 | F35: =IFERROR(__xludf.DUMMYFUNCTION("""COMPUTED_VALUE"""),29.805) -> 29.805 | I35: 300
A36: 46080.706 | B36: Guille UY | C36: 1 x Pivot - Onyx, 2 x Pivot Pine, 1 x Hot knife Pearl, 1 x Hot knife Negro, 1 x Peak - Canyon, 1 x Proxy - Onyx, 1 x Peak Pro 3DXL - Onyx, 1 x Peak Pro 3DXL Chamber - Black, 2 x Adaptador Peak Pro Link, 1 x ROSIN BAGS PACK X 20 UNIDADES ( 5CM X 10 CM) MICRAJE 25 | D36: 1507 | E36: 364.304 | F36: =IFERROR(__xludf.DUMMYFUNCTION("""COMPUTED_VALUE"""),364.304) -> 364.304 | I36: 1507
A37: 46080.707 | B37: Agus HONNEY | C37: 1 x Adaptador Peak Pro Link | D37: 120 | E37: 30.838 | F37: =IFERROR(__xludf.DUMMYFUNCTION("""COMPUTED_VALUE"""),15.418999999999997) -> 15.419 | I37: 120
A38: 46080.817 | B38: leloir ong | C38: 1 x Pivot Pine, 2 x Pivot - Onyx, 1 x Adaptador Peak Pro Link | D38: 450 | E38: 121.618 | F38: =IFERROR(__xludf.DUMMYFUNCTION("""COMPUTED_VALUE"""),121.61800000000001) -> 121.618 | I38: 450
A39: 46080.844 | B39: Nahu La Comarca | C39: 2 x Pivot - Onyx, 2 x Pivot Pine, 2 x Hot knife Negro, 1 x Peak - Pine, 1 x Peak - Onyx, 1 x Peak Pro 3DXL - Onyx | D39: 1270 | E39: 302.926 | F39: =IFERROR(__xludf.DUMMYFUNCTION("""COMPUTED_VALUE"""),302.92600000000004) -> 302.926 | J39: 1270
A40: 46080.847 | B40: Nahu La Comarca | C40: 1 x Peak Pro 3D Chamber, 1 x Peak Pro Glass 2.0, 1 x Pivot Mouthpiece 2-Pack , 1 x GLOB MOPS CLASICO | D40: 172 | E40: 53.594 | F40: =IFERROR(__xludf.DUMMYFUNCTION("""COMPUTED_VALUE"""),53.594) -> 53.594 | J40: 172
A41: 46081.644 | B41: MARSHAL LEAN | C41: 2 x Proxy Bub - Haze, 1 x Proxy Bub - Onyx, 1 x Pivot Pine, 1 x Hot knife Pearl | D41: 430 | E41: 112.23 | F41: =IFERROR(__xludf.DUMMYFUNCTION("""COMPUTED_VALUE"""),112.22999999999999) -> 112.23 | J41: 430
A42: 46083.52 | B42: Agus HONNEY | C42: 2 x Plus Battery - Pearl, 4 x Plus Supercharger | D42: 102 | E42: 16.776 | F42: =IFERROR(__xludf.DUMMYFUNCTION("""COMPUTED_VALUE"""),8.388000000000003) -> 8.388 | I42: 102
A43: 46083.912 | B43: Kanario | C43: 3 x GLOB MOPS CLASICO, 2 x Clear Bucket Bangers - Standard 90-10mm, 2 x Terp Blender Bangers - Full Weld 90-10mm, 2 x Terp Blender Bangers - Full Weld 90-14mm, 2 x MJ Arsenal Puffco Pivot Tops - Sidecar - Clear, 1 x MJ Arsenal Puffco Pivot Tops - Egg- Clear, 1 x BigFun! Puffco Pivot Tops - Drei, 1 x BigFun! Puffco Pivot Tops - LIL' Frosty, 1 x BigFun! Puffco Pivot Tops - LIL' X, 2 x MJ Arsenal Puffco Peak Tops - Quadra, 1 x Peak Pro 3DXL Joystick Caps - Black Nebula, 1 x Peak Pro 3DXL Joystick Caps Blue Lagoon, 1 x Peak Pro 3DXL Joystick Caps - Clear, 1 x Peak Pro 3DXL Joystick Caps - Eclipse, 1 x Ursa Mini Dab Rig - Clear, 1 x Royale Mini Dab Rig - Iridescent, 1 x Infinity Mini Dab Rig - Clear, 1 x Mushroom 2 - Milky Blue, 1 x Mushroom - Purple (Green Base), 1 x Ghost Amber, 1 x Frog Green (Blue Base), 1 x Chili Pepper Red (Yellow Hat), 1 x Turtle - Green (Amber Shell), 1 x Peak Pro 3DXL - Onyx, 1 x Peak Pro 3DXL - Pearl, 1 x Pivot Pine, 1 x Pivot - Onyx, 1 x Peak - Pine, 1 x Peak - Canyon, 1 x Peak - Onyx, 1 x Proxy - Haze, 1 x Proxy - Onyx, 1 x Proxy Bub - Onyx, 2 x Hot knife Pearl, 2 x Hot knife Negro, 4 x Adaptador Peak Pro Link, 1 x Peak Pro 3DXL Chamber - Black, 2 x Pivot Glass Adapter with 3D Chamber - Onyx, 1 x PUFFCO TRAVEL CASE ROJO, 1 x PUFFCO TRAVEL CASE PLATEADO, 1 x Pivot 3D Chamber 2-Pack - Onyx, 3 x PAPEL REYNOLS, 2 x Proxy 3D Chamber - Onyx, 2 x Chamber Plus - Pearl, 10 x ROSIN BAGS PACK X 20 UNIDADES ( 5CM X 10 CM) MICRAJE 25, 4 x ROSIN BAGS PACK X 20UNIDADES ( 3,8 CM X 10 CM) 120 micras, 1 x ROSIN BAGS PACK X 20UNIDADES ( 6 CM X 11 CM) 90 micras | D43: 4257 | E43: 1251.718 | F43: =IFERROR(__xludf.DUMMYFUNCTION("""COMPUTED_VALUE"""),1251.718) -> 1251.718 | J43: 4257
A44: 46084.52 | B44: LELOIR ong | C44: 1 x Pivot Tops Display - V1 (18) | D44: 30 | E44: 13.1 | F44: =IFERROR(__xludf.DUMMYFUNCTION("""COMPUTED_VALUE"""),13.100000000000001) -> 13.1 | I44: 30
A45: 46085.382 | B45: Ale ONG Cordoba | C45: 4 x ROSIN BAGS PACK X 25 UNIDADES ( 6 CM X 11 CM) MICRAJE 25, 1 x Pivot Pine, 1 x Pivot - Onyx, 3 x Hot knife Negro, 1 x Hot knife Pearl, 2 x Proxy - Onyx, 2 x Proxy wizard - marron, 1 x Bloopcycler Dab Rig - Clear, 1 x Ghost Smoke, 1 x Ghost - Lavender, 1 x Chili Pepper - Orange (Milky Yellow Hat), 1 x Frog Light Yellow (Blue Base), 1 x Mushroom 2 - Yellow, 1 x Turtle - Dark Red (Amber Shell), 1 x Terp Blender Bangers - Full Weld 90-10mm, 1 x Quartz Ebanger 14 mm Macho, 1 x GLOB MOPS CLASICO | D45: 1309 | E45: 346.63 | F45: =IFERROR(__xludf.DUMMYFUNCTION("""COMPUTED_VALUE"""),346.63) -> 346.63 | I45: 1309
A46: 46085.388 | B46: Ale ONG Cordoba | C46: 1 x Proxy 3D Chamber - Onyx | D46: 37 | E46: 9.012 | F46: =IFERROR(__xludf.DUMMYFUNCTION("""COMPUTED_VALUE"""),9.012) -> 9.012 | I46: 37
A47: 46085.853 | B47: Nahu La Comarca | C47: 1 x Ursa Mini Dab Rig - Clear, 1 x Royale Mini Dab Rig - Iridescent, 1 x Apollo Mini Dab Rig - Iridescent, 1 x Apollo Mini Dab Rig - Clear, 1 x Titan Mini Dab Rig - Clear, 1 x MJ Arsenal Puffco Peak Tops - Quadra, 1 x 8.5" Swiss Incycler - Iridescent, 1 x Terp Blender Bangers - Full Weld 90-10mm, 1 x Terp Blender Bangers - Full Weld 90-14mm, 1 x Clear Bucket Bangers - Standard 90-10mm XL, 1 x Clear Bucket Bangers - Standard 90-10mm, 1 x Peak Pro 3DXL Joystick Caps - Clear, 1 x Peak Pro 3DXL Joystick Caps - Firestone Red, 1 x Peak Pro 3DXL Joystick Caps Glow in the Dark, 1 x Adaptador Peak Pro Link | D47: 628 | E47: 193.428 | F47: =IFERROR(__xludf.DUMMYFUNCTION("""COMPUTED_VALUE"""),193.42799999999997) -> 193.428 | J47: 628 | K47: A CUENTA USD 500 EN EFT A LUCAS | M47: ENTREGADO AL COLO 12-03-2026
A48: 46085.86 | B48: High up OMG | C48: 4 x Peak Pro 3DXL - Onyx, 2 x Peak Pro 3DXL - Pearl, 1 x Peak Pro 3DXL Chamber - Black, 2 x Peak Pro 3DXL Chamber clasico, 3 x Hot knife Negro, 2 x Pivot - Onyx, 1 x Adaptador Peak Pro Link, 6 x Pivot Tops Display - V1 (18) | D48: 3010 | E48: 702.014 | F48: =IFERROR(__xludf.DUMMYFUNCTION("""COMPUTED_VALUE"""),702.014) -> 702.014 | J48: 3010
A49: 46086.467 | B49: Jona Pura Vibra Chivilicoy | C49: 1 x Peak - Pine, 1 x Peak - Canyon, 1 x Hot knife Negro, 1 x Hot knife Pearl, 1 x Pivot Pine, 1 x Pivot - Onyx | D49: 700 | E49: 172.464 | F49: =IFERROR(__xludf.DUMMYFUNCTION("""COMPUTED_VALUE"""),172.464) -> 172.464 | I49: 700 | K49: PAGO EN EFT A LUCAS $960,000 5/3/2026 | L49: paso por casa | M49: ENTREGADO AL COLO 12-03-2026
A50: 46086.479 | B50: Tin Uy | C50: 1 x Pig - Milky Pink (Clear Base), 2 x Pivot - Onyx, 2 x Pivot Pine, 1 x Proxy 3D Chamber - Onyx, 1 x Proxy - Onyx, 1 x Proxy - Haze, 1 x Pivot 3D Chamber 2-Pack - Onyx | D50: 944 | E50: 242.6 | F50: =IFERROR(__xludf.DUMMYFUNCTION("""COMPUTED_VALUE"""),121.30000000000001) -> 121.3
A51: 46086.502 | B51: Tin UY | C51: 1 x Spinner 3 - Green | D51: 12 | E51: 5.48 | F51: =IFERROR(__xludf.DUMMYFUNCTION("""COMPUTED_VALUE"""),2.74) -> 2.74
A52: 46086.536 | B52: Brian Quilmes | C52: 1 x Peak Pro 3DXL - Pearl, 1 x Teddy Peak Top Teddy Peak Top, 1 x Apollo Mini Dab Rig - Iridescent, 1 x Atlas Mini Dab Rig - Iridescent, 1 x Mini Jig Mini Dab Rig Iridescent, 1 x MJ Arsenal Puffco Pivot Tops - Sidecar - Clear, 1 x Peak Pro 3DXL Chamber - Black, 1 x Peak Pro 3DXL Chamber clasico, 1 x BigFun! Puffco Pivot Tops - Drei, 1 x BigFun! Puffco Pivot Tops - LIL' Frosty, 1 x BigFun! Puffco Pivot Tops - LIL' X, 5 x Pivot Tops Display - V1 (18), 1 x Peak Pro 3DXL Joystick Caps Blue Lagoon, 1 x Peak Pro 3DXL Joystick Caps - Black Nebula, 1 x Peak Pro 3DXL Joystick Caps - Eclipse, 1 x Chili Pepper Green (Red Hat), 1 x Frog Lake Green (Blue Base), 1 x Ghost - Green, 1 x Mushroom Blue (Green Base), 1 x Mushroom 2 - Green, 1 x Spinner 3 - Green, 1 x Turtle Lake Green (Amber Shell), 1 x MJ Arsenal Puffco Peak Tops - Quadra, 1 x Terp Blender Bangers - Full Weld 90-14mm | D52: 1240 | E52: 391.246 | F52: =IFERROR(__xludf.DUMMYFUNCTION("""COMPUTED_VALUE"""),391.2460000000001) -> 391.246 | I52: 1240 | K52: PAGO EN EFT USD A LUCAS 5/3/2026 | L52: entrego y retiro nachito | M52: ENTREGADO AL COLO 12-03-2026
A53: 46086.8 | B53: Alan | C53: 1 x Proxy - Haze, 1 x Teddy Peak Top Teddy Peak Top, 1 x MJ Arsenal Puffco Peak Tops - Quadra, 1 x Love Bug Pivot Top - Love Bug Pivot Top, 1 x Joystick cap Peak New | D53: 386 | E53: 106.492 | F53: =IFERROR(__xludf.DUMMYFUNCTION("""COMPUTED_VALUE"""),106.49199999999999) -> 106.492 | I53: 386
A54: 46087.365 | B54: Alfredo Indajaus | C54: 1 x Peak Pro 3DXL - Onyx, 1 x Proxy - Haze, 1 x Proxy Bub - Haze, 1 x Peak - Canyon, 1 x Peak - Onyx, 1 x Hot knife Pearl, 1 x Pivot Pine | D54: 1180 | E54: 268.748 | F54: =IFERROR(__xludf.DUMMYFUNCTION("""COMPUTED_VALUE"""),268.74800000000005) -> 268.748 | J54: 1180 | K54: A CUENTA USD 500 EN EFT A LUCAS
A55: 46088.94 | B55: Guille Naesa | C55: 1 x Pivot - Onyx, 1 x Peak - Onyx, 1 x Hot knife Negro | D55: 350 | E55: 86.232 | F55: =IFERROR(__xludf.DUMMYFUNCTION("""COMPUTED_VALUE"""),86.23200000000001) -> 86.232
A56: 46091.548 | B56: Tin UY | C56: 20 x 20 GAL ZB, 50 x Pressing Screen (5 pack), 4 x 20-8 ALL MESH, 30 x 5 Gallon Zipper Bag, 30 x 5 GAL 8 B10 BAG KIT (ALL MESH) | D56: 5940 | E56: 1513.8233 | F56: =IFERROR(__xludf.DUMMYFUNCTION("""COMPUTED_VALUE"""),756.9116540649849) -> 756.91165 | K56: A CUENTA USD 1000 EN EFT A LUCAS | M56: ENTREGADO AL COLO 12-03-2026
A57: 46091.553 | B57: Polaco | C57: 1 x Proxy - Onyx, 1 x Peak Pro 3DXL Chamber - Black, 1 x PUFFCO TRAVEL CASE ROJO, 2 x Iso Wipes × 400 | D57: 368 | E57: 137.5409 | F57: =IFERROR(__xludf.DUMMYFUNCTION("""COMPUTED_VALUE"""),137.54089887721995) -> 137.5409 | K57: pago en eft usd 500 los dos pedidos | L57: entrego y retiro nachito | M57: ENTREGADO AL COLO 12-03-2026
A58: 46091.555 | B58: Tin UY | C58: 5 x Iso Wipes × 400 | D58: 70 | E58: 18.102247 | F58: =IFERROR(__xludf.DUMMYFUNCTION("""COMPUTED_VALUE"""),9.051123596524944) -> 9.0511236
A59: 46091.557 | B59: Polaco | C59: 1 x Adaptador Peak Pro Link | D59: 120 | E59: 30.838 | F59: =IFERROR(__xludf.DUMMYFUNCTION("""COMPUTED_VALUE"""),30.837999999999994) -> 30.838 | L59: entrego y retiro nachito | M59: ENTREGADO AL COLO 12-03-2026
A60: 46092.635 | B60: Facu Pisando | C60: 1 x Peak Pro 3DXL - Onyx, 2 x Peak Pro 3DXL - Pearl, 2 x Proxy - Haze, 1 x Peak - Canyon, 1 x Peak - Pine, 3 x Adaptador Peak Pro Link, 2 x Pivot Pine, 2 x Pivot - Onyx, 2 x Peak Pro 3DXL Chamber clasico, 3 x Peak Pro 3DXL Chamber - Black, 2 x Hot knife Negro, 2 x Hot knife Pearl, 1 x Pivot Glass Adapter with 3D Chamber - Onyx, 2 x Pivot 3D Chamber 2-Pack - Onyx, 1 x PUFFCO TRAVEL CASE ROJO, 1 x Coil Caddy Kit with Terp Slurper Set × 1 Green / 14mm, 1 x Spinner 3 Matrix Green, 1 x Spinner 3 - Pink, 1 x Spinner 3 Purple, 2 x Pivot Tops Display - V1 (18), 1 x Infinity Mini Dab Rig - Clear, 1 x Apollo Mini Dab Rig - Pink, 1 x Peak Pro 3DXL Joystick Caps - Firestone Red, 1 x Peak Pro 3DXL Joystick Caps Glow in the Dark, 2 x Peak Pro 3DXL Joystick Caps - Orange, 2 x Peak Pro 3DXL Joystick Caps - Pink UV, 2 x Peak Pro 3DXL Joystick Caps - Slime, 2 x Peak Pro 3DXL Joystick Caps - Sunrise, 2 x Peak Pro TRAVEL GLASS, 2 x Iso Wipes × 400 | D60: 4334 | E60: 1157.9036 | F60: =IFERROR(__xludf.DUMMYFUNCTION("""COMPUTED_VALUE"""),1157.9036180007686) -> 1157.9036
A61: 46093 | B61: CHARLY DISTRI | C61: DEUDA ANTERIOR | D61: 890 | E61: 205.38 | F61: =IFERROR(__xludf.DUMMYFUNCTION("""COMPUTED_VALUE"""),102.69) -> 102.69
A62: 46093.99 | B62: Astro GRow LA PLATA | C62: 1 x Pivot Pine, 1 x Pivot - Onyx, 1 x Adaptador Peak Pro Link, 1 x Atlas Mini Dab Rig - Iridescent, 1 x Peak - Pine, 1 x Peak - Onyx, 2 x Terp Blender Bangers - Full Weld 90-14mm, 1 x Terp Blender Bangers - Full Weld 90-10mm, 1 x Clear Bucket Bangers - Standard 90-10mm XL, 1 x Clear Bucket Bangers - Standard 90-10mm, 1 x Iso Wipes × 400, 2 x Hot knife Pearl, 1 x Peak Pro 3DXL Joystick Caps - Yellow, 1 x Peak Pro 3DXL Joystick Caps - Vintage, 1 x Peak Pro 3DXL Joystick Caps - Transparent Red | D62: 1041 | E62: 284.25845 | F62: =IFERROR(__xludf.DUMMYFUNCTION("""COMPUTED_VALUE"""),284.25844943860994) -> 284.25845 | K62: 13-3 $1,467,781 al colo
A63: 46094.39 | B63: Facu LP | C63: 1 x Apollo Mini Dab Rig - Clear, 1 x Apollo Mini Dab Rig - Pink, 1 x Titan Mini Dab Rig - Clear, 1 x 8.5" Swiss Incycler - Iridescent, 1 x Atlas Mini Dab Rig - Clear, 1 x Teddy Peak Top Teddy Peak Top, 1 x MJ Arsenal Puffco Peak Tops - Quadra, 2 x MJ Arsenal Puffco Pivot Tops - Sidecar - Clear, 2 x MJ Arsenal Puffco Pivot Tops - Egg- Clear, 1 x Royale Mini Dab Rig - Clear, 1 x Mini Jig Mini Dab Rig Iridescent, 1 x Clear Bucket Bangers - Standard 90-10mm XL, 1 x Clear Bucket Bangers - Standard 90-10mm, 1 x Terp Blender Bangers - Full Weld 90-14mm, 1 x BigFun! Puffco Pivot Tops - LIL' X, 1 x Love Bug Pivot Top - Love Bug Pivot Top, 1 x Frog - Matrix Green (Blue Base), 1 x Pig - Milky Pink (Clear Base), 1 x Mushroom Matrix Green (Green Base), 1 x Mushroom 2 Milky Green, 1 x Turtle Matrix Green (Amber Shell), 1 x Chili Pepper Green (Red Hat), 1 x Ghost Smoke, 16 x Iso Wipes × 400, 3 x Pivot Pine, 3 x Pivot - Onyx | D63: 1767 | E63: 534.14319 | F63: =IFERROR(__xludf.DUMMYFUNCTION("""COMPUTED_VALUE"""),534.1431910177598) -> 534.14319
A64: 46094.395 | B64: COCO Salta 420 | C64: 1 x Pivot Pine, 1 x Pivot - Onyx, 1 x Peak - Canyon, 1 x Peak - Pine, 1 x Proxy - Haze, 1 x Peak Pro 3DXL Chamber clasico, 2 x Peak Pro 3DXL Chamber - Black, 1 x Coil Caddy Kit with Terp Slurper Set × 1 Black / 10mm, 1 x Coil Caddy with 40mm Heater Coil × 3, 1 x Coil Caddy with Heater Coil × 3, 1 x Complete MiniNail Kit w/ Quartz Banger × 1 Orange / Flat Tip Dabber and Carb Cap, 1 x Peak Pro Glass 2.0, 10 x ROSIN BAGS PACK X 20 UNIDADES ( 5CM X 10 CM) MICRAJE 25, 1 x BigFun! Puffco Pivot Tops - Drei, 1 x BigFun! Puffco Pivot Tops - LIL' Frosty, 1 x Peak Pro 3DXL Joystick Caps - Transparent Red, 1 x Peak Pro 3DXL Joystick Caps - Vintage, 1 x Peak Pro 3DXL Joystick Caps - Yellow, 4 x Pivot Tops Display - V1 (18), 1 x Spinner 3 Matrix Green, 1 x Spinner 3 - Pink, 2 x Love Bug Pivot Top - Love Bug Pivot Top, 1 x Teddy Peak Top Teddy Peak Top, 3 x Clear Bucket Bangers - Standard 90-10mm, 4 x PAPEL REYNOLS | D64: 2868 | E64: 805.86818 | F64: =IFERROR(__xludf.DUMMYFUNCTION("""COMPUTED_VALUE"""),805.8681751239973) -> 805.86818
A65: 46094.395 | B65: Facu LP | C65: 1 x Proxy - Haze | D65: 200 | E65: 43.492 | F65: =IFERROR(__xludf.DUMMYFUNCTION("""COMPUTED_VALUE"""),43.49199999999999) -> 43.492
A66: 46094.905 | B66: Tin UY | C66: 1 x Peak Atomizer, 1 x Peak 3D Chamber - Onyx | D66: 73 | E66: 17.446 | F66: =IFERROR(__xludf.DUMMYFUNCTION("""COMPUTED_VALUE"""),8.722999999999999) -> 8.723
A67: 46097.502 | B67: CHARLY DISTRI | C67: 6 x Adaptador Peak Pro Link, 2 x Pivot 3D Chamber 2-Pack - Onyx, 2 x MJ Arsenal Puffco Pivot Tops - Egg- Clear, 2 x MJ Arsenal Puffco Pivot Tops - Sidecar - Clear, 1 x Mushroom - Green (Green Base), 1 x Mushroom Light Yellow (Green Base), 1 x Mushroom 2 Milky Purple, 1 x Mushroom Red (Green Base), 1 x Chili Pepper - Orange (Milky Yellow Hat), 1 x Chili Pepper Red (Yellow Hat), 1 x Ghost - Green, 1 x Ghost - Lavender, 1 x Spinner 3 Purple, 5 x Hot knife Pearl, 4 x Peak - Onyx, 3 x Peak - Pine, 3 x Peak - Canyon, 2 x Peak Pro TRAVEL GLASS, 2 x PUFFCO TRAVEL CASE ROJO, 2 x PUFFCO TRAVEL CASE PLATEADO, 10 x Pivot Pine, 10 x Pivot - Onyx, 1 x Proxy wizard - marron, 1 x Proxy Bub viejo - Onyx | D67: 6048 | E67: 1794.994 | F67: =IFERROR(__xludf.DUMMYFUNCTION("""COMPUTED_VALUE"""),897.4970000000001) -> 897.497
A68: 46098.436 | B68: Old Farmers | C68: 2 x Proxy Core, 2 x Proxy Core silicona , 2 x Pivot Mouthpiece 2-Pack pine, 2 x Pivot Mouthpiece 2-Pack moca, 1 x Proxy Bub - Haze, 1 x Proxy Bub - Onyx, 2 x Plus Supercharger, 4 x Chamber Plus - Pearl, 1 x Peak Pro TRAVEL GLASS, 1 x Peak Pro Glass 2.0, 1 x Adaptador Peak Pro Link, 6 x Hot knife NEW NEGRO, 6 x Hot knife NEW PEARL, 2 x Peak Pro 3DXL Chamber clasico, 2 x Peak Pro 3DXL Chamber - Black, 2 x Peak Pro 3D Chamber | D68: 2136 | E68: 557.51972 | F68: =IFERROR(__xludf.DUMMYFUNCTION("""COMPUTED_VALUE"""),557.5197199999999) -> 557.51972 | J68: debe
A69: 46098.516 | B69: Old Farmers | C69: 20 x Iso Wipes × 400 | D69: 280 | E69: 72.408989 | F69: =IFERROR(__xludf.DUMMYFUNCTION("""COMPUTED_VALUE"""),72.40898877219955) -> 72.408989 | J69: debe
A70: 46098.585 | B70: CHARLY DISTRI | C70: 2 x Peak Pro 3DXL - Pearl, 2 x Peak Pro 3DXL - Onyx, 6 x Proxy 3D Chamber - Onyx, 6 x Peak 3D Chamber - Onyx, 6 x Proxy Core, 6 x Proxy Core silicona , 10 x Hot knife NEW NEGRO, 1 x Proxy Bub - Onyx | D70: 3922 | E70: 896.32316 | F70: =IFERROR(__xludf.DUMMYFUNCTION("""COMPUTED_VALUE"""),448.16157999999996) -> 448.16158
A71: 46098.618 | B71: MARSHAL LEAN | C71: 1 x Peak Pro 3DXL - Onyx, 1 x Peak Pro 3DXL - Pearl, 1 x MJ Arsenal Puffco Pivot Tops - Sidecar - Clear, 3 x Hot knife NEW NEGRO, 3 x Hot knife NEW PEARL, 2 x Proxy Core, 2 x Proxy Core silicona , 2 x Peak 3D Chamber - Onyx, 1 x Peak Pro 3DXL Chamber - Black, 6 x Peak Atomizer | D71: 1858 | E71: 427.27772 | F71: =IFERROR(__xludf.DUMMYFUNCTION("""COMPUTED_VALUE"""),427.27771999999993) -> 427.27772
A72: 46099.42 | B72: Facu Pisando | C72: 1 x Peak Pro 3DXL - Onyx, 1 x Peak - Canyon, 2 x Proxy Core, 2 x Proxy Core silicona , 2 x Hot knife NEW NEGRO, 2 x Hot knife NEW PEARL | D72: 1220 | E72: 279.37572 | F72: =IFERROR(__xludf.DUMMYFUNCTION("""COMPUTED_VALUE"""),279.37572) -> 279.37572
A73: 46099.479 | B73: Tuki Grow | C73: 1 x Peak Pro 3DXL - Pearl, 1 x Adaptador Peak Pro Link, 1 x Peak - Pine, 1 x Peak - Canyon, 1 x Peak - Onyx, 2 x Hot knife NEW NEGRO, 2 x Hot knife NEW PEARL, 1 x Proxy - Haze, 2 x Proxy Core, 2 x Proxy Core silicona , 2 x Pivot 3D Chamber 2-Pack - Onyx, 1 x Pivot Glass Adapter with 3D Chamber - Onyx, 3 x Iso Wipes × 400 | D73: 2132 | E73: 514.33707 | F73: =IFERROR(__xludf.DUMMYFUNCTION("""COMPUTED_VALUE"""),514.33706831583) -> 514.33707 | I73: 2135 | K73: transfirio al COLO 18-3 varios comprobantes
A74: 46099.632 | B74: COCO Salta 420 | C74: 3 x Proxy Core, 3 x Proxy Core silicona , 2 x Hot knife NEW NEGRO, 2 x Hot knife NEW PEARL | D74: 920 | E74: 224.86258 | F74: =IFERROR(__xludf.DUMMYFUNCTION("""COMPUTED_VALUE"""),224.86257999999995) -> 224.86258
A75: 46099.656 | B75: The Pot Club | C75: 4 x Pivot Pine, 4 x Pivot - Onyx, 2 x Peak - Onyx, 2 x Pivot Glass Adapter with 3D Chamber - Onyx, 1 x PUFFCO TRAVEL CASE ROJO, 1 x PUFFCO TRAVEL CASE PLATEADO, 2 x Proxy Core, 2 x Proxy Core silicona , 2 x Hot knife NEW NEGRO, 2 x Hot knife NEW PEARL | D75: 2180 | E75: 655.78172 | F75: =IFERROR(__xludf.DUMMYFUNCTION("""COMPUTED_VALUE"""),655.78172) -> 655.78172
A76: 46099.694 | B76: High up OMG | C76: 1 x Peak Pro 3DXL - Onyx, 1 x Peak Pro 3DXL - Pearl, 5 x Proxy Core, 2 x Proxy Core silicona , 4 x Hot knife NEW NEGRO, 4 x Hot knife NEW PEARL, 1 x Peak Pro 3DXL Chamber clasico, 1 x Peak Pro 3DXL Chamber - Black | D76: 2310 | E76: 530.94406 | F76: =IFERROR(__xludf.DUMMYFUNCTION("""COMPUTED_VALUE"""),530.94406) -> 530.94406
A77: 46099.843 | B77: Facu LP | C77: 2 x Proxy Core, 2 x Proxy Core silicona , 2 x Hot knife NEW NEGRO, 2 x Hot knife NEW PEARL | D77: 680 | E77: 164.12172 | F77: =IFERROR(__xludf.DUMMYFUNCTION("""COMPUTED_VALUE"""),164.12171999999998) -> 164.12172
A78: 46100.406 | B78: Tin UY | C78: 1 x Peak Pro 3DXL - Onyx, 2 x Peak Pro 3DXL - Pearl, 2 x Hot knife NEW NEGRO, 2 x Hot knife NEW PEARL, 3 x Proxy Core, 3 x Proxy Core silicona , 1 x Peak - Pine, 2 x Peak - Onyx, 2 x Pivot Pine, 2 x Peak 3D Chamber - Onyx | D78: 2850 | E78: 653.70058 | F78: =IFERROR(__xludf.DUMMYFUNCTION("""COMPUTED_VALUE"""),326.85029) -> 326.85029
A79: 46100.429 | B79: Tin UY | C79: 3 x Proxy 3D Chamber - Onyx | D79: 111 | E79: 27.036 | F79: =IFERROR(__xludf.DUMMYFUNCTION("""COMPUTED_VALUE"""),13.518) -> 13.518
A80: 46100.456 | B80: Iguana MDQ | C80: 1 x Hot knife NEW NEGRO | D80: 50 | E80: 10.66 | F80: =IFERROR(__xludf.DUMMYFUNCTION("""COMPUTED_VALUE"""),10.659999999999997) -> 10.66
A81: 46100.456 | B81: COCO Salta 420 | C81: 1 x Peak Pro Glass 2.0 | D81: 75 | E81: 17.054 | F81: =IFERROR(__xludf.DUMMYFUNCTION("""COMPUTED_VALUE"""),17.054000000000002) -> 17.054
A82: 46100.609 | B82: Cannabis Social Club | C82: 1 x Peak Pro 3DXL - Onyx, 1 x Hot knife NEW PEARL, 2 x Iso Wipes × 400 | D82: 428 | E82: 87.842899 | F82: =IFERROR(__xludf.DUMMYFUNCTION("""COMPUTED_VALUE"""),87.84289887721997) -> 87.842899 | I82: 428 | K82: paga en EFT a nachito 20-3
A83: 46100.817 | B83: Kanario | C83: 1 x Coil Caddy Kit with Terp Slurper Set × 1 Black / 14mm, 1 x Coil Caddy Kit with Terp Slurper Set × 1 Green / 10mm, 2 x Hot knife NEW PEARL, 2 x Hot knife NEW NEGRO, 2 x Proxy Core, 2 x Proxy Core silicona , 10 x Iso Wipes × 400 | D83: 1480 | E83: 367.38765 | F83: =IFERROR(__xludf.DUMMYFUNCTION("""COMPUTED_VALUE"""),367.38765263319715) -> 367.38765
A84: 46100.825 | B84: Tuki Grow | C84: 2 x Pivot Pine, 2 x Pivot - Onyx | D84: 440 | E84: 121.04 | F84: =IFERROR(__xludf.DUMMYFUNCTION("""COMPUTED_VALUE"""),121.04000000000002) -> 121.04 | J84: debe
A85: 46100.825 | B85: Manuja Glass | C85: 1 x Proxy Core | D85: 190 | E85: 43.56078 | F85: =IFERROR(__xludf.DUMMYFUNCTION("""COMPUTED_VALUE"""),43.560779999999994) -> 43.56078 | J85: debe
A86: 46100.919 | B86: Facu Pisando | C86: 1 x Peak - Canyon, 1 x Peak - Onyx | D86: 380 | E86: 90.624 | F86: =IFERROR(__xludf.DUMMYFUNCTION("""COMPUTED_VALUE"""),90.62400000000002) -> 90.624
A87: 46105.509 | B87: Tin UY | C87: 5 x Hot knife NEW NEGRO, 5 x Hot knife NEW PEARL, 1 x Peak - Canyon, 1 x Peak - Pine, 2 x Peak - Onyx, 2 x Proxy Core, 2 x Pivot Pine, 2 x Pivot - Onyx | D87: 2080 | E87: 496.00956 | F87: =IFERROR(__xludf.DUMMYFUNCTION("""COMPUTED_VALUE"""),248.00477999999998) -> 248.00478
A88: 46107.544 | B88: Dedo de Momia | C88: 2 x Proxy Core | D88: 380 | E88: 87.12156 | F88: =IFERROR(__xludf.DUMMYFUNCTION("""COMPUTED_VALUE"""),87.12155999999999) -> 87.12156 | I88: 380 | K88: Transfirio al COLO 26-3 dos comprobantes
A89: 46107.654 | B89: Tin UY | C89: 2 x Proxy Core | D89: 380 | E89: 87.12156 | F89: =IFERROR(__xludf.DUMMYFUNCTION("""COMPUTED_VALUE"""),43.560779999999994) -> 43.56078
A90: 46108.623 | B90: Facu Pisando | C90: 2 x Pivot - Onyx, 1 x Quartz deep dish (REPUESTO cazuela de cuarzo para banger híbrido x 2 u), 1 x Proxy 3D Chamber - Onyx | D90: 282 | E90: 94.532 | F90: =IFERROR(__xludf.DUMMYFUNCTION("""COMPUTED_VALUE"""),94.53200000000001) -> 94.532
A91: 46108.874 | B91: Rasta Ñato | C91: 1 x ROSIN BAGS PACK X 20 UNIDADES ( 5CM X 10 CM) MICRAJE 25, 1 x PAPEL REYNOLS | D91: 43 | E91: 9.714 | F91: =IFERROR(__xludf.DUMMYFUNCTION("""COMPUTED_VALUE"""),9.713999999999999) -> 9.714 | I91: 43 | K91: PAGO EN EFT USD 43 a Lucas 27-3
A92: 46112.638 | B92: Agus HONNEY | C92: 1 x Peak Pro 3DXL - Onyx, 2 x Pivot - Onyx, 2 x ROSIN BAGS PACK X 20 UNIDADES ( 5CM X 10 CM) MICRAJE 25, 1 x PAPEL REYNOLS | D92: 630 | E92: 145.15 | F92: =IFERROR(__xludf.DUMMYFUNCTION("""COMPUTED_VALUE"""),72.57500000000002) -> 72.575 | I92: 630 | K92: 2 transfer al colo
A93: 46112.682 | B93: MARSHAL Lean | C93: 2 x Peak Pro 3DXL Chamber - Black, 2 x Hot knife NEW NEGRO, 2 x Hot knife NEW PEARL, 2 x Proxy Core silicona | D93: 460 | E93: 130.61616 | F93: =IFERROR(__xludf.DUMMYFUNCTION("""COMPUTED_VALUE"""),130.61615999999998) -> 130.61616
A94: 46112.682 | B94: MARSHAL Lean | C94: 1 x Teddy Peak Top Teddy Peak Top | D94: 80 | E94: 17.4 | F94: =IFERROR(__xludf.DUMMYFUNCTION("""COMPUTED_VALUE"""),17.4) -> 17.4
A95: 46112.688 | B95: Vaporever | C95: 1 x Pivot Pine, 1 x Pivot - Onyx | D95: 220 | E95: 60.52 | F95: =IFERROR(__xludf.DUMMYFUNCTION("""COMPUTED_VALUE"""),60.52000000000001) -> 60.52
A96: 46112.694 | B96: Guille UY | C96: 1 x Peak Pro 3DXL - Onyx, 2 x Proxy Core, 2 x Hot knife NEW PEARL, 1 x Hot knife NEW NEGRO, 1 x Adaptador Peak Pro Link, 4 x ROSIN BAGS PACK X 20 UNIDADES ( 5CM X 10 CM) MICRAJE 25, 1 x ROSIN BAGS PACK X 25 UNIDADES ( 6 CM X 11 CM) MICRAJE 25, 1 x Teddy Peak Top Teddy Peak Top, 1 x Peak - Onyx | D96: 1358 | E96: 306.46356 | F96: =IFERROR(__xludf.DUMMYFUNCTION("""COMPUTED_VALUE"""),306.46356) -> 306.46356 | K96: PAGO EN EFT USD 1358 a Lucas 30-3
A97: 46113.338 | B97: Astro Grow La Plata | C97: 2 x Hot knife NEW NEGRO, 2 x Hot knife NEW PEARL, 1 x BigFun! Puffco Pivot Tops - Drei, 2 x Proxy Core silicona , 2 x Proxy Core | D97: 710 | E97: 178.17172 | F97: =IFERROR(__xludf.DUMMYFUNCTION("""COMPUTED_VALUE"""),178.17171999999997) -> 178.17172
A98: 46113.367 | B98: Facu LP | C98: 1 x MJ Arsenal Puffco Peak Tops - Halo, 1 x MJ Arsenal Puffco Peak Tops - Tempest, 1 x MJ Arsenal Puffco Peak Tops - Fabcycler, 1 x Pivot Tops Display - V1 (18), 1 x Pivot Tops Display - V2 (18), 1 x BigFun! Puffco Pivot Tops - Drei, 1 x MJ Arsenal Puffco Pivot Tops - Gourdy (Limited Edition), 1 x Stabwood Dab Tool - Red, 1 x Stabwood Dab Tool-Green, 1 x Stabwood Dab Tool - Blue, 1 x Peak Pro 3DXL Chamber - Black | D98: 480 | E98: 191.368 | F98: =IFERROR(__xludf.DUMMYFUNCTION("""COMPUTED_VALUE"""),191.36799999999997) -> 191.368
A99: 46113.482 | B99: Tin UY | C99: 1 x Peak Pro 3DXL - Onyx, 1 x Peak Pro 3DXL - Pearl, 1 x Pivot Pine, 1 x PUFFCO TRAVEL CASE PLATEADO, 1 x Pivot Tops Display - V1 (18), 1 x Pivot Tops Display - V2 (18), 1 x BigFun! Puffco Pivot Tops - LIL' X, 1 x MJ Arsenal Puffco Pivot Tops - Gourdy (Limited Edition), 1 x MJ Arsenal Puffco Peak Tops - Quadra, 2 x Hot knife NEW NEGRO, 1 x Hot knife NEW PEARL, 2 x Peak 3D Chamber - Onyx, 1 x Peak Pro Glass 2.0, 1 x Proxy Bub Wizard - Haze, 1 x Proxy - Haze, 1 x Proxy - Onyx, 4 x Proxy Core silicona , 1 x Stabwood Dab Tool - Blue, 1 x Stabwood Dab Tool-Green, 1 x Stabwood Dab Tool - Red | D99: 2114 | E99: 573.63032 | F99: =IFERROR(__xludf.DUMMYFUNCTION("""COMPUTED_VALUE"""),286.81516000000005) -> 286.81516
A100: 46113.547 | B100: MARSHAL Lean | C100: 2 x Peak Pro 3DXL - Onyx, 2 x Peak Pro 3DXL - Pearl, 1 x Teddy Peak Top Teddy Peak Top, 1 x Proxy Core silicona , 2 x Hot knife NEW NEGRO, 1 x MJ Arsenal Puffco Peak Tops - Quadra, 4 x Terp Blender Bangers Gold - Full Weld 90-10mm, 1 x Turbine Mini Dab Rig - Clear, 1 x Time Turner Mini Dab Rig Clear, 1 x The Plasma Core Rig - Clear | D100: 1973 | E100: 441.80808 | F100: =IFERROR(__xludf.DUMMYFUNCTION("""COMPUTED_VALUE"""),441.80807999999996) -> 441.80808
...

Sheet Control de errores

Sheet Costo Carga
E1: Peso | G1: Costo
A2: Peak Pro 3DXL - Onyx | B2: 18 | C2: 268 | D2: =C2*B2 -> 4824 | E2: 0.791 | F2: =38*E2 -> 30.058 | G2: =F2+C2 -> 298.058
A3: Peak Pro 3DXL - Pearl | B3: 18 | C3: 250 | D3: =C3*B3 -> 4500 | E3: 0.791 | F3: =38*E3 -> 30.058 | G3: =F3+C3 -> 280.058
A4: Proxy - Haze | B4: 24 | C4: 135 | D4: =C4*B4 -> 3240 | E4: 0.566 | F4: =38*E4 -> 21.508 | G4: =F4+C4 -> 156.508
A5: Proxy - Onyx | B5: 24 | C5: 135 | D5: =C5*B5 -> 3240 | E5: 0.566 | F5: =38*E5 -> 21.508 | G5: =F5+C5 -> 156.508
A6: Pivot Pine | B6: 24 | C6: 71 | D6: =C6*B6 -> 1704 | E6: 0.23 | F6: =38*E6 -> 8.74 | G6: =F6+C6 -> 79.74
A7: Pivot - Onyx | B7: 24 | C7: 71 | D7: =C7*B7 -> 1704 | E7: 0.23 | F7: =38*E7 -> 8.74 | G7: =F7+C7 -> 79.74
A8: Peak Pine | B8: 18 | C8: 119 | D8: =C8*B8 -> 2142 | E8: 0.676 | F8: =38*E8 -> 25.688 | G8: =F8+C8 -> 144.688
A9: Peak - Canyon | B9: 18 | C9: 119 | D9: =C9*B9 -> 2142 | E9: 0.676 | F9: =38*E9 -> 25.688 | G9: =F9+C9 -> 144.688
A10: Peak - Onyx | B10: 12 | C10: 119 | D10: =C10*B10 -> 1428 | E10: 0.676 | F10: =38*E10 -> 25.688 | G10: =F10+C10 -> 144.688
A11: Peak Pro 3DXL Chamber - Black | B11: 30 | C11: 50 | D11: =C11*B11 -> 1500 | E11: 0.084 | F11: =38*E11 -> 3.192 | G11: =F11+C11 -> 53.192
A12: Hot knife Negro | B12: 30 | C12: 32.5 | D12: =C12*B12 -> 975 | E12: 0.18 | F12: =38*E12 -> 6.84 | G12: =F12+C12 -> 39.34
A13: Hot knife Pearl | B13: 30 | C13: 32.5 | D13: =C13*B13 -> 975 | E13: 0.18 | F13: =38*E13 -> 6.84 | G13: =F13+C13 -> 39.34
... A22: Peak Atomizer | B22: 12 | C22: 17.5 | D22: =C22*B22 -> 210 | E22: 0.114 | F22: =38*E22 -> 4.332 | G22: =F22+C22 -> 21.832
A23: Adaptador Peak Pro Link | B23: 18 | C23: 74 | D23: =C23*B23 -> 1332 | E23: 0.399 | F23: =38*E23 -> 15.162 | G23: =F23+C23 -> 89.162 | I23: =E23*18 -> 7.182 | J23: 24 | K23: Pro link
D25: =SUM(D2:D23) -> 34671 | F25: =SUM(F2:F23) -> 260.338
A27: ROSIN BAGS PACK X 20 UNIDADES ( 5CM X 10 CM) MICRAJE 25 | B27: 80 | C27: 11 | D27: =C27*B27 -> 880 | E27: 0.027 | F27: =38*E27 -> 1.026 | G27: =F27+C27 -> 12.026 | I27: =E27*80 -> 2.16
A28: ROSIN BAGS PACK X 25 UNIDADES ( 6 CM X 11 CM) MICRAJE 25 | B28: 20 | C28: 15 | D28: =C28*B28 -> 300 | E28: 0.027 | F28: =38*E28 -> 1.026 | G28: =F28+C28 -> 16.026 | I28: =E28*B28 -> 0.54
A29: MALLAS PARA BUBBLE HASH 20 LITROS PACK x 8 unidades | B29: 5 | C29: 203 | D29: =C29*B29 -> 1015 | E29: 0.56 | F29: =38*E29 -> 21.28 | G29: =F29+C29 -> 224.28 | I29: =E29*B29 -> 2.8
D31: =SUM(D27:D29) -> 2195 | I31: =SUM(I23:I29) -> 12.682
A34: Artículo | B34: 12 | C34: $119 | D34: $1,428
A35: Peak Onyx | B35: 12 | C35: $71 | D35: $852
A36: Pivot Pine | B36: 12 | C36: $71 | D36: $852
A37: Pivot Onyx | B37: 30 | C37: $25,50 | D37: $765
A38: Plus Battery - Pearl | B38: 6 | C38: $53,50 | D38: $321
A39: Proxy Bub - Haze | B39: 6 | C39: $53,50 | D39: $321
A40: Proxy Bub - Onyx | B40: 24 | C40: $74 | D40: $1,776
A41: Peak Pro Link - Onyx | B41: 120 | C41: $4,50 | D41: $540
A42: Plus Supercharger
D43: =SUM(D34:D41) -> 0
A46: ITEM | B46: SKU | C46: PRECIO_UNIT | D46: CANTIDAD | E46: TOTAL_PRECIO | F46: PESO_UNIT_ESTIMADO_KG | G46: PESO | H46: KG USD
A47: BigFun! Puffco Pivot Tops - Drei | B47: BF-PA-PVTOPS-DRDL | C47: 15 | D47: 3 | E47: 45 | F47: 0.025 | G47: =F47*D47 -> 0.075 | H47: =F47*38 -> 0.95 | I47: =H47+C47 -> 15.95
A48: BigFun! Puffco Pivot Tops - LIL' Frosty | B48: BF-PA-PVTOPS-SNWMN | C48: 18 | D48: 3 | E48: 54 | F48: 0.02 | G48: =F48*D48 -> 0.06 | H48: =F48*38 -> 0.76 | I48: =H48+C48 -> 18.76
A49: BigFun! Puffco Pivot Tops - LIL' X | B49: BF-PA-PVTOPS-XMAS | C49: 21 | D49: 3 | E49: 63 | F49: 0.031 | G49: =F49*D49 -> 0.093 | H49: =F49*38 -> 1.178 | I49: =H49+C49 -> 22.178
A50: Peak Pro 3DXL Joystick Caps - Black Nebula | B50: EMPIRE-CC-PKPR3DXLJYSTKCPS-BLKNBLS | C50: 10 | D50: 2 | E50: 20 | F50: 0.001 | G50: =F50*D50 -> 0.002 | H50: =F50*38 -> 0.038 | I50: =H50+C50 -> 10.038
A51: Peak Pro 3DXL Joystick Caps Blue Lagoon | B51: EMPIRECC--PKPR3DXLJYSTKCPS-BLULGN | C51: 10 | D51: 2 | E51: 20 | F51: 0.001 | G51: =F51*D51 -> 0.002 | H51: =F51*38 -> 0.038 | I51: =H51+C51 -> 10.038
A52: Peak Pro 3DXL Joystick Caps - Clear | B52: EMPIRECC--PKPR3DXLJYSTKCPS-CLR | C52: 6 | D52: 2 | E52: 12 | F52: 0.001 | G52: =F52*D52 -> 0.002 | H52: =F52*38 -> 0.038 | I52: =H52+C52 -> 6.038
A53: Peak Pro 3DXL Joystick Caps - Eclipse | B53: EMPIRE-CC-PKPR3DXLJYSTKCPS-ECLPS | C53: 10 | D53: 2 | E53: 20 | F53: 0.001 | G53: =F53*D53 -> 0.002 | H53: =F53*38 -> 0.038 | I53: =H53+C53 -> 10.038
A54: Peak Pro 3DXL Joystick Caps - Firestone Red | B54: EMPIRE-CC-PKPR3DXLJYSTKCPS-FRSTNRD | C54: 10 | D54: 2 | E54: 20 | F54: 0.001 | G54: =F54*D54 -> 0.002 | H54: =F54*38 -> 0.038 | I54: =H54+C54 -> 10.038
A55: Peak Pro 3DXL Joystick Caps Glow in the Dark | B55: EMPIRE-CC-PKPR3DXLJYSTKCPS-GITD | C55: 10 | D55: 2 | E55: 20 | F55: 0.001 | G55: =F55*D55 -> 0.002 | H55: =F55*38 -> 0.038 | I55: =H55+C55 -> 10.038
A56: Peak Pro 3DXL Joystick Caps - Orange | B56: EMPIRE-CC-PKPR3DXLJYSTKCPS-ORA | C56: 10 | D56: 2 | E56: 20 | F56: 0.001 | G56: =F56*D56 -> 0.002 | H56: =F56*38 -> 0.038 | I56: =H56+C56 -> 10.038
A57: Peak Pro 3DXL Joystick Caps - Pink UV | B57: EMPIRECC--PKPR3DXLJYSTKCPS-PNKUV | C57: 10 | D57: 2 | E57: 20 | F57: 0.001 | G57: =F57*D57 -> 0.002 | H57: =F57*38 -> 0.038 | I57: =H57+C57 -> 10.038
A58: Peak Pro 3DXL Joystick Caps - Slime | B58: EMPIRECC--PKPR3DXLJYSTKCPS-SLME | C58: 10 | D58: 2 | E58: 20 | F58: 0.001 | G58: =F58*D58 -> 0.002 | H58: =F58*38 -> 0.038 | I58: =H58+C58 -> 10.038
... A62: Peak Pro 3DXL Joystick Caps - Yellow | B62: EMPIRE-CC-PKPR3DXLJYSTKCPS-YEL | C62: 10 | D62: 2 | E62: 20 | F62: 0.001 | G62: =F62*D62 -> 0.002 | H62: =F62*38 -> 0.038 | I62: =H62+C62 -> 10.038
A63: Pivot Tops Display - V1 (18) | B63: EMPIRE-PA-PVTTOPDIS-18PK | C63: 15 | D63: 18 | E63: =D63*C63 -> 270 | F63: 0.05 | G63: =F63*D63 -> 0.9 | H63: =F63*38 -> 1.9 | I63: =H63+C63 -> 16.9
A64: Chili Pepper Green (Red Hat) | B64: HG-CC-CHLIPEP-REDHT-GRN | C64: 6 | D64: 2 | E64: 12 | F64: 0.025 | G64: =F64*D64 -> 0.05 | H64: =F64*38 -> 0.95 | I64: =H64+C64 -> 6.95
A65: Chili Pepper - Orange (Milky Yellow Hat) | B65: HG-CC-CHLIPEP-MLKYLHT-ORA | C65: 6 | D65: 2 | E65: 12 | F65: 0.025 | G65: =F65*D65 -> 0.05 | H65: =F65*38 -> 0.95 | I65: =H65+C65 -> 6.95
A66: Chili Pepper Red (Yellow Hat) | B66: HGCC--CHLIPEP-YLWHT-RED | C66: 6 | D66: 2 | E66: 12 | F66: 0.025 | G66: =F66*D66 -> 0.05 | H66: =F66*38 -> 0.95 | I66: =H66+C66 -> 6.95
A67: Frog Green (Blue Base) | B67: HG-CC-FRG-BLUBSE-GRN | C67: 6 | D67: 1 | E67: 6 | F67: 0.04 | G67: =F67*D67 -> 0.04 | H67: =F67*38 -> 1.52 | I67: =H67+C67 -> 7.52
A68: Frog Lake Green (Blue Base) | B68: HG-CC-FRG-BLUBSE-LKGRN | C68: 5.5 | D68: 1 | E68: 5.5 | F68: 0.04 | G68: =F68*D68 -> 0.04 | H68: =F68*38 -> 1.52 | I68: =H68+C68 -> 7.02
A69: Frog Light Yellow (Blue Base) | B69: HG-CC-FRG-BLUBSE-LTYEL | C69: 5.5 | D69: 1 | E69: 5.5 | F69: 0.04 | G69: =F69*D69 -> 0.04 | H69: =F69*38 -> 1.52 | I69: =H69+C69 -> 7.02
A70: Frog - Matrix Green (Blue Base) | B70: HG-CC-FRG-BLUBSE-MTXGRN | C70: 6.5 | D70: 1 | E70: 6.5 | F70: 0.04 | G70: =F70*D70 -> 0.04 | H70: =F70*38 -> 1.52 | I70: =H70+C70 -> 8.02
A71: Ghost Amber | B71: HG-CC-GHST-AMBR | C71: 5.25 | D71: 1 | E71: 5.25 | F71: 0.04 | G71: =F71*D71 -> 0.04 | H71: =F71*38 -> 1.52 | I71: =H71+C71 -> 6.77
A72: Ghost - Green | B72: HG-CC-GHST-GRN | C72: 5.25 | D72: 2 | E72: 10.5 | F72: 0.04 | G72: =F72*D72 -> 0.08 | H72: =F72*38 -> 1.52 | I72: =H72+C72 -> 6.77
A73: Ghost - Lavender | B73: HG-CC-GHST-LVNDR | C73: 5.25 | D73: 2 | E73: 10.5 | F73: 0.04 | G73: =F73*D73 -> 0.08 | H73: =F73*38 -> 1.52 | I73: =H73+C73 -> 6.77
A74: Ghost Smoke | B74: HG-CC-GHST-SMK | C74: 5.25 | D74: 2 | E74: 10.5 | F74: 0.04 | G74: =F74*D74 -> 0.08 | H74: =F74*38 -> 1.52 | I74: =H74+C74 -> 6.77
A75: Mushroom Blue (Green Base) | B75: HG-CC-MSHRM1-GRNBSE-BLU | C75: 5.5 | D75: 1 | E75: 5.5 | F75: 0.04 | G75: =F75*D75 -> 0.04 | H75: =F75*38 -> 1.52 | I75: =H75+C75 -> 7.02
... A115: Teddy Peak Top Teddy Peak Top | B115: MJA-PA-VDAY2026LE-TDYPKTP | C115: 55 | D115: 4 | E115: 220 | F115: 0.2 | G115: =F115*D115 -> 0.8 | H115: =F115*38 -> 7.6 | I115: =H115+C115 -> 62.6
A118: Código | B118: Descripción | C118: Cantidad (Unidades Totales) | D118: Precio Unitario | E118: Precio Total
A119: S/C | B119: MiniNail - Coil Caddy Kit with Terp Slurper Set (Black, 14mm) | C119: 1 | D119: 165 | E119: 165 | F119: 1.528 | G119: =F119*38 -> 58.064 | H119: =F119*C119 -> 1.528 | I119: =E119/$E$135 -> 0.027215911 | J119: =$I$135*I119 -> 16.805281 | K119: =J119/C119 -> 16.805281 | L119: =D119*1.04 -> 171.6 | M119: =L119+K119+G119 -> 246.46928
A120: S/C | B120: MiniNail - Coil Caddy Kit with Terp Slurper Set (Black, 10mm) | C120: 1 | D120: 165 | E120: 165 | F120: 1.528 | G120: =F120*38 -> 58.064 | H120: =F120*C120 -> 1.528 | I120: =E120/$E$135 -> 0.027215911 | J120: =$I$135*I120 -> 16.805281 | K120: =J120/C120 -> 16.805281 | L120: =D120*1.04 -> 171.6 | M120: =L120+K120+G120 -> 246.46928
A121: S/C | B121: MiniNail - Coil Caddy Kit with Terp Slurper Set (Green, 14mm) | C121: 1 | D121: 165 | E121: 165 | F121: 1.528 | G121: =F121*38 -> 58.064 | H121: =F121*C121 -> 1.528 | I121: =E121/$E$135 -> 0.027215911 | J121: =$I$135*I121 -> 16.805281 | K121: =J121/C121 -> 16.805281 | L121: =D121*1.04 -> 171.6 | M121: =L121+K121+G121 -> 246.46928
A122: S/C | B122: MiniNail - Coil Caddy Kit with Terp Slurper Set (Green, 10mm) | C122: 1 | D122: 165 | E122: 165 | F122: 1.528 | G122: =F122*38 -> 58.064 | H122: =F122*C122 -> 1.528 | I122: =E122/$E$135 -> 0.027215911 | J122: =$I$135*I122 -> 16.805281 | K122: =J122/C122 -> 16.805281 | L122: =D122*1.04 -> 171.6 | M122: =L122+K122+G122 -> 246.46928
A123: S/C | B123: MiniNail - Complete MiniNail Kit w/ Quartz Banger (Black) | C123: 1 | D123: 150 | E123: 150 | F123: 0.791 | G123: =F123*38 -> 30.058 | H123: =F123*C123 -> 0.791 | I123: =E123/$E$135 -> 0.024741737 | J123: =$I$135*I123 -> 15.277528 | K123: =J123/C123 -> 15.277528 | L123: =D123*1.04 -> 156 | M123: =L123+K123+G123 -> 201.33553
A124: S/C | B124: MiniNail - Complete MiniNail Kit w/ Quartz Banger (Green) | C124: 1 | D124: 150 | E124: 150 | F124: 0.791 | G124: =F124*38 -> 30.058 | H124: =F124*C124 -> 0.791 | I124: =E124/$E$135 -> 0.024741737 | J124: =$I$135*I124 -> 15.277528 | K124: =J124/C124 -> 15.277528 | L124: =D124*1.04 -> 156 | M124: =L124+K124+G124 -> 201.33553
A125: S/C | B125: MiniNail - Iso Wipes | C125: 400 | D125: 3 | E125: 1200 | F125: 0.183 | G125: =F125*38 -> 6.954 | H125: =F125*C125 -> 73.2 | I125: =E125/$E$135 -> 0.1979339 | J125: =$I$135*I125 -> 122.22022 | K125: =J125/C125 -> 0.30555056 | L125: =D125*1.04 -> 3.12 | M125: =L125+K125+G125 -> 10.379551
A126: S/C | B126: MiniNail - Complete MiniNail Kit w/ Quartz Banger (Purple) | C126: 1 | D126: 150 | E126: 150 | F126: 0.791 | G126: =F126*38 -> 30.058 | H126: =F126*C126 -> 0.791 | I126: =E126/$E$135 -> 0.024741737 | J126: =$I$135*I126 -> 15.277528 | K126: =J126/C126 -> 15.277528 | L126: =D126*1.04 -> 156 | M126: =L126+K126+G126 -> 201.33553
A127: S/C | B127: MiniNail - Complete MiniNail Kit w/ Quartz Banger (Orange) | C127: 1 | D127: 150 | E127: 150 | F127: 0.791 | G127: =F127*38 -> 30.058 | H127: =F127*C127 -> 0.791 | I127: =E127/$E$135 -> 0.024741737 | J127: =$I$135*I127 -> 15.277528 | K127: =J127/C127 -> 15.277528 | L127: =D127*1.04 -> 156 | M127: =L127+K127+G127 -> 201.33553
A128: S/C | B128: MiniNail - Coil Caddy with 40mm Heater Coil | C128: 3 | D128: 99.99 | E128: 299.97 | F128: 1.149 | G128: =F128*38 -> 43.662 | H128: =F128*C128 -> 3.447 | I128: =E128/$E$135 -> 0.049478527 | J128: =$I$135*I128 -> 30.552001 | K128: =J128/C128 -> 10.184 | L128: =D128*1.04 -> 103.9896 | M128: =L128+K128+G128 -> 157.8356
A129: S/C | B129: MiniNail - Coil Caddy with Heater Coil | C129: 3 | D129: 84 | E129: 252 | F129: 1.127 | G129: =F129*38 -> 42.826 | H129: =F129*C129 -> 3.381 | I129: =E129/$E$135 -> 0.041566119 | J129: =$I$135*I129 -> 25.666247 | K129: =J129/C129 -> 8.5554157 | L129: =D129*1.04 -> 87.36 | M129: =L129+K129+G129 -> 138.74142
A130: B10 | B130: Bubblebagdude - 5 GAL 8 BAG KIT (ALL MESH) | C130: 30 | D130: 38.99 | E130: 1169.7 | F130: 0.42 | G130: =F130*38 -> 15.96 | H130: =F130*C130 -> 12.6 | I130: =E130/$E$135 -> 0.19293607 | J130: =$I$135*I130 -> 119.13416 | K130: =J130/C130 -> 3.9711388 | L130: =D130*1.04 -> 40.5496 | M130: =L130+K130+G130 -> 60.480739
... A134: B27 | B134: Bubblebagdude - Pressing Screen (5 pack) | C134: 50 | D134: 7.99 | E134: 399.5 | F134: 0.041 | G134: =F134*38 -> 1.558 | H134: =F134*C134 -> 2.05 | I134: =E134/$E$135 -> 0.065895494 | J134: =$I$135*I134 -> 40.68915 | K134: =J134/C134 -> 0.813783 | L134: =D134*1.04 -> 8.3096 | M134: =L134+K134+G134 -> 10.681383
E135: =SUM(E119:E134) -> 6062.63 | I135: =(11*38)+92.67+106.81 -> 617.48
B137: Descripción | C137: Cantidad (Unidades Totales) | D137: Precio Unitario | E137: TOTAL
B138: MiniNail - Coil Caddy Kit with Terp Slurper Set (Black, 14mm) | C138: 1 | D138: 165 | E138: 246.46928 | F138: =E138*1.35 -> 332.73353 | G138: 330
B139: MiniNail - Coil Caddy Kit with Terp Slurper Set (Black, 10mm) | C139: 1 | D139: 165 | E139: 246.46928 | F139: =E139*1.35 -> 332.73353 | G139: 330
B140: MiniNail - Coil Caddy Kit with Terp Slurper Set (Green, 14mm) | C140: 1 | D140: 165 | E140: 246.46928 | F140: =E140*1.35 -> 332.73353 | G140: 330
B141: MiniNail - Coil Caddy Kit with Terp Slurper Set (Green, 10mm) | C141: 1 | D141: 165 | E141: 246.46928 | F141: =E141*1.35 -> 332.73353 | G141: 330
B142: MiniNail - Complete MiniNail Kit w/ Quartz Banger (Black) | C142: 1 | D142: 150 | E142: 201.33553 | F142: =E142*1.35 -> 271.80296 | G142: 270
B143: MiniNail - Complete MiniNail Kit w/ Quartz Banger (Green) | C143: 1 | D143: 150 | E143: 201.33553 | F143: =E143*1.35 -> 271.80296 | G143: 270
B144: MiniNail - Iso Wipes | C144: 400 | D144: 3 | E144: 10.379551 | F144: =E144*1.35 -> 14.012393 | G144: 14
B145: MiniNail - Complete MiniNail Kit w/ Quartz Banger (Purple) | C145: 1 | D145: 150 | E145: 201.33553 | F145: =E145*1.35 -> 271.80296 | G145: 270
B146: MiniNail - Complete MiniNail Kit w/ Quartz Banger (Orange) | C146: 1 | D146: 150 | E146: 201.33553 | F146: =E146*1.35 -> 271.80296 | G146: 270
B147: MiniNail - Coil Caddy with 40mm Heater Coil | C147: 3 | D147: 99.99 | E147: 157.8356 | F147: =E147*1.35 -> 213.07806 | G147: 210
B148: MiniNail - Coil Caddy with Heater Coil | C148: 3 | D148: 84 | E148: 138.74142 | F148: =E148*1.35 -> 187.30091 | G148: 190
B149: Bubblebagdude - 5 GAL 8 BAG KIT (ALL MESH) | C149: 30 | D149: 38.99 | E149: 60.480739 | F149: =E149*1.35 -> 81.648997 | G149: 80
... B153: Bubblebagdude - Pressing Screen (5 pack) | C153: 50 | D153: 7.99 | E153: 10.681383 | F153: =E153*1.35 -> 14.419867 | G153: 15
B156: SKU | C156: PRECIO_UNIT | D156: CANTIDAD | E156: TOTAL_PRECIO | F156: PESO_UNIT_ESTIMADO_KG | G156: PESO | H156: KG USD
B157: Proxy core | C157: 128 | D157: 42 | E157: 45 | F157: 0.373 | G157: =F157*D157 -> 15.666 | H157: =F157*38 -> 14.174 | I157: =(H157+C157)*1.03 -> 146.43922 | O157: =30*0.373 -> 11.19 | P157: =30*0.064 -> 1.92 | Q157: =12*0.128 -> 1.536
B158: Accesorio Proxy core | C158: 27 | D158: 42 | E158: 54 | F158: 0.128 | G158: =F158*D158 -> 5.376 | H158: =F158*38 -> 4.864 | I158: =(H158+C158)*1.03 -> 32.81992
B159: Hot knife | C159: 33 | D159: 70 | E159: 63 | F159: 0.064 | G159: =F159*D159 -> 4.48 | H159: =F159*38 -> 2.432 | I159: =(H159+C159)*1.03 -> 36.49496
B160: Hot knife | C160: 33 | D160: 70 | E160: 20 | F160: 0.064 | G160: =F160*D160 -> 4.48 | H160: =F160*38 -> 2.432 | I160: =(H160+C160)*1.03 -> 36.49496
A162: Código de Item | B162: Descripción | C162: Cantidad | D162: Precio Unitario | E162: Precio Final | F162: PESO_UNIT_ESTIMADO_KG | G162: KG TOTALES | H162: KG USD | I162: COSTO FINAL
A163: BF-PA-PVTOPS-DROL | B163: BigFun! Puffco Pivot Tops - Drei | C163: 3 | D163: 7.2 | E163: 21.6 | F163: 0.025 | G163: =F163*C163 -> 0.075 | H163: =F163*38 -> 0.95 | I163: =(H163+D163)*1.03 -> 8.3945
A164: BF-PA-PVTOPS-SNWMN | B164: BigFun! Puffco Pivot Tops - LIL' Frosty | C164: 3 | D164: 9 | E164: 27 | F164: 0.02 | G164: =F164*C164 -> 0.06 | H164: =F164*38 -> 0.76 | I164: =(H164+D164)*1.03 -> 10.0528
A165: BF-PA-PVTOPS-XMAS | B165: BigFun! Puffco Pivot Tops - LIL' X | C165: 2 | D165: 13.95 | E165: 27.9 | F165: 0.031 | G165: =F165*C165 -> 0.062 | H165: =F165*38 -> 1.178 | I165: =(H165+D165)*1.03 -> 15.58184
A166: EMPIRE-PA-PVTTOPDIS-18PK | B166: Pivot Tops Display - V1 (18) | C166: 1 | D166: 270 | E166: 270 | F166: 0.928 | G166: =F166*C166 -> 0.928 | H166: =F166*38 -> 35.264 | I166: =(H166+D166)*1.03 -> 314.42192
A167: EMPRIE-PA-PVTTOPDIS-V2-18PK | B167: Pivot Tops Display - V2 (18) | C167: 1 | D167: 225 | E167: 225 | F167: 0.828 | G167: =F167*C167 -> 0.828 | H167: =F167*38 -> 31.464 | I167: =(H167+D167)*1.03 -> 264.15792
A168: HG-CC-CHLIPEP-REDHT-GRN | B168: Chili Pepper - Green (Red Hat) | C168: 3 | D168: 5.4 | E168: 16.2 | F168: 0.025 | G168: =F168*C168 -> 0.075 | H168: =F168*38 -> 0.95 | I168: =(H168+D168)*1.03 -> 6.5405
A169: HG-CC-CHLIPEP-YLWHT-RED | B169: Chili Pepper- Red (Yellow Hat) | C169: 4 | D169: 5.4 | E169: 21.6 | F169: 0.025 | G169: =F169*C169 -> 0.1 | H169: =F169*38 -> 0.95 | I169: =(H169+D169)*1.03 -> 6.5405
...

Sheet PESOS
A1: Peak Pro 3DXL - Onyx | B1: 0.791
A2: Peak Pro 3DXL - Pearl | B2: 0.791
A3: Proxy - Haze | B3: 0.566
A4: Proxy - Onyx | B4: 0.566
A5: Pivot Pine | B5: 0.23
A6: Pivot - Onyx | B6: 0.23
A7: Peak Pine | B7: 0.676
A8: Peak - Canyon | B8: 0.676
A9: Peak - Onyx | B9: 0.676
A10: Peak Pro 3DXL Chamber - Black | B10: 0.084
A11: Hot knife Negro | B11: 0.18
A12: Hot knife Pearl | B12: 0.18
... A175: Ursa Mini Dab Rig - Clear | B175: 0.262

Sheet COMPRAS Proveedores
A1: fecha | B1: Pedido | C1: Inversion inicial | D1: GEr | E1: Luke | F1: Monto fc | H1: PAGO A CUENTA CON EL COLO | I1: Fee COLO POR GIRO | J1: KG SIXTAR | N1: fecha | O1: USD
A2: 46062 | D2: 6750 | E2: 6750 | M2: GER PLANTO
B3: puffco | F3: $26,436.00 | G3: pedido iniicial | J3: 4940 | M3: FACU LP
B4: puffco | F4: $7,911.00 | G4: pedido post polaco | M4: ONG HIGH UP
A5: 46063 | B5: mallas THE PRESS CLUB | F5: 2150 | G5: mallas para prensar | J5: 304 | M5: Vendedor Tincho
A6: 46066 | B6: MJA | F6: $2,424.91 | G6: bongs de vidrio | H6: 2424.91 | J6: 532 | M6: Vendedor Agustin
A7: 46063 | B7: puffco | F7: 1776 | G7: pro lin reestock | M7: COCO SALTA 420
A8: 46066 | B8: puffco | F8: $6,315.00 | G8: reestock pivot peak link | J8: 304 | M8: BIG FACU COSTA ATLANTICA
B9: Mininail | F9: 3118.78 | H9: 3118.78 | M9: CHARLY DISTRI
B10: Glob Mops
B11: Formula 420 | F11: 2973.81
B12: papel reynols amazon luke | F12: 353 | J12: 275 | L12: pago luke con TC
B13: Ryanfit Glass pivot | F13: 253 | H13: 253 | L13: pago colo con TC
B14: puffco | F14: 540
B15: puffco | F15: 16116
B16: mallas THE PRESS CLUB reestock | F16: 2710
B17: MJA reestock | F17: 3497.5
B18: puffco producto nuevo | F18: 10470

Sheet Cta Cte total
A1: FECHA INGRESO | B1: SOCIO (Lucas/German) | C1: MONTO PUESTO | E1: FECHA GASTO | F1: DETALLE (Qué se pagó) | G1: MONTO GASTADO | I1: FECHA | J1: MOVIMIENTO | K1: ENTRADA | L1: SALIDA | M1: SALDO EN CAJA
A2: 46062 | B2: Lucas | C2: 6750 | E2: 46063 | F2: Sixstar Puffco 1 | G2: 4940 | I2: =IFERROR(__xludf.DUMMYFUNCTION("SORT(FILTER(VSTACK( IFNA(FILTER(HSTACK(A2:A1000, ""Ingreso: ""&B2:B1000, C2:C1000, IF(ROW(A2:A1000),0)), (A2:A1000<>"""")+(B2:B1000<>"""")+(C2:C1000<>"""")), HSTACK("""","""",0,0)), IFNA(FILTER(HSTACK(E2:E1000, ""Gasto: ""&F2:F1000, IF(ROW(E2:E1000)"&",0), G2:G1000), (E2:E1000<>"""")+(F2:F1000<>"""")+(G2:G1000<>"""")), HSTACK("""","""",0,0)), IFNA(FILTER(HSTACK('CTA CTE COLO'!B2:B1000, ""Colo: ""&'CTA CTE COLO'!A2:A1000, IF('CTA CTE COLO'!F2:F1000>0, 'CTA CTE COLO'!F2:F1000, 0), IF('CTA CTE COLO'!F2"&":F1000<0, ABS('CTA CTE COLO'!F2:F1000), 0)), ISNUMBER('CTA CTE COLO'!F2:F1000)*('CTA CTE COLO'!F2:F1000<>0)), HSTACK("""","""",0,0)) ), INDEX(VSTACK( IFNA(FILTER(A2:A1000, (A2:A1000<>"""")+(B2:B1000<>"""")+(C2:C1000<>"""")), """"), IFNA(FILTER(E2:E1"&"000, (E2:E1000<>"""")+(F2:F1000<>"""")+(G2:G1000<>"""")), """"), IFNA(FILTER('CTA CTE COLO'!B2:B1000, ISNUMBER('CTA CTE COLO'!F2:F1000)*('CTA CTE COLO'!F2:F1000<>0)), """") ), 0, 1)<>""""), 1, TRUE)"),46032.0) -> 46032 | J2: =IFERROR(__xludf.DUMMYFUNCTION("""COMPUTED_VALUE"""),"Colo: ANTERIOR") -> Colo: ANTERIOR | K2: =IFERROR(__xludf.DUMMYFUNCTION("""COMPUTED_VALUE"""),1158.0) -> 1158 | L2: =IFERROR(__xludf.DUMMYFUNCTION("""COMPUTED_VALUE"""),0.0) -> 0 | M2: {=IF(I2:I1000="", "", SCAN(0, N(K2:K1000) - N(L2:L1000), LAMBDA(acumulado, diferencia, acumulado + diferencia)))} -> 1158
A3: 46062 | B3: German | C3: 6750 | E3: 46063 | F3: Sixstar Press club | G3: 304 | I3: =IFERROR(__xludf.DUMMYFUNCTION("""COMPUTED_VALUE"""),46053.0) -> 46053 | J3: =IFERROR(__xludf.DUMMYFUNCTION("""COMPUTED_VALUE"""),"Colo: The press Club") -> Colo: The press Club | K3: =IFERROR(__xludf.DUMMYFUNCTION("""COMPUTED_VALUE"""),0.0) -> 0 | L3: =IFERROR(__xludf.DUMMYFUNCTION("""COMPUTED_VALUE"""),2180.0) -> 2180 | M3: -1022
E4: 46065 | F4: Sixstar Puffco 2 | G4: 304 | I4: =IFERROR(__xludf.DUMMYFUNCTION("""COMPUTED_VALUE"""),46058.0) -> 46058 | J4: =IFERROR(__xludf.DUMMYFUNCTION("""COMPUTED_VALUE"""),"Colo: ANTERIOR") -> Colo: ANTERIOR | K4: =IFERROR(__xludf.DUMMYFUNCTION("""COMPUTED_VALUE"""),386.0) -> 386 | L4: =IFERROR(__xludf.DUMMYFUNCTION("""COMPUTED_VALUE"""),0.0) -> 0 | M4: -636
E5: 46065 | F5: Sixstar Reynols | G5: 275 | I5: =IFERROR(__xludf.DUMMYFUNCTION("""COMPUTED_VALUE"""),46062.0) -> 46062 | J5: =IFERROR(__xludf.DUMMYFUNCTION("""COMPUTED_VALUE"""),"Ingreso: Lucas") -> Ingreso: Lucas | K5: =IFERROR(__xludf.DUMMYFUNCTION("""COMPUTED_VALUE"""),6750.0) -> 6750 | L5: =IFERROR(__xludf.DUMMYFUNCTION("""COMPUTED_VALUE"""),0.0) -> 0 | M5: 6114
E6: 46080 | F6: Sixstar Puffco 3 | G6: 1216 | I6: =IFERROR(__xludf.DUMMYFUNCTION("""COMPUTED_VALUE"""),46062.0) -> 46062 | J6: =IFERROR(__xludf.DUMMYFUNCTION("""COMPUTED_VALUE"""),"Ingreso: German") -> Ingreso: German | K6: =IFERROR(__xludf.DUMMYFUNCTION("""COMPUTED_VALUE"""),6750.0) -> 6750 | L6: =IFERROR(__xludf.DUMMYFUNCTION("""COMPUTED_VALUE"""),0.0) -> 0 | M6: 12864
E7: 46083 | F7: Sixstar MJ ARSENAL | G7: 532 | I7: =IFERROR(__xludf.DUMMYFUNCTION("""COMPUTED_VALUE"""),46063.0) -> 46063 | J7: =IFERROR(__xludf.DUMMYFUNCTION("""COMPUTED_VALUE"""),"Gasto: Sixstar Puffco 1") -> Gasto: Sixstar Puffco 1 | K7: =IFERROR(__xludf.DUMMYFUNCTION("""COMPUTED_VALUE"""),0.0) -> 0 | L7: =IFERROR(__xludf.DUMMYFUNCTION("""COMPUTED_VALUE"""),4940.0) -> 4940 | M7: 7924
E8: 46090 | F8: Sixstar Mininail/bubble | G8: 4750 | I8: =IFERROR(__xludf.DUMMYFUNCTION("""COMPUTED_VALUE"""),46063.0) -> 46063 | J8: =IFERROR(__xludf.DUMMYFUNCTION("""COMPUTED_VALUE"""),"Gasto: Sixstar Press club") -> Gasto: Sixstar Press club | K8: =IFERROR(__xludf.DUMMYFUNCTION("""COMPUTED_VALUE"""),0.0) -> 0 | L8: =IFERROR(__xludf.DUMMYFUNCTION("""COMPUTED_VALUE"""),304.0) -> 304 | M8: 7620
E9: 46091 | F9: Sixstar puffco 4 | G9: 2546 | I9: =IFERROR(__xludf.DUMMYFUNCTION("""COMPUTED_VALUE"""),46064.0) -> 46064 | J9: =IFERROR(__xludf.DUMMYFUNCTION("""COMPUTED_VALUE"""),"Colo: PAGO PUFFCO") -> Colo: PAGO PUFFCO | K9: =IFERROR(__xludf.DUMMYFUNCTION("""COMPUTED_VALUE"""),0.0) -> 0 | L9: =IFERROR(__xludf.DUMMYFUNCTION("""COMPUTED_VALUE"""),4162.0) -> 4162 | M9: 3458
E10: 46086 | F10: Nacho | G10: 282.69 | I10: =IFERROR(__xludf.DUMMYFUNCTION("""COMPUTED_VALUE"""),46064.0) -> 46064 | J10: =IFERROR(__xludf.DUMMYFUNCTION("""COMPUTED_VALUE"""),"Colo: INGRESO LUCAS") -> Colo: INGRESO LUCAS | K10: =IFERROR(__xludf.DUMMYFUNCTION("""COMPUTED_VALUE"""),4000.0) -> 4000 | L10: =IFERROR(__xludf.DUMMYFUNCTION("""COMPUTED_VALUE"""),0.0) -> 0 | M10: 7458
E11: 46086 | F11: Coca | G11: 240.28 | I11: =IFERROR(__xludf.DUMMYFUNCTION("""COMPUTED_VALUE"""),46065.0) -> 46065 | J11: =IFERROR(__xludf.DUMMYFUNCTION("""COMPUTED_VALUE"""),"Gasto: Sixstar Puffco 2") -> Gasto: Sixstar Puffco 2 | K11: =IFERROR(__xludf.DUMMYFUNCTION("""COMPUTED_VALUE"""),0.0) -> 0 | L11: =IFERROR(__xludf.DUMMYFUNCTION("""COMPUTED_VALUE"""),304.0) -> 304 | M11: 7154
E12: 46094 | F12: Sistar puffco 5 (proxy core) | G12: 1140 | I12: =IFERROR(__xludf.DUMMYFUNCTION("""COMPUTED_VALUE"""),46065.0) -> 46065 | J12: =IFERROR(__xludf.DUMMYFUNCTION("""COMPUTED_VALUE"""),"Gasto: Sixstar Reynols") -> Gasto: Sixstar Reynols | K12: =IFERROR(__xludf.DUMMYFUNCTION("""COMPUTED_VALUE"""),0.0) -> 0 | L12: =IFERROR(__xludf.DUMMYFUNCTION("""COMPUTED_VALUE"""),275.0) -> 275 | M12: 6879 | O12: Le di 300 dls que habia dejado FACU LP para completar el retiro
E13: 46099 | F13: nachito al dia | G13: 418 | I13: =IFERROR(__xludf.DUMMYFUNCTION("""COMPUTED_VALUE"""),46067.0) -> 46067 | J13: =IFERROR(__xludf.DUMMYFUNCTION("""COMPUTED_VALUE"""),"Colo: PAGO MEDUSA") -> Colo: PAGO MEDUSA | K13: =IFERROR(__xludf.DUMMYFUNCTION("""COMPUTED_VALUE"""),0.0) -> 0 | L13: =IFERROR(__xludf.DUMMYFUNCTION("""COMPUTED_VALUE"""),2349.0) -> 2349 | M13: 4530 | O13: Le di pesos que dejo Marshal
E14: 46100 | F14: reserva oficina Leloir | G14: 400 | I14: =IFERROR(__xludf.DUMMYFUNCTION("""COMPUTED_VALUE"""),46070.0) -> 46070 | J14: =IFERROR(__xludf.DUMMYFUNCTION("""COMPUTED_VALUE"""),"Colo: Facundo Millan") -> Colo: Facundo Millan | K14: =IFERROR(__xludf.DUMMYFUNCTION("""COMPUTED_VALUE"""),4542.0) -> 4542 | L14: =IFERROR(__xludf.DUMMYFUNCTION("""COMPUTED_VALUE"""),0.0) -> 0 | M14: 9072 | O14: le di dolares que dejo Marshal
E15: 46101 | F15: Sixstar MJ ARSENAL 2 29kg | G15: 1102 | I15: =IFERROR(__xludf.DUMMYFUNCTION("""COMPUTED_VALUE"""),46071.0) -> 46071 | J15: =IFERROR(__xludf.DUMMYFUNCTION("""COMPUTED_VALUE"""),"Colo: PAGO MININAIL") -> Colo: PAGO MININAIL | K15: =IFERROR(__xludf.DUMMYFUNCTION("""COMPUTED_VALUE"""),0.0) -> 0 | L15: =IFERROR(__xludf.DUMMYFUNCTION("""COMPUTED_VALUE"""),3043.0) -> 3043 | M15: 6029 | O15: le di a nachito resto de Marshal y y Social club 428 sobran en EFT USD 177
E16: 46105 | F16: pago bolsas la despensa | G16: 120 | I16: =IFERROR(__xludf.DUMMYFUNCTION("""COMPUTED_VALUE"""),46072.0) -> 46072 | J16: =IFERROR(__xludf.DUMMYFUNCTION("""COMPUTED_VALUE"""),"Colo: Nachito") -> Colo: Nachito | K16: =IFERROR(__xludf.DUMMYFUNCTION("""COMPUTED_VALUE"""),694.0) -> 694 | L16: =IFERROR(__xludf.DUMMYFUNCTION("""COMPUTED_VALUE"""),0.0) -> 0 | M16: 6723 | O16: de los 177 use 120 para el pago de bolsas $187500 sobran USD 57
E17: 46111 | F17: Sixtar puffco 6 (pro proxy) 64,5kg | G17: 2451 | I17: =IFERROR(__xludf.DUMMYFUNCTION("""COMPUTED_VALUE"""),46072.0) -> 46072 | J17: =IFERROR(__xludf.DUMMYFUNCTION("""COMPUTED_VALUE"""),"Colo: Nachito") -> Colo: Nachito | K17: =IFERROR(__xludf.DUMMYFUNCTION("""COMPUTED_VALUE"""),1740.0) -> 1740 | L17: =IFERROR(__xludf.DUMMYFUNCTION("""COMPUTED_VALUE"""),0.0) -> 0 | M17: 8463 | O17: 2000 de eft de Tincho UY + 300 marshal 1-4 + 151 cambio
E18: 46114 | F18: oficina leloir (deposito 500 + honorarios 570+ alquiler 50dls (400 fueron de reserva) | G18: 1209 | I18: =IFERROR(__xludf.DUMMYFUNCTION("""COMPUTED_VALUE"""),46072.0) -> 46072 | J18: =IFERROR(__xludf.DUMMYFUNCTION("""COMPUTED_VALUE"""),"Colo: PAGO REYNOLS") -> Colo: PAGO REYNOLS | K18: =IFERROR(__xludf.DUMMYFUNCTION("""COMPUTED_VALUE"""),0.0) -> 0 | L18: =IFERROR(__xludf.DUMMYFUNCTION("""COMPUTED_VALUE"""),304.0) -> 304 | M18: 8159 | O18: 1840 de eft de Tincho sobran USD 631
E19: 46127 | F19: puffco 7 (core + hot +acc) 14kg | G19: 532 | I19: =IFERROR(__xludf.DUMMYFUNCTION("""COMPUTED_VALUE"""),46072.0) -> 46072 | J19: =IFERROR(__xludf.DUMMYFUNCTION("""COMPUTED_VALUE"""),"Colo: CARGO POR USD") -> Colo: CARGO POR USD | K19: =IFERROR(__xludf.DUMMYFUNCTION("""COMPUTED_VALUE"""),0.0) -> 0 | L19: =IFERROR(__xludf.DUMMYFUNCTION("""COMPUTED_VALUE"""),35.0) -> 35 | M19: 8124
E20: 46127 | F20: mallas press club 16,5 kg | G20: 627 | I20: =IFERROR(__xludf.DUMMYFUNCTION("""COMPUTED_VALUE"""),46072.0) -> 46072 | J20: =IFERROR(__xludf.DUMMYFUNCTION("""COMPUTED_VALUE"""),"Colo: Nachito") -> Colo: Nachito | K20: =IFERROR(__xludf.DUMMYFUNCTION("""COMPUTED_VALUE"""),5900.0) -> 5900 | L20: =IFERROR(__xludf.DUMMYFUNCTION("""COMPUTED_VALUE"""),0.0) -> 0 | M20: 14024
E21: 46128 | F21: nachito al dia | G21: 400 | I21: =IFERROR(__xludf.DUMMYFUNCTION("""COMPUTED_VALUE"""),46075.0) -> 46075 | J21: =IFERROR(__xludf.DUMMYFUNCTION("""COMPUTED_VALUE"""),"Colo: Abril Barbaria") -> Colo: Abril Barbaria | K21: =IFERROR(__xludf.DUMMYFUNCTION("""COMPUTED_VALUE"""),3001.0) -> 3001 | L21: =IFERROR(__xludf.DUMMYFUNCTION("""COMPUTED_VALUE"""),0.0) -> 0 | M21: 17025
E22: 46128 | F22: Puesta a punto oficina insumos electricidad LED | G22: 320 | I22: =IFERROR(__xludf.DUMMYFUNCTION("""COMPUTED_VALUE"""),46077.0) -> 46077 | J22: =IFERROR(__xludf.DUMMYFUNCTION("""COMPUTED_VALUE"""),"Colo: PAGO PUFCO") -> Colo: PAGO PUFCO | K22: =IFERROR(__xludf.DUMMYFUNCTION("""COMPUTED_VALUE"""),0.0) -> 0 | L22: =IFERROR(__xludf.DUMMYFUNCTION("""COMPUTED_VALUE"""),7190.0) -> 7190 | M22: 9835
E23: 46134 | F23: puffco 8 (proxy v2, pro hot | G23: 874 | I23: =IFERROR(__xludf.DUMMYFUNCTION("""COMPUTED_VALUE"""),46077.0) -> 46077 | J23: =IFERROR(__xludf.DUMMYFUNCTION("""COMPUTED_VALUE"""),"Colo: PAGO TIN UY") -> Colo: PAGO TIN UY | K23: =IFERROR(__xludf.DUMMYFUNCTION("""COMPUTED_VALUE"""),2000.0) -> 2000 | L23: =IFERROR(__xludf.DUMMYFUNCTION("""COMPUTED_VALUE"""),0.0) -> 0 | M23: 11835
E24: 46148 | F24: cortinas oficina | G24: 478 | I24: =IFERROR(__xludf.DUMMYFUNCTION("""COMPUTED_VALUE"""),46077.0) -> 46077 | J24: =IFERROR(__xludf.DUMMYFUNCTION("""COMPUTED_VALUE"""),"Colo: BUBBLE BAG") -> Colo: BUBBLE BAG | K24: =IFERROR(__xludf.DUMMYFUNCTION("""COMPUTED_VALUE"""),0.0) -> 0 | L24: =IFERROR(__xludf.DUMMYFUNCTION("""COMPUTED_VALUE"""),3243.0) -> 3243 | M24: 8592 | O24: se abono con parte de pedido de maldita tangie
E25: 46148 | F25: coca abril y mayo | G25: 485 | I25: =IFERROR(__xludf.DUMMYFUNCTION("""COMPUTED_VALUE"""),46077.0) -> 46077 | J25: =IFERROR(__xludf.DUMMYFUNCTION("""COMPUTED_VALUE"""),"Colo: Formula 420") -> Colo: Formula 420 | K25: =IFERROR(__xludf.DUMMYFUNCTION("""COMPUTED_VALUE"""),0.0) -> 0 | L25: =IFERROR(__xludf.DUMMYFUNCTION("""COMPUTED_VALUE"""),3048.0) -> 3048 | M25: 5544
E26: 46151 | F26: nachito al dia | G26: 470 | I26: =IFERROR(__xludf.DUMMYFUNCTION("""COMPUTED_VALUE"""),46077.0) -> 46077 | J26: =IFERROR(__xludf.DUMMYFUNCTION("""COMPUTED_VALUE"""),"Colo: The press club") -> Colo: The press club | K26: =IFERROR(__xludf.DUMMYFUNCTION("""COMPUTED_VALUE"""),0.0) -> 0 | L26: =IFERROR(__xludf.DUMMYFUNCTION("""COMPUTED_VALUE"""),2785.0) -> 2785 | M26: 2759
E27: 46153 | F27: Alquiler Mayo y Junio | G27: 900 | I27: =IFERROR(__xludf.DUMMYFUNCTION("""COMPUTED_VALUE"""),46077.0) -> 46077 | J27: =IFERROR(__xludf.DUMMYFUNCTION("""COMPUTED_VALUE"""),"Colo: Formula 420") -> Colo: Formula 420 | K27: =IFERROR(__xludf.DUMMYFUNCTION("""COMPUTED_VALUE"""),0.0) -> 0 | L27: =IFERROR(__xludf.DUMMYFUNCTION("""COMPUTED_VALUE"""),3572.0) -> 3572 | M27: -813
E28: 46153 | F28: expensas e impuestos ver | G28: 230 | I28: =IFERROR(__xludf.DUMMYFUNCTION("""COMPUTED_VALUE"""),46078.0) -> 46078 | J28: =IFERROR(__xludf.DUMMYFUNCTION("""COMPUTED_VALUE"""),"Colo: Rodrigo Orellano") -> Colo: Rodrigo Orellano | K28: =IFERROR(__xludf.DUMMYFUNCTION("""COMPUTED_VALUE"""),1481.0) -> 1481 | L28: =IFERROR(__xludf.DUMMYFUNCTION("""COMPUTED_VALUE"""),0.0) -> 0 | M28: 668
E29: 46157 | F29: puffco 9 reestoc 46kg | G29: 1748 | I29: =IFERROR(__xludf.DUMMYFUNCTION("""COMPUTED_VALUE"""),46080.0) -> 46080 | J29: =IFERROR(__xludf.DUMMYFUNCTION("""COMPUTED_VALUE"""),"Gasto: Sixstar Puffco 3") -> Gasto: Sixstar Puffco 3 | K29: =IFERROR(__xludf.DUMMYFUNCTION("""COMPUTED_VALUE"""),0.0) -> 0 | L29: =IFERROR(__xludf.DUMMYFUNCTION("""COMPUTED_VALUE"""),1216.0) -> 1216 | M29: -548
E30: 46161 | F30: puffco 10 producto nuevo 93kg | G30: 3534 | I30: =IFERROR(__xludf.DUMMYFUNCTION("""COMPUTED_VALUE"""),46080.0) -> 46080 | J30: =IFERROR(__xludf.DUMMYFUNCTION("""COMPUTED_VALUE"""),"Colo: Nuñez Agustin") -> Colo: Nuñez Agustin | K30: =IFERROR(__xludf.DUMMYFUNCTION("""COMPUTED_VALUE"""),609.0) -> 609 | L30: =IFERROR(__xludf.DUMMYFUNCTION("""COMPUTED_VALUE"""),0.0) -> 0 | M30: 61
E31: 46176 | F31: retirar holanda 134kg + 57kg vol | G31: 6720 | I31: =IFERROR(__xludf.DUMMYFUNCTION("""COMPUTED_VALUE"""),46083.0) -> 46083 | J31: =IFERROR(__xludf.DUMMYFUNCTION("""COMPUTED_VALUE"""),"Gasto: Sixstar MJ ARSENAL") -> Gasto: Sixstar MJ ARSENAL | K31: =IFERROR(__xludf.DUMMYFUNCTION("""COMPUTED_VALUE"""),0.0) -> 0 | L31: =IFERROR(__xludf.DUMMYFUNCTION("""COMPUTED_VALUE"""),532.0) -> 532 | M31: -471
E32: 46181 | F32: MJA vidrios 3 usa 23kg | G32: 874 | I32: =IFERROR(__xludf.DUMMYFUNCTION("""COMPUTED_VALUE"""),46086.0) -> 46086 | J32: =IFERROR(__xludf.DUMMYFUNCTION("""COMPUTED_VALUE"""),"Gasto: Nacho") -> Gasto: Nacho | K32: =IFERROR(__xludf.DUMMYFUNCTION("""COMPUTED_VALUE"""),0.0) -> 0 | L32: =IFERROR(__xludf.DUMMYFUNCTION("""COMPUTED_VALUE"""),282.69) -> 282.69 | M32: -753.69
E33: 46182 | F33: puffco 11 pivot knife 27,5 | G33: 1045 | I33: =IFERROR(__xludf.DUMMYFUNCTION("""COMPUTED_VALUE"""),46086.0) -> 46086 | J33: =IFERROR(__xludf.DUMMYFUNCTION("""COMPUTED_VALUE"""),"Gasto: Coca") -> Gasto: Coca | K33: =IFERROR(__xludf.DUMMYFUNCTION("""COMPUTED_VALUE"""),0.0) -> 0 | L33: =IFERROR(__xludf.DUMMYFUNCTION("""COMPUTED_VALUE"""),240.28) -> 240.28 | M33: -993.97
E34: 46191 | F34: edenor, municipal ofi | G34: 200 | I34: =IFERROR(__xludf.DUMMYFUNCTION("""COMPUTED_VALUE"""),46087.0) -> 46087 | J34: =IFERROR(__xludf.DUMMYFUNCTION("""COMPUTED_VALUE"""),"Colo: Barbaria Abril") -> Colo: Barbaria Abril | K34: =IFERROR(__xludf.DUMMYFUNCTION("""COMPUTED_VALUE"""),1786.0) -> 1786 | L34: =IFERROR(__xludf.DUMMYFUNCTION("""COMPUTED_VALUE"""),0.0) -> 0 | M34: 792.03
E35: 46192 | F35: coca junio | G35: 235 | I35: =IFERROR(__xludf.DUMMYFUNCTION("""COMPUTED_VALUE"""),46090.0) -> 46090 | J35: =IFERROR(__xludf.DUMMYFUNCTION("""COMPUTED_VALUE"""),"Gasto: Sixstar Mininail/bubble") -> Gasto: Sixstar Mininail/bubble | K35: =IFERROR(__xludf.DUMMYFUNCTION("""COMPUTED_VALUE"""),0.0) -> 0 | L35: =IFERROR(__xludf.DUMMYFUNCTION("""COMPUTED_VALUE"""),4750.0) -> 4750 | M35: -3957.97
E36: 46192 | F36: nachito | G36: 340 | I36: =IFERROR(__xludf.DUMMYFUNCTION("""COMPUTED_VALUE"""),46091.0) -> 46091 | J36: =IFERROR(__xludf.DUMMYFUNCTION("""COMPUTED_VALUE"""),"Gasto: Sixstar puffco 4") -> Gasto: Sixstar puffco 4 | K36: =IFERROR(__xludf.DUMMYFUNCTION("""COMPUTED_VALUE"""),0.0) -> 0 | L36: =IFERROR(__xludf.DUMMYFUNCTION("""COMPUTED_VALUE"""),2546.0) -> 2546 | M36: -6503.97
E37: 46202 | F37: puffco 12 71kg | G37: 2698 | I37: =IFERROR(__xludf.DUMMYFUNCTION("""COMPUTED_VALUE"""),46093.0) -> 46093 | J37: =IFERROR(__xludf.DUMMYFUNCTION("""COMPUTED_VALUE"""),"Colo: Nachito") -> Colo: Nachito | K37: =IFERROR(__xludf.DUMMYFUNCTION("""COMPUTED_VALUE"""),3680.0) -> 3680 | L37: =IFERROR(__xludf.DUMMYFUNCTION("""COMPUTED_VALUE"""),0.0) -> 0 | M37: -2823.97
E38: 46205 | F38: bolsas la despensa | G38: 240 | I38: =IFERROR(__xludf.DUMMYFUNCTION("""COMPUTED_VALUE"""),46094.0) -> 46094 | J38: =IFERROR(__xludf.DUMMYFUNCTION("""COMPUTED_VALUE"""),"Gasto: Sistar puffco 5 (proxy core)") -> Gasto: Sistar puffco 5 (proxy core) | K38: =IFERROR(__xludf.DUMMYFUNCTION("""COMPUTED_VALUE"""),0.0) -> 0 | L38: =IFERROR(__xludf.DUMMYFUNCTION("""COMPUTED_VALUE"""),1140.0) -> 1140 | M38: -3963.97
E39: 46213 | F39: nacho al dia | G39: 300 | I39: =IFERROR(__xludf.DUMMYFUNCTION("""COMPUTED_VALUE"""),46097.0) -> 46097 | J39: =IFERROR(__xludf.DUMMYFUNCTION("""COMPUTED_VALUE"""),"Colo: Carranza Alejandro") -> Colo: Carranza Alejandro | K39: =IFERROR(__xludf.DUMMYFUNCTION("""COMPUTED_VALUE"""),3215.0) -> 3215 | L39: =IFERROR(__xludf.DUMMYFUNCTION("""COMPUTED_VALUE"""),0.0) -> 0 | M39: -748.97
E40: 46216 | F40: alquiler Julio y aogsto | G40: 900 | I40: =IFERROR(__xludf.DUMMYFUNCTION("""COMPUTED_VALUE"""),46098.0) -> 46098 | J40: =IFERROR(__xludf.DUMMYFUNCTION("""COMPUTED_VALUE"""),"Colo: PAGO PUFCO") -> Colo: PAGO PUFCO | K40: =IFERROR(__xludf.DUMMYFUNCTION("""COMPUTED_VALUE"""),0.0) -> 0 | L40: =IFERROR(__xludf.DUMMYFUNCTION("""COMPUTED_VALUE"""),5175.0) -> 5175 | M40: -5923.97 | O40: 600 de guille naesa + 300 nahu la comarca
E41: 46219 | F41: coca | G41: 235 | I41: =IFERROR(__xludf.DUMMYFUNCTION("""COMPUTED_VALUE"""),46098.0) -> 46098 | J41: =IFERROR(__xludf.DUMMYFUNCTION("""COMPUTED_VALUE"""),"Colo: VANDERVERG") -> Colo: VANDERVERG | K41: =IFERROR(__xludf.DUMMYFUNCTION("""COMPUTED_VALUE"""),0.0) -> 0 | L41: =IFERROR(__xludf.DUMMYFUNCTION("""COMPUTED_VALUE"""),13665.0) -> 13665 | M41: -19588.97
E42: 46219 | F42: expensas e impuestos luz caldera cochera | G42: 560 | I42: =IFERROR(__xludf.DUMMYFUNCTION("""COMPUTED_VALUE"""),46099.0) -> 46099 | J42: =IFERROR(__xludf.DUMMYFUNCTION("""COMPUTED_VALUE"""),"Gasto: nachito al dia") -> Gasto: nachito al dia | K42: =IFERROR(__xludf.DUMMYFUNCTION("""COMPUTED_VALUE"""),0.0) -> 0 | L42: =IFERROR(__xludf.DUMMYFUNCTION("""COMPUTED_VALUE"""),418.0) -> 418 | M42: -20006.97
E43: 46220 | F43: Pines fundido en bronce LA DESPENSA (para expo cannabis) 500 uni | G43: 650 | I43: =IFERROR(__xludf.DUMMYFUNCTION("""COMPUTED_VALUE"""),46100.0) -> 46100 | J43: =IFERROR(__xludf.DUMMYFUNCTION("""COMPUTED_VALUE"""),"Gasto: reserva oficina Leloir") -> Gasto: reserva oficina Leloir | K43: =IFERROR(__xludf.DUMMYFUNCTION("""COMPUTED_VALUE"""),0.0) -> 0 | L43: =IFERROR(__xludf.DUMMYFUNCTION("""COMPUTED_VALUE"""),400.0) -> 400 | M43: -20406.97
E44: 46220 | F44: remeras LA DESPENSA expo cannabis 30 unidades | G44: 550 | I44: =IFERROR(__xludf.DUMMYFUNCTION("""COMPUTED_VALUE"""),46100.0) -> 46100 | J44: =IFERROR(__xludf.DUMMYFUNCTION("""COMPUTED_VALUE"""),"Colo: Aquino Ignacio") -> Colo: Aquino Ignacio | K44: =IFERROR(__xludf.DUMMYFUNCTION("""COMPUTED_VALUE"""),6946.0) -> 6946 | L44: =IFERROR(__xludf.DUMMYFUNCTION("""COMPUTED_VALUE"""),0.0) -> 0 | M44: -13460.97
E45: 46221 | F45: nacho al dia | G45: 200 | I45: =IFERROR(__xludf.DUMMYFUNCTION("""COMPUTED_VALUE"""),46101.0) -> 46101 | J45: =IFERROR(__xludf.DUMMYFUNCTION("""COMPUTED_VALUE"""),"Gasto: Sixstar MJ ARSENAL 2 29kg") -> Gasto: Sixstar MJ ARSENAL 2 29kg | K45: =IFERROR(__xludf.DUMMYFUNCTION("""COMPUTED_VALUE"""),0.0) -> 0 | L45: =IFERROR(__xludf.DUMMYFUNCTION("""COMPUTED_VALUE"""),1102.0) -> 1102 | M45: -14562.97
E46: 46223 | F46: puffco 13 + medusa 150kg | G46: 5700 | I46: =IFERROR(__xludf.DUMMYFUNCTION("""COMPUTED_VALUE"""),46105.0) -> 46105 | J46: =IFERROR(__xludf.DUMMYFUNCTION("""COMPUTED_VALUE"""),"Gasto: pago bolsas la despensa") -> Gasto: pago bolsas la despensa | K46: =IFERROR(__xludf.DUMMYFUNCTION("""COMPUTED_VALUE"""),0.0) -> 0 | L46: =IFERROR(__xludf.DUMMYFUNCTION("""COMPUTED_VALUE"""),120.0) -> 120 | M46: -14682.97
E47: 46226 | F47: puffco 14 + resto de medusa 95kg | G47: 3610 | I47: =IFERROR(__xludf.DUMMYFUNCTION("""COMPUTED_VALUE"""),46105.0) -> 46105 | J47: =IFERROR(__xludf.DUMMYFUNCTION("""COMPUTED_VALUE"""),"Colo: Farias Sergio") -> Colo: Farias Sergio | K47: =IFERROR(__xludf.DUMMYFUNCTION("""COMPUTED_VALUE"""),1378.0) -> 1378 | L47: =IFERROR(__xludf.DUMMYFUNCTION("""COMPUTED_VALUE"""),0.0) -> 0 | M47: -13304.97
E48: 46246 | F48: puffco 15 | G48: 2394 | I48: =IFERROR(__xludf.DUMMYFUNCTION("""COMPUTED_VALUE"""),46106.0) -> 46106 | J48: =IFERROR(__xludf.DUMMYFUNCTION("""COMPUTED_VALUE"""),"Colo: Nachito") -> Colo: Nachito | K48: =IFERROR(__xludf.DUMMYFUNCTION("""COMPUTED_VALUE"""),7000.0) -> 7000 | L48: =IFERROR(__xludf.DUMMYFUNCTION("""COMPUTED_VALUE"""),0.0) -> 0 | M48: -6304.97
E49: 46246 | F49: coca | G49: 235 | I49: =IFERROR(__xludf.DUMMYFUNCTION("""COMPUTED_VALUE"""),46108.0) -> 46108 | J49: =IFERROR(__xludf.DUMMYFUNCTION("""COMPUTED_VALUE"""),"Colo: ") -> Colo: | K49: =IFERROR(__xludf.DUMMYFUNCTION("""COMPUTED_VALUE"""),2399.0) -> 2399 | L49: =IFERROR(__xludf.DUMMYFUNCTION("""COMPUTED_VALUE"""),0.0) -> 0 | M49: -3905.97
E50: 46246 | F50: nachito al dia | G50: 360 | I50: =IFERROR(__xludf.DUMMYFUNCTION("""COMPUTED_VALUE"""),46111.0) -> 46111 | J50: =IFERROR(__xludf.DUMMYFUNCTION("""COMPUTED_VALUE"""),"Gasto: Sixtar puffco 6 (pro proxy) 64,5kg") -> Gasto: Sixtar puffco 6 (pro proxy) 64,5kg | K50: =IFERROR(__xludf.DUMMYFUNCTION("""COMPUTED_VALUE"""),0.0) -> 0 | L50: =IFERROR(__xludf.DUMMYFUNCTION("""COMPUTED_VALUE"""),2451.0) -> 2451 | M50: -6356.97
E51: 46253 | F51: vidrios 43kg | G51: 1634 | I51: =IFERROR(__xludf.DUMMYFUNCTION("""COMPUTED_VALUE"""),46111.0) -> 46111 | J51: =IFERROR(__xludf.DUMMYFUNCTION("""COMPUTED_VALUE"""),"Colo: PUFFCO") -> Colo: PUFFCO | K51: =IFERROR(__xludf.DUMMYFUNCTION("""COMPUTED_VALUE"""),0.0) -> 0 | L51: =IFERROR(__xludf.DUMMYFUNCTION("""COMPUTED_VALUE"""),15450.0) -> 15450 | M51: -21806.97
E52: 46261 | F52: puffco 2 cargas juntas 16/17 193 | G52: 7394 | I52: =IFERROR(__xludf.DUMMYFUNCTION("""COMPUTED_VALUE"""),46114.0) -> 46114 | J52: =IFERROR(__xludf.DUMMYFUNCTION("""COMPUTED_VALUE"""),"Gasto: oficina leloir (deposito 500 + honorarios 570+ alquiler 50dls (400 fueron de reserva)") -> Gasto: oficina leloir (deposito 500 + honorarios 570+ alquiler 50dls (400 fueron de reserva) | K52: =IFERROR(__xludf.DUMMYFUNCTION("""COMPUTED_VALUE"""),0.0) -> 0 | L52: =IFERROR(__xludf.DUMMYFUNCTION("""COMPUTED_VALUE"""),1209.0) -> 1209 | M52: -23015.97
E53: 46266 | F53: medusa 110 kg | G53: 4180 | I53: =IFERROR(__xludf.DUMMYFUNCTION("""COMPUTED_VALUE"""),46115.0) -> 46115 | J53: =IFERROR(__xludf.DUMMYFUNCTION("""COMPUTED_VALUE"""),"Colo: Nuñez Lucas") -> Colo: Nuñez Lucas | K53: =IFERROR(__xludf.DUMMYFUNCTION("""COMPUTED_VALUE"""),4003.0) -> 4003 | L53: =IFERROR(__xludf.DUMMYFUNCTION("""COMPUTED_VALUE"""),0.0) -> 0 | M53: -19012.97
E54: 46267 | F54: estantes x 3 | G54: 300 | I54: =IFERROR(__xludf.DUMMYFUNCTION("""COMPUTED_VALUE"""),46122.0) -> 46122 | J54: =IFERROR(__xludf.DUMMYFUNCTION("""COMPUTED_VALUE"""),"Colo: ") -> Colo: | K54: =IFERROR(__xludf.DUMMYFUNCTION("""COMPUTED_VALUE"""),2049.0) -> 2049 | L54: =IFERROR(__xludf.DUMMYFUNCTION("""COMPUTED_VALUE"""),0.0) -> 0 | M54: -16963.97
E55: 46267 | F55: nachito al dia | G55: 500 | I55: =IFERROR(__xludf.DUMMYFUNCTION("""COMPUTED_VALUE"""),46127.0) -> 46127 | J55: =IFERROR(__xludf.DUMMYFUNCTION("""COMPUTED_VALUE"""),"Gasto: puffco 7 (core + hot +acc) 14kg") -> Gasto: puffco 7 (core + hot +acc) 14kg | K55: =IFERROR(__xludf.DUMMYFUNCTION("""COMPUTED_VALUE"""),0.0) -> 0 | L55: =IFERROR(__xludf.DUMMYFUNCTION("""COMPUTED_VALUE"""),532.0) -> 532 | M55: -17495.97
E56: 46268 | F56: alquiler sep y octubre 2026 | G56: 900 | I56: =IFERROR(__xludf.DUMMYFUNCTION("""COMPUTED_VALUE"""),46127.0) -> 46127 | J56: =IFERROR(__xludf.DUMMYFUNCTION("""COMPUTED_VALUE"""),"Gasto: mallas press club 16,5 kg") -> Gasto: mallas press club 16,5 kg | K56: =IFERROR(__xludf.DUMMYFUNCTION("""COMPUTED_VALUE"""),0.0) -> 0 | L56: =IFERROR(__xludf.DUMMYFUNCTION("""COMPUTED_VALUE"""),627.0) -> 627 | M56: -18122.97
E57: 46269 | F57: mueble de vidrio y repisas led | G57: 800 | I57: =IFERROR(__xludf.DUMMYFUNCTION("""COMPUTED_VALUE"""),46128.0) -> 46128 | J57: =IFERROR(__xludf.DUMMYFUNCTION("""COMPUTED_VALUE"""),"Gasto: nachito al dia") -> Gasto: nachito al dia | K57: =IFERROR(__xludf.DUMMYFUNCTION("""COMPUTED_VALUE"""),0.0) -> 0 | L57: =IFERROR(__xludf.DUMMYFUNCTION("""COMPUTED_VALUE"""),400.0) -> 400 | M57: -18522.97
E58: 46280 | F58: coca | G58: 235 | I58: =IFERROR(__xludf.DUMMYFUNCTION("""COMPUTED_VALUE"""),46128.0) -> 46128 | J58: =IFERROR(__xludf.DUMMYFUNCTION("""COMPUTED_VALUE"""),"Gasto: Puesta a punto oficina insumos electricidad LED") -> Gasto: Puesta a punto oficina insumos electricidad LED | K58: =IFERROR(__xludf.DUMMYFUNCTION("""COMPUTED_VALUE"""),0.0) -> 0 | L58: =IFERROR(__xludf.DUMMYFUNCTION("""COMPUTED_VALUE"""),320.0) -> 320 | M58: -18842.97
E59: 46280 | F59: nachito | G59: 250 | I59: =IFERROR(__xludf.DUMMYFUNCTION("""COMPUTED_VALUE"""),46128.0) -> 46128 | J59: =IFERROR(__xludf.DUMMYFUNCTION("""COMPUTED_VALUE"""),"Colo: Quilaleo Nicolas") -> Colo: Quilaleo Nicolas | K59: =IFERROR(__xludf.DUMMYFUNCTION("""COMPUTED_VALUE"""),2516.0) -> 2516 | L59: =IFERROR(__xludf.DUMMYFUNCTION("""COMPUTED_VALUE"""),0.0) -> 0 | M59: -16326.97
E60: 46281 | F60: expensas | G60: 80 | I60: =IFERROR(__xludf.DUMMYFUNCTION("""COMPUTED_VALUE"""),46134.0) -> 46134 | J60: =IFERROR(__xludf.DUMMYFUNCTION("""COMPUTED_VALUE"""),"Gasto: puffco 8 (proxy v2, pro hot") -> Gasto: puffco 8 (proxy v2, pro hot | K60: =IFERROR(__xludf.DUMMYFUNCTION("""COMPUTED_VALUE"""),0.0) -> 0 | L60: =IFERROR(__xludf.DUMMYFUNCTION("""COMPUTED_VALUE"""),874.0) -> 874 | M60: -17200.97
E61: 46295 | F61: dab rite 21kg medidor de temperatura termometro infrarojo | G61: 803 | I61: =IFERROR(__xludf.DUMMYFUNCTION("""COMPUTED_VALUE"""),46135.0) -> 46135 | J61: =IFERROR(__xludf.DUMMYFUNCTION("""COMPUTED_VALUE"""),"Colo: ") -> Colo: | K61: =IFERROR(__xludf.DUMMYFUNCTION("""COMPUTED_VALUE"""),2888.0) -> 2888 | L61: =IFERROR(__xludf.DUMMYFUNCTION("""COMPUTED_VALUE"""),0.0) -> 0 | M61: -14312.97
I62: =IFERROR(__xludf.DUMMYFUNCTION("""COMPUTED_VALUE"""),46136.0) -> 46136 | J62: =IFERROR(__xludf.DUMMYFUNCTION("""COMPUTED_VALUE"""),"Colo: PUFFCO") -> Colo: PUFFCO | K62: =IFERROR(__xludf.DUMMYFUNCTION("""COMPUTED_VALUE"""),0.0) -> 0 | L62: =IFERROR(__xludf.DUMMYFUNCTION("""COMPUTED_VALUE"""),7400.0) -> 7400 | M62: -21712.97
I63: =IFERROR(__xludf.DUMMYFUNCTION("""COMPUTED_VALUE"""),46139.0) -> 46139 | J63: =IFERROR(__xludf.DUMMYFUNCTION("""COMPUTED_VALUE"""),"Colo: Nachito") -> Colo: Nachito | K63: =IFERROR(__xludf.DUMMYFUNCTION("""COMPUTED_VALUE"""),4950.0) -> 4950 | L63: =IFERROR(__xludf.DUMMYFUNCTION("""COMPUTED_VALUE"""),0.0) -> 0 | M63: -16762.97
I64: =IFERROR(__xludf.DUMMYFUNCTION("""COMPUTED_VALUE"""),46146.0) -> 46146 | J64: =IFERROR(__xludf.DUMMYFUNCTION("""COMPUTED_VALUE"""),"Colo: PUFFCO") -> Colo: PUFFCO | K64: =IFERROR(__xludf.DUMMYFUNCTION("""COMPUTED_VALUE"""),0.0) -> 0 | L64: =IFERROR(__xludf.DUMMYFUNCTION("""COMPUTED_VALUE"""),8350.0) -> 8350 | M64: -25112.97
I65: =IFERROR(__xludf.DUMMYFUNCTION("""COMPUTED_VALUE"""),46147.0) -> 46147 | J65: =IFERROR(__xludf.DUMMYFUNCTION("""COMPUTED_VALUE"""),"Colo: Singlau Leandro") -> Colo: Singlau Leandro | K65: =IFERROR(__xludf.DUMMYFUNCTION("""COMPUTED_VALUE"""),1490.0) -> 1490 | L65: =IFERROR(__xludf.DUMMYFUNCTION("""COMPUTED_VALUE"""),0.0) -> 0 | M65: -23622.97
I66: =IFERROR(__xludf.DUMMYFUNCTION("""COMPUTED_VALUE"""),46148.0) -> 46148 | J66: =IFERROR(__xludf.DUMMYFUNCTION("""COMPUTED_VALUE"""),"Gasto: cortinas oficina") -> Gasto: cortinas oficina | K66: =IFERROR(__xludf.DUMMYFUNCTION("""COMPUTED_VALUE"""),0.0) -> 0 | L66: =IFERROR(__xludf.DUMMYFUNCTION("""COMPUTED_VALUE"""),478.0) -> 478 | M66: -24100.97
I67: =IFERROR(__xludf.DUMMYFUNCTION("""COMPUTED_VALUE"""),46148.0) -> 46148 | J67: =IFERROR(__xludf.DUMMYFUNCTION("""COMPUTED_VALUE"""),"Gasto: coca abril y mayo") -> Gasto: coca abril y mayo | K67: =IFERROR(__xludf.DUMMYFUNCTION("""COMPUTED_VALUE"""),0.0) -> 0 | L67: =IFERROR(__xludf.DUMMYFUNCTION("""COMPUTED_VALUE"""),485.0) -> 485 | M67: -24585.97
I68: =IFERROR(__xludf.DUMMYFUNCTION("""COMPUTED_VALUE"""),46148.0) -> 46148 | J68: =IFERROR(__xludf.DUMMYFUNCTION("""COMPUTED_VALUE"""),"Colo: Brusco Emiliano") -> Colo: Brusco Emiliano | K68: =IFERROR(__xludf.DUMMYFUNCTION("""COMPUTED_VALUE"""),12264.0) -> 12264 | L68: =IFERROR(__xludf.DUMMYFUNCTION("""COMPUTED_VALUE"""),0.0) -> 0 | M68: -12321.97
I69: =IFERROR(__xludf.DUMMYFUNCTION("""COMPUTED_VALUE"""),46150.0) -> 46150 | J69: =IFERROR(__xludf.DUMMYFUNCTION("""COMPUTED_VALUE"""),"Colo: PUFFCO") -> Colo: PUFFCO | K69: =IFERROR(__xludf.DUMMYFUNCTION("""COMPUTED_VALUE"""),0.0) -> 0 | L69: =IFERROR(__xludf.DUMMYFUNCTION("""COMPUTED_VALUE"""),5175.0) -> 5175 | M69: -17496.97
I70: =IFERROR(__xludf.DUMMYFUNCTION("""COMPUTED_VALUE"""),46150.0) -> 46150 | J70: =IFERROR(__xludf.DUMMYFUNCTION("""COMPUTED_VALUE"""),"Colo: MEDUSA") -> Colo: MEDUSA | K70: =IFERROR(__xludf.DUMMYFUNCTION("""COMPUTED_VALUE"""),0.0) -> 0 | L70: =IFERROR(__xludf.DUMMYFUNCTION("""COMPUTED_VALUE"""),2778.0) -> 2778 | M70: -20274.97
I71: =IFERROR(__xludf.DUMMYFUNCTION("""COMPUTED_VALUE"""),46151.0) -> 46151 | J71: =IFERROR(__xludf.DUMMYFUNCTION("""COMPUTED_VALUE"""),"Gasto: nachito al dia") -> Gasto: nachito al dia | K71: =IFERROR(__xludf.DUMMYFUNCTION("""COMPUTED_VALUE"""),0.0) -> 0 | L71: =IFERROR(__xludf.DUMMYFUNCTION("""COMPUTED_VALUE"""),470.0) -> 470 | M71: -20744.97
I72: =IFERROR(__xludf.DUMMYFUNCTION("""COMPUTED_VALUE"""),46153.0) -> 46153 | J72: =IFERROR(__xludf.DUMMYFUNCTION("""COMPUTED_VALUE"""),"Gasto: Alquiler Mayo y Junio") -> Gasto: Alquiler Mayo y Junio | K72: =IFERROR(__xludf.DUMMYFUNCTION("""COMPUTED_VALUE"""),0.0) -> 0 | L72: =IFERROR(__xludf.DUMMYFUNCTION("""COMPUTED_VALUE"""),900.0) -> 900 | M72: -21644.97
I73: =IFERROR(__xludf.DUMMYFUNCTION("""COMPUTED_VALUE"""),46153.0) -> 46153 | J73: =IFERROR(__xludf.DUMMYFUNCTION("""COMPUTED_VALUE"""),"Gasto: expensas e impuestos ver") -> Gasto: expensas e impuestos ver | K73: =IFERROR(__xludf.DUMMYFUNCTION("""COMPUTED_VALUE"""),0.0) -> 0 | L73: =IFERROR(__xludf.DUMMYFUNCTION("""COMPUTED_VALUE"""),230.0) -> 230 | M73: -21874.97
I74: =IFERROR(__xludf.DUMMYFUNCTION("""COMPUTED_VALUE"""),46153.0) -> 46153 | J74: =IFERROR(__xludf.DUMMYFUNCTION("""COMPUTED_VALUE"""),"Colo: PUFFCO") -> Colo: PUFFCO | K74: =IFERROR(__xludf.DUMMYFUNCTION("""COMPUTED_VALUE"""),0.0) -> 0 | L74: =IFERROR(__xludf.DUMMYFUNCTION("""COMPUTED_VALUE"""),5175.0) -> 5175 | M74: -27049.97
I75: =IFERROR(__xludf.DUMMYFUNCTION("""COMPUTED_VALUE"""),46154.0) -> 46154 | J75: =IFERROR(__xludf.DUMMYFUNCTION("""COMPUTED_VALUE"""),"Colo: ") -> Colo: | K75: =IFERROR(__xludf.DUMMYFUNCTION("""COMPUTED_VALUE"""),4668.0) -> 4668 | L75: =IFERROR(__xludf.DUMMYFUNCTION("""COMPUTED_VALUE"""),0.0) -> 0 | M75: -22381.97
I76: =IFERROR(__xludf.DUMMYFUNCTION("""COMPUTED_VALUE"""),46157.0) -> 46157 | J76: =IFERROR(__xludf.DUMMYFUNCTION("""COMPUTED_VALUE"""),"Gasto: puffco 9 reestoc 46kg") -> Gasto: puffco 9 reestoc 46kg | K76: =IFERROR(__xludf.DUMMYFUNCTION("""COMPUTED_VALUE"""),0.0) -> 0 | L76: =IFERROR(__xludf.DUMMYFUNCTION("""COMPUTED_VALUE"""),1748.0) -> 1748 | M76: -24129.97
I77: =IFERROR(__xludf.DUMMYFUNCTION("""COMPUTED_VALUE"""),46160.0) -> 46160 | J77: =IFERROR(__xludf.DUMMYFUNCTION("""COMPUTED_VALUE"""),"Colo: Russo Lucas") -> Colo: Russo Lucas | K77: =IFERROR(__xludf.DUMMYFUNCTION("""COMPUTED_VALUE"""),2274.0) -> 2274 | L77: =IFERROR(__xludf.DUMMYFUNCTION("""COMPUTED_VALUE"""),0.0) -> 0 | M77: -21855.97
I78: =IFERROR(__xludf.DUMMYFUNCTION("""COMPUTED_VALUE"""),46161.0) -> 46161 | J78: =IFERROR(__xludf.DUMMYFUNCTION("""COMPUTED_VALUE"""),"Gasto: puffco 10 producto nuevo 93kg") -> Gasto: puffco 10 producto nuevo 93kg | K78: =IFERROR(__xludf.DUMMYFUNCTION("""COMPUTED_VALUE"""),0.0) -> 0 | L78: =IFERROR(__xludf.DUMMYFUNCTION("""COMPUTED_VALUE"""),3534.0) -> 3534 | M78: -25389.97
I79: =IFERROR(__xludf.DUMMYFUNCTION("""COMPUTED_VALUE"""),46162.0) -> 46162 | J79: =IFERROR(__xludf.DUMMYFUNCTION("""COMPUTED_VALUE"""),"Colo: Mendoza Matias") -> Colo: Mendoza Matias | K79: =IFERROR(__xludf.DUMMYFUNCTION("""COMPUTED_VALUE"""),1248.0) -> 1248 | L79: =IFERROR(__xludf.DUMMYFUNCTION("""COMPUTED_VALUE"""),0.0) -> 0 | M79: -24141.97
I80: =IFERROR(__xludf.DUMMYFUNCTION("""COMPUTED_VALUE"""),46167.0) -> 46167 | J80: =IFERROR(__xludf.DUMMYFUNCTION("""COMPUTED_VALUE"""),"Colo: Nuñe Agustin") -> Colo: Nuñe Agustin | K80: =IFERROR(__xludf.DUMMYFUNCTION("""COMPUTED_VALUE"""),2792.0) -> 2792 | L80: =IFERROR(__xludf.DUMMYFUNCTION("""COMPUTED_VALUE"""),0.0) -> 0 | M80: -21349.97
I81: =IFERROR(__xludf.DUMMYFUNCTION("""COMPUTED_VALUE"""),46170.0) -> 46170 | J81: =IFERROR(__xludf.DUMMYFUNCTION("""COMPUTED_VALUE"""),"Colo: Greheb") -> Colo: Greheb | K81: =IFERROR(__xludf.DUMMYFUNCTION("""COMPUTED_VALUE"""),5010.0) -> 5010 | L81: =IFERROR(__xludf.DUMMYFUNCTION("""COMPUTED_VALUE"""),0.0) -> 0 | M81: -16339.97
I82: =IFERROR(__xludf.DUMMYFUNCTION("""COMPUTED_VALUE"""),46174.0) -> 46174 | J82: =IFERROR(__xludf.DUMMYFUNCTION("""COMPUTED_VALUE"""),"Colo: Nuñez Lucas") -> Colo: Nuñez Lucas | K82: =IFERROR(__xludf.DUMMYFUNCTION("""COMPUTED_VALUE"""),3284.0) -> 3284 | L82: =IFERROR(__xludf.DUMMYFUNCTION("""COMPUTED_VALUE"""),0.0) -> 0 | M82: -13055.97
I83: =IFERROR(__xludf.DUMMYFUNCTION("""COMPUTED_VALUE"""),46175.0) -> 46175 | J83: =IFERROR(__xludf.DUMMYFUNCTION("""COMPUTED_VALUE"""),"Colo: PUFFCO") -> Colo: PUFFCO | K83: =IFERROR(__xludf.DUMMYFUNCTION("""COMPUTED_VALUE"""),0.0) -> 0 | L83: =IFERROR(__xludf.DUMMYFUNCTION("""COMPUTED_VALUE"""),17510.0) -> 17510 | M83: -30565.97
I84: =IFERROR(__xludf.DUMMYFUNCTION("""COMPUTED_VALUE"""),46176.0) -> 46176 | J84: =IFERROR(__xludf.DUMMYFUNCTION("""COMPUTED_VALUE"""),"Gasto: retirar holanda 134kg + 57kg vol") -> Gasto: retirar holanda 134kg + 57kg vol | K84: =IFERROR(__xludf.DUMMYFUNCTION("""COMPUTED_VALUE"""),0.0) -> 0 | L84: =IFERROR(__xludf.DUMMYFUNCTION("""COMPUTED_VALUE"""),6720.0) -> 6720 | M84: -37285.97
I85: =IFERROR(__xludf.DUMMYFUNCTION("""COMPUTED_VALUE"""),46176.0) -> 46176 | J85: =IFERROR(__xludf.DUMMYFUNCTION("""COMPUTED_VALUE"""),"Colo: Morrone Dante") -> Colo: Morrone Dante | K85: =IFERROR(__xludf.DUMMYFUNCTION("""COMPUTED_VALUE"""),657.38) -> 657.38 | L85: =IFERROR(__xludf.DUMMYFUNCTION("""COMPUTED_VALUE"""),0.0) -> 0 | M85: -36628.59
I86: =IFERROR(__xludf.DUMMYFUNCTION("""COMPUTED_VALUE"""),46181.0) -> 46181 | J86: =IFERROR(__xludf.DUMMYFUNCTION("""COMPUTED_VALUE"""),"Gasto: MJA vidrios 3 usa 23kg") -> Gasto: MJA vidrios 3 usa 23kg | K86: =IFERROR(__xludf.DUMMYFUNCTION("""COMPUTED_VALUE"""),0.0) -> 0 | L86: =IFERROR(__xludf.DUMMYFUNCTION("""COMPUTED_VALUE"""),874.0) -> 874 | M86: -37502.59
I87: =IFERROR(__xludf.DUMMYFUNCTION("""COMPUTED_VALUE"""),46181.0) -> 46181 | J87: =IFERROR(__xludf.DUMMYFUNCTION("""COMPUTED_VALUE"""),"Colo: Gonzalez Jeremias") -> Colo: Gonzalez Jeremias | K87: =IFERROR(__xludf.DUMMYFUNCTION("""COMPUTED_VALUE"""),2344.97) -> 2344.97 | L87: =IFERROR(__xludf.DUMMYFUNCTION("""COMPUTED_VALUE"""),0.0) -> 0 | M87: -35157.62
I88: =IFERROR(__xludf.DUMMYFUNCTION("""COMPUTED_VALUE"""),46182.0) -> 46182 | J88: =IFERROR(__xludf.DUMMYFUNCTION("""COMPUTED_VALUE"""),"Gasto: puffco 11 pivot knife 27,5") -> Gasto: puffco 11 pivot knife 27,5 | K88: =IFERROR(__xludf.DUMMYFUNCTION("""COMPUTED_VALUE"""),0.0) -> 0 | L88: =IFERROR(__xludf.DUMMYFUNCTION("""COMPUTED_VALUE"""),1045.0) -> 1045 | M88: -36202.62
I89: =IFERROR(__xludf.DUMMYFUNCTION("""COMPUTED_VALUE"""),46183.0) -> 46183 | J89: =IFERROR(__xludf.DUMMYFUNCTION("""COMPUTED_VALUE"""),"Colo: Yensen Salvador") -> Colo: Yensen Salvador | K89: =IFERROR(__xludf.DUMMYFUNCTION("""COMPUTED_VALUE"""),1089.19) -> 1089.19 | L89: =IFERROR(__xludf.DUMMYFUNCTION("""COMPUTED_VALUE"""),0.0) -> 0 | M89: -35113.43
I90: =IFERROR(__xludf.DUMMYFUNCTION("""COMPUTED_VALUE"""),46185.0) -> 46185 | J90: =IFERROR(__xludf.DUMMYFUNCTION("""COMPUTED_VALUE"""),"Colo: Bartolome Jeronimo") -> Colo: Bartolome Jeronimo | K90: =IFERROR(__xludf.DUMMYFUNCTION("""COMPUTED_VALUE"""),1513.47) -> 1513.47 | L90: =IFERROR(__xludf.DUMMYFUNCTION("""COMPUTED_VALUE"""),0.0) -> 0 | M90: -33599.96
I91: =IFERROR(__xludf.DUMMYFUNCTION("""COMPUTED_VALUE"""),46191.0) -> 46191 | J91: =IFERROR(__xludf.DUMMYFUNCTION("""COMPUTED_VALUE"""),"Gasto: edenor, municipal ofi") -> Gasto: edenor, municipal ofi | K91: =IFERROR(__xludf.DUMMYFUNCTION("""COMPUTED_VALUE"""),0.0) -> 0 | L91: =IFERROR(__xludf.DUMMYFUNCTION("""COMPUTED_VALUE"""),200.0) -> 200 | M91: -33799.96
I92: =IFERROR(__xludf.DUMMYFUNCTION("""COMPUTED_VALUE"""),46192.0) -> 46192 | J92: =IFERROR(__xludf.DUMMYFUNCTION("""COMPUTED_VALUE"""),"Gasto: coca junio ") -> Gasto: coca junio | K92: =IFERROR(__xludf.DUMMYFUNCTION("""COMPUTED_VALUE"""),0.0) -> 0 | L92: =IFERROR(__xludf.DUMMYFUNCTION("""COMPUTED_VALUE"""),235.0) -> 235 | M92: -34034.96
I93: =IFERROR(__xludf.DUMMYFUNCTION("""COMPUTED_VALUE"""),46192.0) -> 46192 | J93: =IFERROR(__xludf.DUMMYFUNCTION("""COMPUTED_VALUE"""),"Gasto: nachito") -> Gasto: nachito | K93: =IFERROR(__xludf.DUMMYFUNCTION("""COMPUTED_VALUE"""),0.0) -> 0 | L93: =IFERROR(__xludf.DUMMYFUNCTION("""COMPUTED_VALUE"""),340.0) -> 340 | M93: -34374.96
I94: =IFERROR(__xludf.DUMMYFUNCTION("""COMPUTED_VALUE"""),46192.0) -> 46192 | J94: =IFERROR(__xludf.DUMMYFUNCTION("""COMPUTED_VALUE"""),"Colo: MEDUSA") -> Colo: MEDUSA | K94: =IFERROR(__xludf.DUMMYFUNCTION("""COMPUTED_VALUE"""),0.0) -> 0 | L94: =IFERROR(__xludf.DUMMYFUNCTION("""COMPUTED_VALUE"""),3750.0) -> 3750 | M94: -38124.96
I95: =IFERROR(__xludf.DUMMYFUNCTION("""COMPUTED_VALUE"""),46194.0) -> 46194 | J95: =IFERROR(__xludf.DUMMYFUNCTION("""COMPUTED_VALUE"""),"Colo: Millan Facundo") -> Colo: Millan Facundo | K95: =IFERROR(__xludf.DUMMYFUNCTION("""COMPUTED_VALUE"""),2624.59) -> 2624.59 | L95: =IFERROR(__xludf.DUMMYFUNCTION("""COMPUTED_VALUE"""),0.0) -> 0 | M95: -35500.37
I96: =IFERROR(__xludf.DUMMYFUNCTION("""COMPUTED_VALUE"""),46195.0) -> 46195 | J96: =IFERROR(__xludf.DUMMYFUNCTION("""COMPUTED_VALUE"""),"Colo: PUFFCO") -> Colo: PUFFCO | K96: =IFERROR(__xludf.DUMMYFUNCTION("""COMPUTED_VALUE"""),0.0) -> 0 | L96: =IFERROR(__xludf.DUMMYFUNCTION("""COMPUTED_VALUE"""),19570.0) -> 19570 | M96: -55070.37
I97: =IFERROR(__xludf.DUMMYFUNCTION("""COMPUTED_VALUE"""),46196.0) -> 46196 | J97: =IFERROR(__xludf.DUMMYFUNCTION("""COMPUTED_VALUE"""),"Colo: Garcia Hugo") -> Colo: Garcia Hugo | K97: =IFERROR(__xludf.DUMMYFUNCTION("""COMPUTED_VALUE"""),7643.44) -> 7643.44 | L97: =IFERROR(__xludf.DUMMYFUNCTION("""COMPUTED_VALUE"""),0.0) -> 0 | M97: -47426.93
I98: =IFERROR(__xludf.DUMMYFUNCTION("""COMPUTED_VALUE"""),46202.0) -> 46202 | J98: =IFERROR(__xludf.DUMMYFUNCTION("""COMPUTED_VALUE"""),"Gasto: puffco 12 71kg") -> Gasto: puffco 12 71kg | K98: =IFERROR(__xludf.DUMMYFUNCTION("""COMPUTED_VALUE"""),0.0) -> 0 | L98: =IFERROR(__xludf.DUMMYFUNCTION("""COMPUTED_VALUE"""),2698.0) -> 2698 | M98: -50124.93
I99: =IFERROR(__xludf.DUMMYFUNCTION("""COMPUTED_VALUE"""),46203.0) -> 46203 | J99: =IFERROR(__xludf.DUMMYFUNCTION("""COMPUTED_VALUE"""),"Colo: Ferro") -> Colo: Ferro | K99: =IFERROR(__xludf.DUMMYFUNCTION("""COMPUTED_VALUE"""),2323.92) -> 2323.92 | L99: =IFERROR(__xludf.DUMMYFUNCTION("""COMPUTED_VALUE"""),0.0) -> 0 | M99: -47801.01
I100: =IFERROR(__xludf.DUMMYFUNCTION("""COMPUTED_VALUE"""),46205.0) -> 46205 | J100: =IFERROR(__xludf.DUMMYFUNCTION("""COMPUTED_VALUE"""),"Gasto: bolsas la despensa") -> Gasto: bolsas la despensa | K100: =IFERROR(__xludf.DUMMYFUNCTION("""COMPUTED_VALUE"""),0.0) -> 0 | L100: =IFERROR(__xludf.DUMMYFUNCTION("""COMPUTED_VALUE"""),240.0) -> 240 | M100: -48041.01
...

Sheet CTA CTE COLO
A1: Cliente | B1: Fecha | C1: Pesos | D1: Fee | E1: RECIBIDO | F1: USD | G1: Chequeado | H1: TC
A2: ANTERIOR | B2: 46373 | C2: 165000 | D2: =C2*3.5% -> 5775 | E2: =C2-D2 -> 159225 | G2: x | I2: =SUM(F2:F1077) -> -4353.88
A3: ANTERIOR | B3: 46375 | C3: 163350 | D3: =C3*3.5% -> 5717.25 | E3: =C3-D3 -> 157632.75 | G3: x
A4: ANTERIOR | B4: 46378 | C4: 282150 | D4: =C4*3.5% -> 9875.25 | E4: =C4-D4 -> 272274.75 | G4: x
A5: ANTERIOR | B5: 46378 | C5: 500000 | D5: =C5*3.5% -> 17500 | E5: =C5-D5 -> 482500 | G5: x
A6: ANTERIOR | B6: 46379 | C6: 500000 | D6: =C6*3.5% -> 17500 | E6: =C6-D6 -> 482500 | G6: x
A7: ANTERIOR | B7: 46031 | C7: 75000 | D7: =C7*3.5% -> 2625 | E7: =C7-D7 -> 72375 | G7: x
A8: ANTERIOR | B8: 46032 | C8: 45000 | D8: =C8*3.5% -> 1575 | E8: =C8-D8 -> 43425 | G8: x
A9: ANTERIOR | B9: 46032 | C9: 75000 | D9: =C9*3.5% -> 2625 | E9: =C9-D9 -> 72375 | F9: 1158 | G9: x | H9: 1504.58
A10: The press Club | B10: 46053 | C10: 0 | D10: =C10*3.5% -> 0 | E10: =C10-D10 -> 0 | F10: -2180 | G10: x
A11: ANTERIOR | B11: 46058 | C11: 576000 | D11: =C11*3.5% -> 20160 | E11: =C11-D11 -> 555840 | F11: 386 | G11: x | H11: =E11/F11 -> 1440
A12: PAGO PUFFCO | B12: 46064 | C12: 0 | D12: =C12*3.5% -> 0 | E12: =C12-D12 -> 0 | F12: -4162 | G12: x
A13: ANTERIOR | B13: 46060 | C13: 150000 | D13: =C13*3.5% -> 5250 | E13: =C13-D13 -> 144750 | G13: x
A14: ANTERIOR | B14: 46063 | C14: 7300 | D14: =C14*3.5% -> 255.5 | E14: =C14-D14 -> 7044.5 | G14: x
A15: ANTERIOR | B15: 46063 | C15: 228000 | D15: =C15*3.5% -> 7980 | E15: =C15-D15 -> 220020 | G15: x
A16: INGRESO LUCAS | B16: 46064 | C16: 0 | D16: =C16*3.5% -> 0 | E16: =C16-D16 -> 0 | F16: 4000 | G16: x
A17: ANTERIOR | B17: 46064 | C17: 1988075 | D17: =C17*3.5% -> 69582.625 | E17: =C17-D17 -> 1918492.4 | G17: x
A18: Juan Carlos Morales | B18: 46065 | C18: 1875000 | D18: =C18*3.5% -> 65625 | E18: =C18-D18 -> 1809375 | G18: x
A19: Rodrigo Orellano | B19: 46065 | C19: 215250 | D19: =C19*3.5% -> 7533.75 | E19: =C19-D19 -> 207716.25 | G19: x
A20: Gaston Balsamo | B20: 46065 | C20: 230000 | D20: =C20*3.5% -> 8050 | E20: =C20-D20 -> 221950 | G20: x
A21: Abril Barbaria | B21: 46066 | C21: 430000 | D21: =C21*3.5% -> 15050 | E21: =C21-D21 -> 414950 | G21: x
A22: Facundo Millan | B22: 46066 | C22: 426000 | D22: =C22*3.5% -> 14910 | E22: =C22-D22 -> 411090 | G22: x
A23: Rodrigo Hanun | B23: 46066 | C23: 230400 | D23: =C23*3.5% -> 8064 | E23: =C23-D23 -> 222336 | G23: x
A24: Leandro Lujan | B24: 46066 | C24: 288000 | D24: =C24*3.5% -> 10080 | E24: =C24-D24 -> 277920 | G24: x
A25: Facundo Millan | B25: 46070 | C25: 710000 | D25: =C25*3.5% -> 24850 | E25: =C25-D25 -> 685150 | F25: 4542 | G25: x | H25: =SUM(E13:E25)/F25 -> 1440.0692
A26: PAGO MEDUSA | B26: 46067 | F26: -2349 | G26: x
A27: PAGO MININAIL | B27: 46071 | F27: -3043 | G27: x
A28: Nachito | B28: 46072 | C28: 1000000 | D28: =C28*3.5% -> 35000 | E28: =C28-D28 -> 965000 | F28: 694 | G28: x | H28: =E28/F28 -> 1390.4899
A29: Nachito | B29: 46072 | F29: 1740 | G29: x
A30: PAGO REYNOLS | B30: 46072 | F30: -304 | G30: x
A31: CARGO POR USD | B31: 46072 | F31: -35 | G31: x
A32: Rodrigo Orellano | B32: 46071 | C32: 452000 | D32: =C32*3.5% -> 15820 | E32: =C32-D32 -> 436180 | G32: x
A33: Palomeque Matias | B33: 46072 | C33: 115000 | D33: =C33*3.5% -> 4025 | E33: =C33-D33 -> 110975 | G33: x
A34: Flavio Papa | B34: 46072 | C34: 145000 | D34: =C34*3.5% -> 5075 | E34: =C34-D34 -> 139925 | G34: x
A35: Bosio German | B35: 46072 | C35: 1022400 | D35: =C35*3.5% -> 35784 | E35: =C35-D35 -> 986616 | G35: x
A36: Abril Barbaria | B36: 46072 | C36: 94000 | D36: =C36*3.5% -> 3290 | E36: =C36-D36 -> 90710 | G36: x
A37: Rodrigo Sosa | B37: 46073 | C37: 500000 | D37: =C37*3.5% -> 17500 | E37: =C37-D37 -> 482500 | G37: x
A38: Astrogrow | B38: 46073 | C38: 1591400 | D38: =C38*3.5% -> 55699 | E38: =C38-D38 -> 1535701 | G38: x
A39: Abril Barbaria | B39: 46075 | C39: 543000 | D39: =C39*3.5% -> 19005 | E39: =C39-D39 -> 523995 | F39: 3001 | G39: x | H39: =SUM(E32:E39)/F39 -> 1435.0556
A40: PAGO PUFCO | B40: 46077 | F40: -7190 | G40: x
A41: PAGO TIN UY | B41: 46077 | F41: 2000 | G41: x
A42: BUBBLE BAG | B42: 46077 | F42: -3243 | G42: x
A43: Metrallier Matias | B43: 46077 | C43: 267000 | D43: =C43*3.5% -> 9345 | E43: =C43-D43 -> 257655 | G43: x
A44: Robledo Cristian | B44: 46077 | C44: 969540 | D44: =C44*3.5% -> 33933.9 | E44: =C44-D44 -> 935606.1 | G44: x
A45: Cruz Jonathan | B45: 46077 | C45: 171600 | D45: =C45*3.5% -> 6006 | E45: =C45-D45 -> 165594 | G45: x
A46: Fujii Lucas | B46: 46077 | C46: 286000 | D46: =C46*3.5% -> 10010 | E46: =C46-D46 -> 275990 | G46: x
A47: Veron Arami | B47: 46077 | C47: 143000 | D47: =C47*3.5% -> 5005 | E47: =C47-D47 -> 137995 | G47: x
A48: Creavero Negocios | B48: 46078 | C48: 173000 | D48: =C48*3.5% -> 6055 | E48: =C48-D48 -> 166945 | G48: x
A49: Rodrigo Orellano | B49: 46078 | C49: 215250 | D49: =C49*3.5% -> 7533.75 | E49: =C49-D49 -> 207716.25 | F49: 1481 | G49: x | H49: =SUM(E43:E49)/F49 -> 1450.0347
A50: Brea Carolina | B50: 46079 | C50: 722500 | D50: =C50*3.5% -> 25287.5 | E50: =C50-D50 -> 697212.5 | G50: x
A51: Nuñez Agustin | B51: 46080 | C51: 170400 | D51: =C51*3.5% -> 5964 | E51: =C51-D51 -> 164436 | F51: 609 | G51: x | H51: =SUM(E50:E51)/F51 -> 1414.858
A52: Formula 420 | B52: 46077 | F52: -3048 | G52: x
A53: Nuñez Agustin | B53: 46083 | C53: 122550 | D53: =C53*3.5% -> 4289.25 | E53: =C53-D53 -> 118260.75 | G53: x
A54: Orellano Rodrigo | B54: 46084 | C54: 106500 | D54: =C54*3.5% -> 3727.5 | E54: =C54-D54 -> 102772.5 | G54: x
A55: Millan Facundo | B55: 46085 | C55: 424500 | D55: =C55*3.5% -> 14857.5 | E55: =C55-D55 -> 409642.5 | G55: x
A56: Leloir Club | B56: 46085 | C56: 732720 | D56: =C56*3.5% -> 25645.2 | E56: =C56-D56 -> 707074.8 | G56: x
A57: Torres Gonzalo | B57: 46086 | C57: 300000 | D57: =C57*3.5% -> 10500 | E57: =C57-D57 -> 289500 | G57: x
A58: Leguizamon Agustin | B58: 46087 | C58: 470000 | D58: =C58*3.5% -> 16450 | E58: =C58-D58 -> 453550 | G58: x
A59: Barbaria Abril | B59: 46087 | C59: 490000 | D59: =C59*3.5% -> 17150 | E59: =C59-D59 -> 472850 | F59: 1786 | G59: x | H59: =SUM(E53:E59)/F59 -> 1429.8155
A60: Nachito | B60: 46072 | F60: 5900
A61: The press club | B61: 46077 | F61: -2785 | G61: x
A62: Formula 420 | B62: 46077 | F62: -3572 | G62: x
A63: Pinilla Martin | B63: 46091 | C63: 427500 | D63: =C63*3.5% -> 14962.5 | E63: =C63-D63 -> 412537.5 | G63: x
A64: Rosso Geronimo | B64: 46091 | C64: 429000 | D64: =C64*3.5% -> 15015 | E64: =C64-D64 -> 413985 | G64: x
A65: Morales Juan | B65: 46092 | C65: 1148000 | D65: =C65*3.5% -> 40180 | E65: =C65-D65 -> 1107820 | G65: x
A66: Nachito | B66: 46093 | F66: 3680
A67: Astrogrow | B67: 46094 | C67: 1467781 | D67: =C67*3.5% -> 51372.335 | E67: =C67-D67 -> 1416408.7 | G67: x
B68: 46094 | C68: 91650 | D68: =C68*3.5% -> 3207.75 | E68: =C68-D68 -> 88442.25 | G68: x
A69: Carranza Alejandro | B69: 46097 | C69: 1200000 | D69: =C69*3.5% -> 42000 | E69: =C69-D69 -> 1158000 | F69: 3215 | G69: x | H69: =SUM(E62:E69)/F69 -> 1429.9202
A70: Bosio German | B70: 46094 | C70: 4409100 | D70: =C70*3.5% -> 154318.5 | E70: =C70-D70 -> 4254781.5 | G70: x
A71: PAGO PUFCO | B71: 46098 | F71: -5175 | G71: x
A72: Pinilla Martin | B72: 46098 | C72: 500000 | D72: =C72*3.5% -> 17500 | E72: =C72-D72 -> 482500 | G72: x
A73: Carranza Alejandro | B73: 46099 | C73: 752400 | D73: =C73*3.5% -> 26334 | E73: =C73-D73 -> 726066 | G73: x
A74: Saldana Florencia | B74: 46099 | C74: 1780000 | D74: =C74*3.5% -> 62300 | E74: =C74-D74 -> 1717700 | G74: x
A75: Saldana Florencia | B75: 46099 | C75: 800000 | D75: =C75*3.5% -> 28000 | E75: =C75-D75 -> 772000 | G75: x
A76: Saldana Florencia | B76: 46099 | C76: 485160 | D76: =C76*3.5% -> 16980.6 | E76: =C76-D76 -> 468179.4 | G76: x
A77: Louge Nazareno | B77: 46099 | C77: 156750 | D77: =C77*3.5% -> 5486.25 | E77: =C77-D77 -> 151263.75 | G77: x
A78: Morales Juan Carlos | B78: 46100 | C78: 426000 | D78: =C78*3.5% -> 14910 | E78: =C78-D78 -> 411090 | G78: x
A79: Romera Luciano | B79: 46100 | C79: 343200 | D79: =C79*3.5% -> 12012 | E79: =C79-D79 -> 331188 | G79: x
A80: Albarez Jonathan | B80: 46100 | C80: 34000 | D80: =C80*3.5% -> 1190 | E80: =C80-D80 -> 32810 | G80: x
A81: Castillo Nicolas | B81: 46100 | C81: 142500 | D81: =C81*3.5% -> 4987.5 | E81: =C81-D81 -> 137512.5 | G81: x
A82: Aquino Ignacio | B82: 46100 | C82: 500000 | D82: =C82*3.5% -> 17500 | E82: =C82-D82 -> 482500 | F82: 6946 | G82: x | H82: =SUM(E72:E82)/F82 -> 822.46036
A83: Scherger Horacio | B83: 46101 | C83: 800000 | D83: =C83*3.5% -> 28000 | E83: =C83-D83 -> 772000 | G83: x
A84: Aquino Ignacio | B84: 46102 | C84: 200000 | D84: =C84*3.5% -> 7000 | E84: =C84-D84 -> 193000 | G84: x
A85: Zubizarreta Emiliano | B85: 46102 | C85: 285000 | D85: =C85*3.5% -> 9975 | E85: =C85-D85 -> 275025 | G85: x
A86: Diaz Martin | B86: 46104 | C86: 300000 | D86: =C86*3.5% -> 10500 | E86: =C86-D86 -> 289500 | G86: x
A87: Pinilla Martin | B87: 46104 | C87: 100000 | D87: =C87*3.5% -> 3500 | E87: =C87-D87 -> 96500 | G87: x
A88: Farias Sergio | B88: 46105 | C88: 350000 | D88: =C88*3.5% -> 12250 | E88: =C88-D88 -> 337750 | F88: 1378 | G88: x | H88: =SUM(E83:E88)/F88 -> 1425.0907
A89: Nachito | B89: 46106 | F89: 7000
A90: Millan Facundo | B90: 46106 | C90: 702500 | D90: =C90*3.5% -> 24587.5 | E90: =C90-D90 -> 677912.5 | G90: x
A91: Mauro Maria | B91: 46105 | C91: 170000 | D91: =C91*3.5% -> 5950 | E91: =C91-D91 -> 164050 | G91: x
A92: Russo Lucas | B92: 46106 | C92: 270750 | D92: =C92*3.5% -> 9476.25 | E92: =C92-D92 -> 261273.75 | G92: x
A93: Russo Lucas | B93: 46107 | C93: 270750 | D93: =C93*3.5% -> 9476.25 | E93: =C93-D93 -> 261273.75 | G93: x
A94: Aguilo Joaquin | B94: 46107 | C94: 210000 | D94: =C94*3.5% -> 7350 | E94: =C94-D94 -> 202650 | G94: x
B95: 46107 | C95: 270000 | D95: =C95*3.5% -> 9450 | E95: =C95-D95 -> 260550 | G95: x
B96: 46107 | C96: 75000 | D96: =C96*3.5% -> 2625 | E96: =C96-D96 -> 72375 | G96: x
A97: Robledo Cristian | B97: 46108 | C97: 255600 | D97: =C97*3.5% -> 8946 | E97: =C97-D97 -> 246654 | G97: x
A98: Martinelli Micaela | B98: 46108 | C98: 481000 | D98: =C98*3.5% -> 16835 | E98: =C98-D98 -> 464165 | G98: x
B99: 46108 | C99: 850000 | D99: =C99*3.5% -> 29750 | E99: =C99-D99 -> 820250 | F99: 2399 | G99: x | H99: =SUM(E91:E99)/F99 -> 1147.6622
A100: VANDERVERG | B100: 46098 | F100: -13665 | G100: x
...

Sheet TIN UY
A1: Fecha | B1: Total de pedido | C1: Comision | D1: a Rendir | E1: Fecha Pago | F1: Pago | H1: SALDO ACTUAL: | I1: =SUM(D2:D1007) - SUM(F2:F1007) -> 10639.221
A2: =IFERROR(__xludf.DUMMYFUNCTION("QUERY(Pedidos!A2:E1007, ""SELECT A, D, (E/2) WHERE lower(B) CONTAINS 'tin uy'"", 0)"),"") | B2: =IFERROR(__xludf.DUMMYFUNCTION("""COMPUTED_VALUE"""),"") | C2: =IFERROR(__xludf.DUMMYFUNCTION("""COMPUTED_VALUE"""),"quotient(2())") -> quotient(2()) | D2: {=IF(B2:B1007="", "", B2:B1007 - C2:C1007)} | E2: 46023 | F2: 0
A3: =IFERROR(__xludf.DUMMYFUNCTION("""COMPUTED_VALUE"""),46065.56648637731) -> 46065.566 | B3: =IFERROR(__xludf.DUMMYFUNCTION("""COMPUTED_VALUE"""),5185.0) -> 5185 | C3: =IFERROR(__xludf.DUMMYFUNCTION("""COMPUTED_VALUE"""),630.0029999999999) -> 630.003 | D3: 4554.997 | E3: 46058 | F3: 400 | H3: 576000 | I3: =H3/F3 -> 1440
A4: =IFERROR(__xludf.DUMMYFUNCTION("""COMPUTED_VALUE"""),46066.48805971065) -> 46066.488 | B4: =IFERROR(__xludf.DUMMYFUNCTION("""COMPUTED_VALUE"""),380.0) -> 380 | C4: =IFERROR(__xludf.DUMMYFUNCTION("""COMPUTED_VALUE"""),50.720000000000006) -> 50.72 | D4: 329.28 | E4: 46060 | F4: 104 | H4: 150000 | I4: =H4/F4 -> 1442.3077
A5: =IFERROR(__xludf.DUMMYFUNCTION("""COMPUTED_VALUE"""),46066.4891578125) -> 46066.489 | B5: =IFERROR(__xludf.DUMMYFUNCTION("""COMPUTED_VALUE"""),140.0) -> 140 | C5: =IFERROR(__xludf.DUMMYFUNCTION("""COMPUTED_VALUE"""),20.82) -> 20.82 | D5: 119.18 | E5: 46063 | F5: 6 | H5: 7300 | I5: =H5/F5 -> 1216.6667 | K5: COMISION USD 2900 (REUNION CON GER ESE DIA SE PAGO)
A6: =IFERROR(__xludf.DUMMYFUNCTION("""COMPUTED_VALUE"""),46071.321232905095) -> 46071.321 | B6: =IFERROR(__xludf.DUMMYFUNCTION("""COMPUTED_VALUE"""),710.0) -> 710 | C6: =IFERROR(__xludf.DUMMYFUNCTION("""COMPUTED_VALUE"""),85.07199999999999) -> 85.072 | D6: 624.928 | E6: 46063 | F6: 160 | H6: 228000 | I6: =H6/F6 -> 1425 | K6: COMISION USD 5915 17-6
A7: =IFERROR(__xludf.DUMMYFUNCTION("""COMPUTED_VALUE"""),46071.32832734953) -> 46071.328 | B7: =IFERROR(__xludf.DUMMYFUNCTION("""COMPUTED_VALUE"""),110.0) -> 110 | C7: =IFERROR(__xludf.DUMMYFUNCTION("""COMPUTED_VALUE"""),15.130000000000003) -> 15.13 | D7: 94.87 | E7: 46065 | F7: 1306 | H7: 1875000 | I7: =H7/F7 -> 1435.6815 | K7: COMISION USD 4782 25-7
A8: =IFERROR(__xludf.DUMMYFUNCTION("""COMPUTED_VALUE"""),46071.362096689816) -> 46071.362 | B8: =IFERROR(__xludf.DUMMYFUNCTION("""COMPUTED_VALUE"""),110.0) -> 110 | C8: =IFERROR(__xludf.DUMMYFUNCTION("""COMPUTED_VALUE"""),15.130000000000003) -> 15.13 | D8: 94.87 | E8: 46065 | F8: 150 | H8: 215250 | I8: =H8/F8 -> 1435
A9: =IFERROR(__xludf.DUMMYFUNCTION("""COMPUTED_VALUE"""),46072.99220949074) -> 46072.992 | B9: =IFERROR(__xludf.DUMMYFUNCTION("""COMPUTED_VALUE"""),75.0) -> 75 | C9: =IFERROR(__xludf.DUMMYFUNCTION("""COMPUTED_VALUE"""),8.527000000000001) -> 8.527 | D9: 66.473 | E9: 46065 | F9: 160 | H9: 230000 | I9: =H9/F9 -> 1437.5
A10: =IFERROR(__xludf.DUMMYFUNCTION("""COMPUTED_VALUE"""),46073.0) -> 46073 | B10: =IFERROR(__xludf.DUMMYFUNCTION("""COMPUTED_VALUE"""),154.0) -> 154 | D10: 154 | E10: 46066 | F10: 300 | H10: 430000 | I10: =H10/F10 -> 1433.3333
A11: =IFERROR(__xludf.DUMMYFUNCTION("""COMPUTED_VALUE"""),46076.36990046296) -> 46076.37 | B11: =IFERROR(__xludf.DUMMYFUNCTION("""COMPUTED_VALUE"""),680.0) -> 680 | C11: =IFERROR(__xludf.DUMMYFUNCTION("""COMPUTED_VALUE"""),128.802) -> 128.802 | D11: 551.198 | E11: 46066 | F11: 160 | H11: 230400 | I11: =H11/F11 -> 1440
A12: =IFERROR(__xludf.DUMMYFUNCTION("""COMPUTED_VALUE"""),46077.4104953125) -> 46077.41 | B12: =IFERROR(__xludf.DUMMYFUNCTION("""COMPUTED_VALUE"""),720.0) -> 720 | C12: =IFERROR(__xludf.DUMMYFUNCTION("""COMPUTED_VALUE"""),92.51399999999998) -> 92.514 | D12: 627.486 | E12: 46066 | F12: 200 | H12: 288000 | I12: =H12/F12 -> 1440
A13: =IFERROR(__xludf.DUMMYFUNCTION("""COMPUTED_VALUE"""),46086.478767754634) -> 46086.479 | B13: =IFERROR(__xludf.DUMMYFUNCTION("""COMPUTED_VALUE"""),944.0) -> 944 | C13: =IFERROR(__xludf.DUMMYFUNCTION("""COMPUTED_VALUE"""),121.30000000000001) -> 121.3 | D13: 822.7 | E13: 46071 | F13: 314 | H13: 452000 | I13: =H13/F13 -> 1439.4904
A14: =IFERROR(__xludf.DUMMYFUNCTION("""COMPUTED_VALUE"""),46086.501544467596) -> 46086.502 | B14: =IFERROR(__xludf.DUMMYFUNCTION("""COMPUTED_VALUE"""),12.0) -> 12 | C14: =IFERROR(__xludf.DUMMYFUNCTION("""COMPUTED_VALUE"""),2.74) -> 2.74 | D14: 9.26 | E14: 46072 | F14: 80 | H14: 115000 | I14: =H14/F14 -> 1437.5
A15: =IFERROR(__xludf.DUMMYFUNCTION("""COMPUTED_VALUE"""),46091.547995636574) -> 46091.548 | B15: =IFERROR(__xludf.DUMMYFUNCTION("""COMPUTED_VALUE"""),5940.0) -> 5940 | C15: =IFERROR(__xludf.DUMMYFUNCTION("""COMPUTED_VALUE"""),756.9116540649849) -> 756.91165 | D15: 5183.0883 | E15: 46072 | F15: 65 | H15: 94000 | I15: =H15/F15 -> 1446.1538
A16: =IFERROR(__xludf.DUMMYFUNCTION("""COMPUTED_VALUE"""),46091.55504461806) -> 46091.555 | B16: =IFERROR(__xludf.DUMMYFUNCTION("""COMPUTED_VALUE"""),70.0) -> 70 | C16: =IFERROR(__xludf.DUMMYFUNCTION("""COMPUTED_VALUE"""),9.051123596524944) -> 9.0511236 | D16: 60.948876 | E16: 46076 | F16: 2000
A17: =IFERROR(__xludf.DUMMYFUNCTION("""COMPUTED_VALUE"""),46094.90472501158) -> 46094.905 | B17: =IFERROR(__xludf.DUMMYFUNCTION("""COMPUTED_VALUE"""),73.0) -> 73 | C17: =IFERROR(__xludf.DUMMYFUNCTION("""COMPUTED_VALUE"""),8.722999999999999) -> 8.723 | D17: 64.277 | E17: 46077 | F17: 678 | H17: 969540 | I17: =H17/F17 -> 1430
A18: =IFERROR(__xludf.DUMMYFUNCTION("""COMPUTED_VALUE"""),46100.40611190972) -> 46100.406 | B18: =IFERROR(__xludf.DUMMYFUNCTION("""COMPUTED_VALUE"""),2850.0) -> 2850 | C18: =IFERROR(__xludf.DUMMYFUNCTION("""COMPUTED_VALUE"""),326.85029) -> 326.85029 | D18: 2523.1497 | E18: 46078 | F18: 150 | H18: 215250 | I18: =H18/F18 -> 1435
A19: =IFERROR(__xludf.DUMMYFUNCTION("""COMPUTED_VALUE"""),46100.42895394676) -> 46100.429 | B19: =IFERROR(__xludf.DUMMYFUNCTION("""COMPUTED_VALUE"""),111.0) -> 111 | C19: =IFERROR(__xludf.DUMMYFUNCTION("""COMPUTED_VALUE"""),13.518) -> 13.518 | D19: 97.482 | E19: 46079 | F19: 500 | H19: 722500 | I19: =H19/F19 -> 1445
A20: =IFERROR(__xludf.DUMMYFUNCTION("""COMPUTED_VALUE"""),46105.50936083333) -> 46105.509 | B20: =IFERROR(__xludf.DUMMYFUNCTION("""COMPUTED_VALUE"""),2080.0) -> 2080 | C20: =IFERROR(__xludf.DUMMYFUNCTION("""COMPUTED_VALUE"""),248.00477999999998) -> 248.00478 | D20: 1831.9952 | E20: 46084 | F20: 75 | H20: 106500 | I20: =H20/F20 -> 1420
A21: =IFERROR(__xludf.DUMMYFUNCTION("""COMPUTED_VALUE"""),46107.65429967592) -> 46107.654 | B21: =IFERROR(__xludf.DUMMYFUNCTION("""COMPUTED_VALUE"""),380.0) -> 380 | C21: =IFERROR(__xludf.DUMMYFUNCTION("""COMPUTED_VALUE"""),43.560779999999994) -> 43.56078 | D21: 336.43922 | E21: 46087 | F21: 350 | H21: 490000 | I21: =H21/F21 -> 1400
A22: =IFERROR(__xludf.DUMMYFUNCTION("""COMPUTED_VALUE"""),46113.48244548611) -> 46113.482 | B22: =IFERROR(__xludf.DUMMYFUNCTION("""COMPUTED_VALUE"""),2114.0) -> 2114 | C22: =IFERROR(__xludf.DUMMYFUNCTION("""COMPUTED_VALUE"""),286.81516000000005) -> 286.81516 | D22: 1827.1848 | E22: 46092 | F22: 820 | H22: 1148000 | I22: =H22/F22 -> 1400
A23: =IFERROR(__xludf.DUMMYFUNCTION("""COMPUTED_VALUE"""),46115.50344347222) -> 46115.503 | B23: =IFERROR(__xludf.DUMMYFUNCTION("""COMPUTED_VALUE"""),43.0) -> 43 | C23: =IFERROR(__xludf.DUMMYFUNCTION("""COMPUTED_VALUE"""),4.856999999999999) -> 4.857 | D23: 38.143 | E23: 46092 | F23: 1000 | I23: =H23/F23 -> 0 | J23: eft
A24: =IFERROR(__xludf.DUMMYFUNCTION("""COMPUTED_VALUE"""),46122.48845561343) -> 46122.488 | B24: =IFERROR(__xludf.DUMMYFUNCTION("""COMPUTED_VALUE"""),1540.0) -> 1540 | C24: =IFERROR(__xludf.DUMMYFUNCTION("""COMPUTED_VALUE"""),173.954) -> 173.954 | D24: 1366.046 | E24: 46094 | F24: 73 | H24: 91650 | I24: =H24/F24 -> 1255.4795
A25: =IFERROR(__xludf.DUMMYFUNCTION("""COMPUTED_VALUE"""),46122.50316644676) -> 46122.503 | B25: =IFERROR(__xludf.DUMMYFUNCTION("""COMPUTED_VALUE"""),37.0) -> 37 | C25: =IFERROR(__xludf.DUMMYFUNCTION("""COMPUTED_VALUE"""),4.506) -> 4.506 | D25: 32.494 | E25: 46100 | F25: 300 | H25: 426000 | I25: =H25/F25 -> 1420
A26: =IFERROR(__xludf.DUMMYFUNCTION("""COMPUTED_VALUE"""),46125.548567962964) -> 46125.549 | B26: =IFERROR(__xludf.DUMMYFUNCTION("""COMPUTED_VALUE"""),827.0) -> 827 | C26: =IFERROR(__xludf.DUMMYFUNCTION("""COMPUTED_VALUE"""),117.30700000000002) -> 117.307 | D26: 709.693 | E26: 46100 | F26: 350 | H26: 500000 | I26: =H26/F26 -> 1428.5714
A27: =IFERROR(__xludf.DUMMYFUNCTION("""COMPUTED_VALUE"""),46128.612426458334) -> 46128.612 | B27: =IFERROR(__xludf.DUMMYFUNCTION("""COMPUTED_VALUE"""),556.0) -> 556 | C27: =IFERROR(__xludf.DUMMYFUNCTION("""COMPUTED_VALUE"""),60.104) -> 60.104 | D27: 495.896 | E27: 46102 | F27: 140 | H27: 200000 | I27: =H27/F27 -> 1428.5714
A28: =IFERROR(__xludf.DUMMYFUNCTION("""COMPUTED_VALUE"""),46129.60218375001) -> 46129.602 | B28: =IFERROR(__xludf.DUMMYFUNCTION("""COMPUTED_VALUE"""),1656.0) -> 1656 | C28: =IFERROR(__xludf.DUMMYFUNCTION("""COMPUTED_VALUE"""),194.29837999999998) -> 194.29838 | D28: 1461.7016 | E28: 46102 | F28: 200 | H28: 285000 | I28: =H28/F28 -> 1425
A29: =IFERROR(__xludf.DUMMYFUNCTION("""COMPUTED_VALUE"""),46134.53675914351) -> 46134.537 | B29: =IFERROR(__xludf.DUMMYFUNCTION("""COMPUTED_VALUE"""),1024.0) -> 1024 | C29: =IFERROR(__xludf.DUMMYFUNCTION("""COMPUTED_VALUE"""),147.26108) -> 147.26108 | D29: 876.73892 | E29: 46106 | F29: 120 | H29: 170000 | I29: =H29/F29 -> 1416.6667
A30: =IFERROR(__xludf.DUMMYFUNCTION("""COMPUTED_VALUE"""),46135.65397158565) -> 46135.654 | B30: =IFERROR(__xludf.DUMMYFUNCTION("""COMPUTED_VALUE"""),1200.0) -> 1200 | C30: =IFERROR(__xludf.DUMMYFUNCTION("""COMPUTED_VALUE"""),147.64156) -> 147.64156 | D30: 1052.3584 | E30: 46107 | F30: 2000 | J30: eft utilizado para pagar six 6
A31: =IFERROR(__xludf.DUMMYFUNCTION("""COMPUTED_VALUE"""),46136.51522201389) -> 46136.515 | B31: =IFERROR(__xludf.DUMMYFUNCTION("""COMPUTED_VALUE"""),2090.0) -> 2090 | C31: =IFERROR(__xludf.DUMMYFUNCTION("""COMPUTED_VALUE"""),350.3999999999999) -> 350.4 | D31: 1739.6 | E31: 46107 | F31: 190 | H31: 270000 | I31: =H31/F31 -> 1421.0526
A32: =IFERROR(__xludf.DUMMYFUNCTION("""COMPUTED_VALUE"""),46136.52892653935) -> 46136.529 | B32: =IFERROR(__xludf.DUMMYFUNCTION("""COMPUTED_VALUE"""),170.0) -> 170 | C32: =IFERROR(__xludf.DUMMYFUNCTION("""COMPUTED_VALUE"""),25.0) -> 25 | D32: 145 | E32: 46108 | F32: 180 | H32: 255600 | I32: =H32/F32 -> 1420
A33: =IFERROR(__xludf.DUMMYFUNCTION("""COMPUTED_VALUE"""),46142.002299872685) -> 46142.002 | B33: =IFERROR(__xludf.DUMMYFUNCTION("""COMPUTED_VALUE"""),2770.0) -> 2770 | C33: =IFERROR(__xludf.DUMMYFUNCTION("""COMPUTED_VALUE"""),858.495) -> 858.495 | D33: 1911.505 | E33: 46109 | F33: 120 | H33: 170400 | I33: =H33/F33 -> 1420
A34: =IFERROR(__xludf.DUMMYFUNCTION("""COMPUTED_VALUE"""),46142.49808829861) -> 46142.498 | B34: =IFERROR(__xludf.DUMMYFUNCTION("""COMPUTED_VALUE"""),4670.0) -> 4670 | C34: =IFERROR(__xludf.DUMMYFUNCTION("""COMPUTED_VALUE"""),1091.942) -> 1091.942 | D34: 3578.058 | E34: 46111 | F34: 150 | H34: 212250 | I34: =H34/F34 -> 1415
A35: =IFERROR(__xludf.DUMMYFUNCTION("""COMPUTED_VALUE"""),46157.52252828704) -> 46157.523 | B35: =IFERROR(__xludf.DUMMYFUNCTION("""COMPUTED_VALUE"""),2554.0) -> 2554 | C35: =IFERROR(__xludf.DUMMYFUNCTION("""COMPUTED_VALUE"""),342.2393748424694) -> 342.23937 | D35: 2211.7606 | E35: 46114 | F35: 1840 | I35: =H35/F35 -> 0 | J35: eft a lucas utilizado para pagar oficina Resta dinero
A36: =IFERROR(__xludf.DUMMYFUNCTION("""COMPUTED_VALUE"""),46157.52398521991) -> 46157.524 | B36: =IFERROR(__xludf.DUMMYFUNCTION("""COMPUTED_VALUE"""),950.0) -> 950 | C36: =IFERROR(__xludf.DUMMYFUNCTION("""COMPUTED_VALUE"""),124.67799999999997) -> 124.678 | D36: 825.322 | E36: 46115 | F36: 277 | H36: 389025 | I36: =H36/F36 -> 1404.4224 | J36: pesos a lucas
A37: =IFERROR(__xludf.DUMMYFUNCTION("""COMPUTED_VALUE"""),46160.66341793982) -> 46160.663 | B37: =IFERROR(__xludf.DUMMYFUNCTION("""COMPUTED_VALUE"""),750.0) -> 750 | C37: =IFERROR(__xludf.DUMMYFUNCTION("""COMPUTED_VALUE"""),90.92723596524941) -> 90.927236 | D37: 659.07276 | E37: 46117 | F37: 150 | H37: 214500 | I37: =H37/F37 -> 1430
A38: =IFERROR(__xludf.DUMMYFUNCTION("""COMPUTED_VALUE"""),46162.58799190972) -> 46162.588 | B38: =IFERROR(__xludf.DUMMYFUNCTION("""COMPUTED_VALUE"""),8428.0) -> 8428 | C38: =IFERROR(__xludf.DUMMYFUNCTION("""COMPUTED_VALUE"""),1008.7526200000001) -> 1008.7526 | D38: 7419.2474 | E38: 46121 | F38: 300 | H38: 420000 | I38: =H38/F38 -> 1400
A39: =IFERROR(__xludf.DUMMYFUNCTION("""COMPUTED_VALUE"""),46163.50381354166) -> 46163.504 | B39: =IFERROR(__xludf.DUMMYFUNCTION("""COMPUTED_VALUE"""),2034.0) -> 2034 | C39: =IFERROR(__xludf.DUMMYFUNCTION("""COMPUTED_VALUE"""),285.312) -> 285.312 | D39: 1748.688 | E39: 46122 | F39: 120 | H39: 165000 | I39: =H39/F39 -> 1375
A40: =IFERROR(__xludf.DUMMYFUNCTION("""COMPUTED_VALUE"""),46166.95721944445) -> 46166.957 | B40: =IFERROR(__xludf.DUMMYFUNCTION("""COMPUTED_VALUE"""),1400.0) -> 1400 | C40: =IFERROR(__xludf.DUMMYFUNCTION("""COMPUTED_VALUE"""),386.984) -> 386.984 | D40: 1013.016 | E40: 46122 | F40: 310 | H40: 430000 | I40: =H40/F40 -> 1387.0968
A41: =IFERROR(__xludf.DUMMYFUNCTION("""COMPUTED_VALUE"""),46183.55062210648) -> 46183.551 | B41: =IFERROR(__xludf.DUMMYFUNCTION("""COMPUTED_VALUE"""),3838.0) -> 3838 | C41: =IFERROR(__xludf.DUMMYFUNCTION("""COMPUTED_VALUE"""),656.8530000000001) -> 656.853 | D41: 3181.147 | E41: 46122 | F41: 40 | H41: 57000 | I41: =H41/F41 -> 1425
A42: =IFERROR(__xludf.DUMMYFUNCTION("""COMPUTED_VALUE"""),46191.66320418982) -> 46191.663 | B42: =IFERROR(__xludf.DUMMYFUNCTION("""COMPUTED_VALUE"""),1968.0) -> 1968 | C42: =IFERROR(__xludf.DUMMYFUNCTION("""COMPUTED_VALUE"""),261.10100000000006) -> 261.101 | D42: 1706.899 | E42: 46122 | F42: 95 | H42: 132050 | I42: =H42/F42 -> 1390
A43: =IFERROR(__xludf.DUMMYFUNCTION("""COMPUTED_VALUE"""),46191.66387959491) -> 46191.664 | B43: =IFERROR(__xludf.DUMMYFUNCTION("""COMPUTED_VALUE"""),200.0) -> 200 | C43: =IFERROR(__xludf.DUMMYFUNCTION("""COMPUTED_VALUE"""),21.319999999999993) -> 21.32 | D43: 178.68 | E43: 46123 | F43: 72 | H43: 100000 | I43: =H43/F43 -> 1388.8889
A44: =IFERROR(__xludf.DUMMYFUNCTION("""COMPUTED_VALUE"""),46203.506490659725) -> 46203.506 | B44: =IFERROR(__xludf.DUMMYFUNCTION("""COMPUTED_VALUE"""),10012.0) -> 10012 | C44: =IFERROR(__xludf.DUMMYFUNCTION("""COMPUTED_VALUE"""),1116.2410000000002) -> 1116.241 | D44: 8895.759 | E44: 46123 | F44: 92 | H44: 130000 | I44: =H44/F44 -> 1413.0435
A45: =IFERROR(__xludf.DUMMYFUNCTION("""COMPUTED_VALUE"""),46203.50971693287) -> 46203.51 | B45: =IFERROR(__xludf.DUMMYFUNCTION("""COMPUTED_VALUE"""),990.0) -> 990 | C45: =IFERROR(__xludf.DUMMYFUNCTION("""COMPUTED_VALUE"""),150.29) -> 150.29 | D45: 839.71 | E45: 46124 | F45: 60 | H45: 84000 | I45: =H45/F45 -> 1400
A46: =IFERROR(__xludf.DUMMYFUNCTION("""COMPUTED_VALUE"""),46210.64257081019) -> 46210.643 | B46: =IFERROR(__xludf.DUMMYFUNCTION("""COMPUTED_VALUE"""),2421.0) -> 2421 | C46: =IFERROR(__xludf.DUMMYFUNCTION("""COMPUTED_VALUE"""),273.03508) -> 273.03508 | D46: 2147.9649 | E46: 46125 | F46: 72 | H46: 100000 | I46: =H46/F46 -> 1388.8889
A47: =IFERROR(__xludf.DUMMYFUNCTION("""COMPUTED_VALUE"""),46210.66190644675) -> 46210.662 | B47: =IFERROR(__xludf.DUMMYFUNCTION("""COMPUTED_VALUE"""),8709.0) -> 8709 | C47: =IFERROR(__xludf.DUMMYFUNCTION("""COMPUTED_VALUE"""),1196.361) -> 1196.361 | D47: 7512.639 | E47: 46126 | F47: 108 | H47: 150000 | I47: =H47/F47 -> 1388.8889
A48: =IFERROR(__xludf.DUMMYFUNCTION("""COMPUTED_VALUE"""),46224.51148100694) -> 46224.511 | B48: =IFERROR(__xludf.DUMMYFUNCTION("""COMPUTED_VALUE"""),7585.0) -> 7585 | C48: =IFERROR(__xludf.DUMMYFUNCTION("""COMPUTED_VALUE"""),1098.2689800000005) -> 1098.269 | D48: 6486.731 | E48: 46126 | F48: 82 | H48: 115000 | I48: =H48/F48 -> 1402.439 | L48: =SUM(D3:D56) -> 103594.65
A49: =IFERROR(__xludf.DUMMYFUNCTION("""COMPUTED_VALUE"""),46224.51991461805) -> 46224.52 | B49: =IFERROR(__xludf.DUMMYFUNCTION("""COMPUTED_VALUE"""),184.0) -> 184 | C49: =IFERROR(__xludf.DUMMYFUNCTION("""COMPUTED_VALUE"""),8.53966063348416) -> 8.5396606 | D49: 175.46034 | E49: 46127 | F49: 190 | H49: 268000 | I49: =H49/F49 -> 1410.5263 | L49: =SUM(F3:F139) -> 89910.14
A50: =IFERROR(__xludf.DUMMYFUNCTION("""COMPUTED_VALUE"""),46228.39590101852) -> 46228.396 | B50: =IFERROR(__xludf.DUMMYFUNCTION("""COMPUTED_VALUE"""),5986.0) -> 5986 | C50: =IFERROR(__xludf.DUMMYFUNCTION("""COMPUTED_VALUE"""),566.96631) -> 566.96631 | D50: 5419.0337 | E50: 46127 | F50: 2000 | I50: =H50/F50 -> 0 | J50: entregado al colo 27-4
A51: =IFERROR(__xludf.DUMMYFUNCTION("""COMPUTED_VALUE"""),46228.39667952546) -> 46228.397 | B51: =IFERROR(__xludf.DUMMYFUNCTION("""COMPUTED_VALUE"""),960.0) -> 960 | C51: =IFERROR(__xludf.DUMMYFUNCTION("""COMPUTED_VALUE"""),160.848) -> 160.848 | D51: 799.152 | E51: 46128 | F51: 110 | H51: 155100 | I51: =H51/F51 -> 1410 | L51: =L48-L49 -> 13684.508
A52: =IFERROR(__xludf.DUMMYFUNCTION("""COMPUTED_VALUE"""),46247.329295428244) -> 46247.329 | B52: =IFERROR(__xludf.DUMMYFUNCTION("""COMPUTED_VALUE"""),4296.0) -> 4296 | C52: =IFERROR(__xludf.DUMMYFUNCTION("""COMPUTED_VALUE"""),398.0655000000001) -> 398.0655 | D52: 3897.9345 | E52: 46135 | F52: 430 | H52: 600000 | I52: =H52/F52 -> 1395.3488
A53: =IFERROR(__xludf.DUMMYFUNCTION("""COMPUTED_VALUE"""),46247.33372537037) -> 46247.334 | B53: =IFERROR(__xludf.DUMMYFUNCTION("""COMPUTED_VALUE"""),2500.0) -> 2500 | C53: =IFERROR(__xludf.DUMMYFUNCTION("""COMPUTED_VALUE"""),461.029455) -> 461.02945 | D53: 2038.9705 | E53: 46135 | F53: 550 | H53: 770000 | I53: =H53/F53 -> 1400
A54: =IFERROR(__xludf.DUMMYFUNCTION("""COMPUTED_VALUE"""),46263.44154148148) -> 46263.442 | B54: =IFERROR(__xludf.DUMMYFUNCTION("""COMPUTED_VALUE"""),10014.0) -> 10014 | C54: =IFERROR(__xludf.DUMMYFUNCTION("""COMPUTED_VALUE"""),1181.8645946137403) -> 1181.8646 | D54: 8832.1354 | E54: 46139 | F54: 300 | H54: 420000 | I54: =H54/F54 -> 1400
A55: =IFERROR(__xludf.DUMMYFUNCTION("""COMPUTED_VALUE"""),46274.59657954862) -> 46274.597 | B55: =IFERROR(__xludf.DUMMYFUNCTION("""COMPUTED_VALUE"""),1560.0) -> 1560 | C55: =IFERROR(__xludf.DUMMYFUNCTION("""COMPUTED_VALUE"""),142.04157000000006) -> 142.04157 | D55: 1417.9584 | E55: 46139 | F55: 200 | H55: 286000 | I55: =H55/F55 -> 1430
A56: =IFERROR(__xludf.DUMMYFUNCTION("""COMPUTED_VALUE"""),46275.51611456018) -> 46275.516 | B56: =IFERROR(__xludf.DUMMYFUNCTION("""COMPUTED_VALUE"""),3344.0) -> 3344 | C56: =IFERROR(__xludf.DUMMYFUNCTION("""COMPUTED_VALUE"""),537.6752308371041) -> 537.67523 | D56: 2806.3248 | E56: 46140 | F56: 385 | H56: 540000 | I56: =H56/F56 -> 1402.5974
A57: =IFERROR(__xludf.DUMMYFUNCTION("""COMPUTED_VALUE"""),46295.558942418975) -> 46295.559 | B57: =IFERROR(__xludf.DUMMYFUNCTION("""COMPUTED_VALUE"""),1910.0) -> 1910 | C57: =IFERROR(__xludf.DUMMYFUNCTION("""COMPUTED_VALUE"""),515.29826) -> 515.29826 | D57: 1394.7017 | E57: 46141 | F57: 180 | H57: 255600 | I57: =H57/F57 -> 1420
A58: =IFERROR(__xludf.DUMMYFUNCTION("""COMPUTED_VALUE"""),46296.556629224535) -> 46296.557 | B58: =IFERROR(__xludf.DUMMYFUNCTION("""COMPUTED_VALUE"""),1794.0) -> 1794 | C58: =IFERROR(__xludf.DUMMYFUNCTION("""COMPUTED_VALUE"""),188.98800000000003) -> 188.988 | D58: 1605.012 | E58: 46141 | F58: 3000 | I58: =H58/F58 -> 0 | J58: eft nachito lleva a YAMIL por CARGA 30-4
E59: 46144 | F59: 285 | H59: 400000 | I59: =H59/F59 -> 1403.5088
E60: 46144 | F60: 305 | H60: 427000 | I60: =H60/F60 -> 1400
E61: 46144 | F61: 100 | H61: 140000 | I61: =H61/F61 -> 1400
E62: 46145 | F62: 200 | H62: 280000 | I62: =H62/F62 -> 1400
E63: 46145 | F63: 230 | H63: 322000 | I63: =H63/F63 -> 1400
E64: 46145 | F64: 230 | H64: 322000 | I64: =H64/F64 -> 1400
E65: 46147 | F65: 220 | H65: 309100 | I65: =H65/F65 -> 1405
E66: 46147 | F66: 285 | H66: 400000 | I66: =H66/F66 -> 1403.5088
E67: 46147 | F67: 1800 | J67: eft nachito lleva a YAMIL y cancela deuda de USD 1800
E68: 46179 | F68: 190 | H68: 266000
E69: 46179 | F69: 440 | H69: 619770
E70: 46180 | F70: 310 | H70: 434000
E71: 46155 | F71: 100 | H71: 140000
E72: 46157 | F72: 3045 | J72: eft a nachito RETIRA SIXTAR USD 1748 RESTO GUARDAR PARA GER
E73: 46157 | F73: 110 | H73: 154000
E74: 46158 | F74: 750 | H74: 1135050
E75: 46162 | F75: 570 | H75: 800000
E76: 46162 | F76: 255 | H76: 363000
E77: 46165 | F77: 500 | H77: 712500
E78: 46165 | F78: 160 | H78: 227000
E79: 46165 | F79: 100 | H79: 140000
E80: 46168 | F80: 120 | H80: 172000
E81: 46168 | F81: 150 | H81: 210000
E82: 46171 | F82: 110 | H82: 160000
E83: 46176 | F83: 330 | H83: 473550
E84: 46176 | F84: 3000 | J84: eft sixtar parte Holanda
E85: 46179 | F85: 350 | H85: 501000
E86: 46182 | F86: 400 | H86: 600000
E87: 46182 | F87: 480 | H87: 657150
E88: 46189 | F88: 100 | H88: 145500
E89: 46190 | F89: 130 | H89: 189150
E90: 46191 | F90: 920 | H90: 1334000
E91: 46192 | F91: 4000 | J91: eft a nachito para el colo
E92: 46196 | F92: 210
E93: 46210 | F93: 815 | H93: 3 transfer al colo
E94: 46210 | F94: 7100 | J94: eft para enviar al COLO el dia miercoles 8-7 con nachito
E95: 46210 | F95: 1400 | H95: 5 transfer al colo
E96: 46212 | F96: 1240 | H96: 1872400
E97: 46212 | F97: 445 | H97: 672000
E98: 46215 | F98: 666 | H98: 1000000
E99: 46217 | F99: 563 | J99: Moco 10g + cartuchos c/resi (atencion al colo por todo)
E100: 46219 | F100: 660 | H100: 1000000
...

Sheet Pedro
A1: Fecha | B1: Total de pedido | C1: Comision | D1: a Rendir | E1: Fecha Pago | F1: Pago | H1: SALDO ACTUAL: | I1: =SUM(D2:D1000) - SUM(F2:F1000) -> 1467.7487
A2: =IFERROR(__xludf.DUMMYFUNCTION("QUERY(Pedidos!A2:E1000, ""SELECT A, D, (E/2) WHERE lower(B) CONTAINS 'pedro'"", 0)"),"") | B2: =IFERROR(__xludf.DUMMYFUNCTION("""COMPUTED_VALUE"""),"") | C2: =IFERROR(__xludf.DUMMYFUNCTION("""COMPUTED_VALUE"""),"quotient(2())") -> quotient(2()) | D2: {=IF(B2:B1000="", "", B2:B1000 - C2:C1000)} | E2: 46023 | F2: 0
A3: =IFERROR(__xludf.DUMMYFUNCTION("""COMPUTED_VALUE"""),46205.732028148144) -> 46205.732 | B3: =IFERROR(__xludf.DUMMYFUNCTION("""COMPUTED_VALUE"""),1684.0) -> 1684 | C3: =IFERROR(__xludf.DUMMYFUNCTION("""COMPUTED_VALUE"""),216.25134831582997) -> 216.25135 | D3: 1467.7487

Sheet Charly Distri
A1: Fecha | B1: Total de pedido | C1: Comision | D1: a Rendir | E1: Fecha Pago | F1: Pago | H1: SALDO ACTUAL: | I1: =SUM(D2:D1000) - SUM(F2:F1000) -> -0.002455
A2: =IFERROR(__xludf.DUMMYFUNCTION("QUERY(Pedidos!A2:E1000, ""SELECT A, D, (E/2) WHERE lower(B) CONTAINS 'charly distri'"", 0)"),"") | B2: =IFERROR(__xludf.DUMMYFUNCTION("""COMPUTED_VALUE"""),"") | C2: =IFERROR(__xludf.DUMMYFUNCTION("""COMPUTED_VALUE"""),"quotient(2())") -> quotient(2()) | D2: {=IF(B2:B1000="", "", B2:B1000 - C2:C1000)} | E2: 46023 | F2: 0
A3: =IFERROR(__xludf.DUMMYFUNCTION("""COMPUTED_VALUE"""),46065.586095694445) -> 46065.586 | B3: =IFERROR(__xludf.DUMMYFUNCTION("""COMPUTED_VALUE"""),6534.0) -> 6534 | C3: =IFERROR(__xludf.DUMMYFUNCTION("""COMPUTED_VALUE"""),800.289) -> 800.289 | D3: 5733.711 | E3: 46098 | F3: 7000
A4: =IFERROR(__xludf.DUMMYFUNCTION("""COMPUTED_VALUE"""),46093.0) -> 46093 | B4: =IFERROR(__xludf.DUMMYFUNCTION("""COMPUTED_VALUE"""),890.0) -> 890 | C4: =IFERROR(__xludf.DUMMYFUNCTION("""COMPUTED_VALUE"""),102.69) -> 102.69 | D4: 787.31 | E4: 46153 | F4: 5000 | J4: EFT a GER 11-5
A5: =IFERROR(__xludf.DUMMYFUNCTION("""COMPUTED_VALUE"""),46097.50213896991) -> 46097.502 | B5: =IFERROR(__xludf.DUMMYFUNCTION("""COMPUTED_VALUE"""),6048.0) -> 6048 | C5: =IFERROR(__xludf.DUMMYFUNCTION("""COMPUTED_VALUE"""),897.4970000000001) -> 897.497 | D5: 5150.503 | E5: 46225 | F5: 1700
A6: =IFERROR(__xludf.DUMMYFUNCTION("""COMPUTED_VALUE"""),46098.58466619213) -> 46098.585 | B6: =IFERROR(__xludf.DUMMYFUNCTION("""COMPUTED_VALUE"""),3922.0) -> 3922 | C6: =IFERROR(__xludf.DUMMYFUNCTION("""COMPUTED_VALUE"""),448.16157999999996) -> 448.16158 | D6: 3473.8384 | E6: 46228 | F6: 3620 | J6: eft nachito al colo 25-7
A7: =IFERROR(__xludf.DUMMYFUNCTION("""COMPUTED_VALUE"""),46228.41644241898) -> 46228.416 | B7: =IFERROR(__xludf.DUMMYFUNCTION("""COMPUTED_VALUE"""),4055.0) -> 4055 | C7: =IFERROR(__xludf.DUMMYFUNCTION("""COMPUTED_VALUE"""),434.844875) -> 434.84488 | D7: 3620.1551 | E7: 46280.57 | F7: 1445.52 | K7: Pago en Efectivo/Transf USD

Sheet FACU LP
A1: Fecha | B1: Total de pedido | C1: Comision | D1: a Rendir | E1: Fecha Pago | F1: Pago | H1: SALDO ACTUAL: | I1: =SUM(D2:D1000) - SUM(F2:F1000) -> 3477 | K1: Obs.
A2: =IFERROR(__xludf.DUMMYFUNCTION("QUERY(Pedidos!A2:E1000, ""SELECT A, D, (E/0) WHERE lower(B) CONTAINS 'facu lp'"", 0)"),"") | B2: =IFERROR(__xludf.DUMMYFUNCTION("""COMPUTED_VALUE"""),"") | C2: =IFERROR(__xludf.DUMMYFUNCTION("""COMPUTED_VALUE"""),"quotient(0())") -> quotient(0()) | D2: {=IF(B2:B1000="", "", B2:B1000 - C2:C1000)} | E2: 46023 | F2: 0
A3: =IFERROR(__xludf.DUMMYFUNCTION("""COMPUTED_VALUE"""),46066.45211443287) -> 46066.452 | B3: =IFERROR(__xludf.DUMMYFUNCTION("""COMPUTED_VALUE"""),700.0) -> 700 | D3: 700 | E3: 46066 | F3: 300
A4: =IFERROR(__xludf.DUMMYFUNCTION("""COMPUTED_VALUE"""),46066.48658791667) -> 46066.487 | B4: =IFERROR(__xludf.DUMMYFUNCTION("""COMPUTED_VALUE"""),70.0) -> 70 | D4: 70 | E4: 46070 | F4: 500
A5: =IFERROR(__xludf.DUMMYFUNCTION("""COMPUTED_VALUE"""),46073.563214456015) -> 46073.563 | B5: =IFERROR(__xludf.DUMMYFUNCTION("""COMPUTED_VALUE"""),295.0) -> 295 | D5: 295 | E5: 46085 | F5: 300 | H5: 424500 | I5: =H5/F5 -> 1415
A6: =IFERROR(__xludf.DUMMYFUNCTION("""COMPUTED_VALUE"""),46077.42361723379) -> 46077.424 | B6: =IFERROR(__xludf.DUMMYFUNCTION("""COMPUTED_VALUE"""),1750.0) -> 1750 | D6: 1750 | E6: 46094 | F6: 300 | K6: LUCAS LO UTILIZO PARA PAGAR los 30kg de SIXTAR 5 del 13-03
B7: =IFERROR(__xludf.DUMMYFUNCTION("""COMPUTED_VALUE"""),725.0) -> 725 | D7: 725 | E7: 46106 | F7: 500 | H7: 702500 | I7: 1405
A8: =IFERROR(__xludf.DUMMYFUNCTION("""COMPUTED_VALUE"""),46094.39025872685) -> 46094.39 | B8: =IFERROR(__xludf.DUMMYFUNCTION("""COMPUTED_VALUE"""),1767.0) -> 1767 | D8: 1767 | E8: 46112 | F8: 500 | H8: 705000 | I8: 1415
A9: =IFERROR(__xludf.DUMMYFUNCTION("""COMPUTED_VALUE"""),46094.39536949074) -> 46094.395 | B9: =IFERROR(__xludf.DUMMYFUNCTION("""COMPUTED_VALUE"""),200.0) -> 200 | D9: 200 | E9: 46133 | F9: 500 | H9: 695000 | I9: 1415
A10: =IFERROR(__xludf.DUMMYFUNCTION("""COMPUTED_VALUE"""),46099.84272181713) -> 46099.843 | B10: =IFERROR(__xludf.DUMMYFUNCTION("""COMPUTED_VALUE"""),680.0) -> 680 | D10: 680 | E10: 46148 | F10: 358 | H10: 500000
A11: =IFERROR(__xludf.DUMMYFUNCTION("""COMPUTED_VALUE"""),46113.3673287963) -> 46113.367 | B11: =IFERROR(__xludf.DUMMYFUNCTION("""COMPUTED_VALUE"""),480.0) -> 480 | D11: 480 | E11: 46150 | F11: 321 | H11: 450000
A12: =IFERROR(__xludf.DUMMYFUNCTION("""COMPUTED_VALUE"""),46142.97240875) -> 46142.972 | B12: =IFERROR(__xludf.DUMMYFUNCTION("""COMPUTED_VALUE"""),50.0) -> 50 | D12: 50 | E12: 46163 | F12: 300 | H12: 465000
A13: =IFERROR(__xludf.DUMMYFUNCTION("""COMPUTED_VALUE"""),46157.53089638888) -> 46157.531 | B13: =IFERROR(__xludf.DUMMYFUNCTION("""COMPUTED_VALUE"""),605.0) -> 605 | D13: 605 | E13: 46194 | F13: 400 | H13: 568000
A14: =IFERROR(__xludf.DUMMYFUNCTION("""COMPUTED_VALUE"""),46161.53586685185) -> 46161.536 | B14: =IFERROR(__xludf.DUMMYFUNCTION("""COMPUTED_VALUE"""),240.0) -> 240 | D14: 240
A15: =IFERROR(__xludf.DUMMYFUNCTION("""COMPUTED_VALUE"""),46184.71363414352) -> 46184.714 | B15: =IFERROR(__xludf.DUMMYFUNCTION("""COMPUTED_VALUE"""),194.0) -> 194 | D15: 194

Sheet Agus Honney
A1: Fecha | B1: Total de pedido | C1: Comision | D1: a Rendir | E1: Fecha Pago | F1: Pago | H1: SALDO ACTUAL: | I1: =SUM(D2:D1000) - SUM(F2:F1000) -> 68.659953
A2: =IFERROR(__xludf.DUMMYFUNCTION("QUERY(Pedidos!A2:E1000, ""SELECT A, D, (E/2) WHERE lower(B) CONTAINS 'agus honney'"", 0)"),"") | B2: =IFERROR(__xludf.DUMMYFUNCTION("""COMPUTED_VALUE"""),"") | C2: =IFERROR(__xludf.DUMMYFUNCTION("""COMPUTED_VALUE"""),"quotient(2())") -> quotient(2()) | D2: {=IF(B2:B1000="", "", B2:B1000 - C2:C1000)} | E2: 46023 | F2: 0
A3: =IFERROR(__xludf.DUMMYFUNCTION("""COMPUTED_VALUE"""),46073.35723768519) -> 46073.357 | B3: =IFERROR(__xludf.DUMMYFUNCTION("""COMPUTED_VALUE"""),214.0) -> 214 | C3: =IFERROR(__xludf.DUMMYFUNCTION("""COMPUTED_VALUE"""),34.656000000000006) -> 34.656 | D3: 179.344 | E3: 46077 | F3: 214
A4: =IFERROR(__xludf.DUMMYFUNCTION("""COMPUTED_VALUE"""),46078.00643018518) -> 46078.006 | B4: =IFERROR(__xludf.DUMMYFUNCTION("""COMPUTED_VALUE"""),300.0) -> 300 | C4: =IFERROR(__xludf.DUMMYFUNCTION("""COMPUTED_VALUE"""),29.805) -> 29.805 | D4: 270.195 | E4: 46078 | F4: 300
A5: =IFERROR(__xludf.DUMMYFUNCTION("""COMPUTED_VALUE"""),46080.70734325231) -> 46080.707 | B5: =IFERROR(__xludf.DUMMYFUNCTION("""COMPUTED_VALUE"""),120.0) -> 120 | C5: =IFERROR(__xludf.DUMMYFUNCTION("""COMPUTED_VALUE"""),15.418999999999997) -> 15.419 | D5: 104.581 | E5: 46080 | F5: 120
A6: =IFERROR(__xludf.DUMMYFUNCTION("""COMPUTED_VALUE"""),46083.52029925926) -> 46083.52 | B6: =IFERROR(__xludf.DUMMYFUNCTION("""COMPUTED_VALUE"""),102.0) -> 102 | C6: =IFERROR(__xludf.DUMMYFUNCTION("""COMPUTED_VALUE"""),8.388000000000003) -> 8.388 | D6: 93.612 | E6: 46093 | F6: 102
A7: =IFERROR(__xludf.DUMMYFUNCTION("""COMPUTED_VALUE"""),46112.6378921412) -> 46112.638 | B7: =IFERROR(__xludf.DUMMYFUNCTION("""COMPUTED_VALUE"""),630.0) -> 630 | C7: =IFERROR(__xludf.DUMMYFUNCTION("""COMPUTED_VALUE"""),72.57500000000002) -> 72.575 | D7: 557.425 | E7: 46112 | F7: 236 | G7: 335335
A8: =IFERROR(__xludf.DUMMYFUNCTION("""COMPUTED_VALUE"""),46115.50622765046) -> 46115.506 | B8: =IFERROR(__xludf.DUMMYFUNCTION("""COMPUTED_VALUE"""),401.0) -> 401 | C8: =IFERROR(__xludf.DUMMYFUNCTION("""COMPUTED_VALUE"""),42.432) -> 42.432 | D8: 358.568 | E8: 46112 | F8: 295 | G8: 418680
A9: =IFERROR(__xludf.DUMMYFUNCTION("""COMPUTED_VALUE"""),46115.5404390625) -> 46115.54 | B9: =IFERROR(__xludf.DUMMYFUNCTION("""COMPUTED_VALUE"""),50.0) -> 50 | C9: =IFERROR(__xludf.DUMMYFUNCTION("""COMPUTED_VALUE"""),5.329999999999998) -> 5.33 | D9: 44.67 | E9: 46115 | F9: 341.4 | G9: 379667
A10: =IFERROR(__xludf.DUMMYFUNCTION("""COMPUTED_VALUE"""),46122.48950604167) -> 46122.49 | B10: =IFERROR(__xludf.DUMMYFUNCTION("""COMPUTED_VALUE"""),220.0) -> 220 | C10: =IFERROR(__xludf.DUMMYFUNCTION("""COMPUTED_VALUE"""),30.260000000000005) -> 30.26 | D10: 189.74 | E10: 46129 | F10: 189.74 | G10: 268483
A11: =IFERROR(__xludf.DUMMYFUNCTION("""COMPUTED_VALUE"""),46147.36818777778) -> 46147.368 | B11: =IFERROR(__xludf.DUMMYFUNCTION("""COMPUTED_VALUE"""),57.0) -> 57 | C11: =IFERROR(__xludf.DUMMYFUNCTION("""COMPUTED_VALUE"""),10.29) -> 10.29 | D11: 46.71 | E11: 46147 | F11: 46.71 | G11: 65600
A12: =IFERROR(__xludf.DUMMYFUNCTION("""COMPUTED_VALUE"""),46170.44907133102) -> 46170.449 | B12: =IFERROR(__xludf.DUMMYFUNCTION("""COMPUTED_VALUE"""),1130.5) -> 1130.5 | C12: =IFERROR(__xludf.DUMMYFUNCTION("""COMPUTED_VALUE"""),138.913) -> 138.913 | D12: 991.587 | E12: 46170 | F12: 991.58 | G12: 991588
A13: =IFERROR(__xludf.DUMMYFUNCTION("""COMPUTED_VALUE"""),46184.45560317129) -> 46184.456 | B13: =IFERROR(__xludf.DUMMYFUNCTION("""COMPUTED_VALUE"""),610.0) -> 610 | C13: =IFERROR(__xludf.DUMMYFUNCTION("""COMPUTED_VALUE"""),104.67039000000001) -> 104.67039 | D13: 505.32961 | E13: 46174 | F13: 293 | G13: 419442
A14: =IFERROR(__xludf.DUMMYFUNCTION("""COMPUTED_VALUE"""),46192.47812678241) -> 46192.478 | B14: =IFERROR(__xludf.DUMMYFUNCTION("""COMPUTED_VALUE"""),285.0) -> 285 | C14: =IFERROR(__xludf.DUMMYFUNCTION("""COMPUTED_VALUE"""),50.260000000000005) -> 50.26 | D14: 234.74 | E14: 46184 | F14: 110 | G14: 159500
A15: =IFERROR(__xludf.DUMMYFUNCTION("""COMPUTED_VALUE"""),46196.89307288194) -> 46196.893 | B15: =IFERROR(__xludf.DUMMYFUNCTION("""COMPUTED_VALUE"""),332.0) -> 332 | C15: =IFERROR(__xludf.DUMMYFUNCTION("""COMPUTED_VALUE"""),35.41165681824555) -> 35.411657 | D15: 296.58834 | E15: 46184 | F15: 110 | G15: 159500
E16: 46192 | F16: 255 | G16: 370400
E17: 46197 | F17: 200 | H17: eft a caja para puffco 12

Sheet MARSHAL LEAN
A1: Fecha | B1: Total de pedido | C1: Comision | D1: a Rendir | E1: Fecha Pago | F1: Pago | H1: SALDO ACTUAL: | I1: =SUM(D2:D1000) - SUM(F2:F1000) -> 2551.5 | K1: Observaciones
A2: =IFERROR(__xludf.DUMMYFUNCTION("QUERY(Pedidos!A2:E1000, ""SELECT A, D, (E/0) WHERE lower(B) CONTAINS 'marshal lean'"", 0)"),"") | B2: =IFERROR(__xludf.DUMMYFUNCTION("""COMPUTED_VALUE"""),"") | C2: =IFERROR(__xludf.DUMMYFUNCTION("""COMPUTED_VALUE"""),"quotient(0())") -> quotient(0()) | D2: {=IF(B2:B1000="", "", B2:B1000 - C2:C1000)} | E2: 46023 | F2: 0 | G2: $ | H2: TC
A3: =IFERROR(__xludf.DUMMYFUNCTION("""COMPUTED_VALUE"""),46066.69084402778) -> 46066.691 | B3: =IFERROR(__xludf.DUMMYFUNCTION("""COMPUTED_VALUE"""),1855.0) -> 1855 | D3: 1855 | E3: 46098 | F3: 800
A4: =IFERROR(__xludf.DUMMYFUNCTION("""COMPUTED_VALUE"""),46077.64660891204) -> 46077.647 | B4: =IFERROR(__xludf.DUMMYFUNCTION("""COMPUTED_VALUE"""),1410.0) -> 1410 | D4: 1410 | E4: 46098 | F4: 870 | G4: 1244000 | H4: 1430
A5: =IFERROR(__xludf.DUMMYFUNCTION("""COMPUTED_VALUE"""),46081.6443337963) -> 46081.644 | B5: =IFERROR(__xludf.DUMMYFUNCTION("""COMPUTED_VALUE"""),430.0) -> 430 | D5: 430 | E5: 46107 | F5: 100 | K5: eft
A6: =IFERROR(__xludf.DUMMYFUNCTION("""COMPUTED_VALUE"""),46098.61810814815) -> 46098.618 | B6: =IFERROR(__xludf.DUMMYFUNCTION("""COMPUTED_VALUE"""),1858.0) -> 1858 | D6: 1858 | E6: 46108 | F6: 1100 | K6: eft
A7: =IFERROR(__xludf.DUMMYFUNCTION("""COMPUTED_VALUE"""),46112.68195954861) -> 46112.682 | B7: =IFERROR(__xludf.DUMMYFUNCTION("""COMPUTED_VALUE"""),460.0) -> 460 | D7: 460 | E7: 46108 | F7: 400 | G7: 566000
A8: =IFERROR(__xludf.DUMMYFUNCTION("""COMPUTED_VALUE"""),46112.68247824074) -> 46112.682 | B8: =IFERROR(__xludf.DUMMYFUNCTION("""COMPUTED_VALUE"""),80.0) -> 80 | D8: 80 | E8: 46113 | F8: 500 | G8: 700000
A9: =IFERROR(__xludf.DUMMYFUNCTION("""COMPUTED_VALUE"""),46113.54717881944) -> 46113.547 | B9: =IFERROR(__xludf.DUMMYFUNCTION("""COMPUTED_VALUE"""),1973.0) -> 1973 | D9: 1973 | E9: 46113 | F9: 300 | K9: eft
A10: =IFERROR(__xludf.DUMMYFUNCTION("""COMPUTED_VALUE"""),46122.72316917824) -> 46122.723 | B10: =IFERROR(__xludf.DUMMYFUNCTION("""COMPUTED_VALUE"""),1007.0) -> 1007 | D10: 1007 | E10: 46130 | F10: 700 | K10: eft
A11: =IFERROR(__xludf.DUMMYFUNCTION("""COMPUTED_VALUE"""),46130.444627777775) -> 46130.445 | B11: =IFERROR(__xludf.DUMMYFUNCTION("""COMPUTED_VALUE"""),895.0) -> 895 | D11: 895 | E11: 46136 | F11: 1600 | K11: eft
A12: =IFERROR(__xludf.DUMMYFUNCTION("""COMPUTED_VALUE"""),46136.974764756946) -> 46136.975 | B12: =IFERROR(__xludf.DUMMYFUNCTION("""COMPUTED_VALUE"""),1654.0) -> 1654 | D12: 1654 | E12: 46154 | F12: 1200 | K12: eft
A13: =IFERROR(__xludf.DUMMYFUNCTION("""COMPUTED_VALUE"""),46146.639216759264) -> 46146.639 | B13: =IFERROR(__xludf.DUMMYFUNCTION("""COMPUTED_VALUE"""),760.0) -> 760 | D13: 760 | E13: 46164 | F13: 1600 | K13: eft
A14: =IFERROR(__xludf.DUMMYFUNCTION("""COMPUTED_VALUE"""),46154.67779767361) -> 46154.678 | B14: =IFERROR(__xludf.DUMMYFUNCTION("""COMPUTED_VALUE"""),781.5) -> 781.5 | D14: 781.5 | E14: 46164 | F14: 20
A15: =IFERROR(__xludf.DUMMYFUNCTION("""COMPUTED_VALUE"""),46164.677052708335) -> 46164.677 | B15: =IFERROR(__xludf.DUMMYFUNCTION("""COMPUTED_VALUE"""),2150.0) -> 2150 | D15: 2150 | E15: 46183 | F15: 1220 | K15: eft
A16: =IFERROR(__xludf.DUMMYFUNCTION("""COMPUTED_VALUE"""),46171.580637060186) -> 46171.581 | B16: =IFERROR(__xludf.DUMMYFUNCTION("""COMPUTED_VALUE"""),1184.0) -> 1184 | D16: 1184 | E16: 46191 | F16: 1300 | K16: eft
A17: =IFERROR(__xludf.DUMMYFUNCTION("""COMPUTED_VALUE"""),46183.99001662037) -> 46183.99 | B17: =IFERROR(__xludf.DUMMYFUNCTION("""COMPUTED_VALUE"""),910.0) -> 910 | D17: 910 | E17: 46206 | F17: 263 | G17: 400000
A18: =IFERROR(__xludf.DUMMYFUNCTION("""COMPUTED_VALUE"""),46191.66817881945) -> 46191.668 | B18: =IFERROR(__xludf.DUMMYFUNCTION("""COMPUTED_VALUE"""),410.0) -> 410 | D18: 410 | E18: 46207 | F18: 240 | G18: 364800
A19: =IFERROR(__xludf.DUMMYFUNCTION("""COMPUTED_VALUE"""),46210.79241748843) -> 46210.792 | B19: =IFERROR(__xludf.DUMMYFUNCTION("""COMPUTED_VALUE"""),1225.0) -> 1225 | D19: 1225 | E19: 46208 | F19: 345 | G19: 520950
A20: =IFERROR(__xludf.DUMMYFUNCTION("""COMPUTED_VALUE"""),46210.79332670139) -> 46210.793 | B20: =IFERROR(__xludf.DUMMYFUNCTION("""COMPUTED_VALUE"""),222.0) -> 222 | D20: 222 | E20: 46216 | F20: 240 | G20: 366000
A21: =IFERROR(__xludf.DUMMYFUNCTION("""COMPUTED_VALUE"""),46224.493222303245) -> 46224.493 | B21: =IFERROR(__xludf.DUMMYFUNCTION("""COMPUTED_VALUE"""),755.0) -> 755 | D21: 755 | E21: 46219 | F21: 3170 | K21: eft
E22: 46219 | F22: 830 | G22: 1265750
E23: 46237 | F23: 60
E24: 46239 | F24: 300 | G24: 462000 | K24: transfer a RUSSO GER
E25: 46261 | F25: 10
E26: 46261 | F26: 110 | K26: ong
E27: 46287 | F27: 190 | K27: rasta paz copa

Sheet Ale Ong Cordoba
A1: Fecha | B1: Total de pedido | C1: Comision | D1: a Rendir | E1: Fecha Pago | F1: Pago | H1: SALDO ACTUAL: | I1: =SUM(D2:D1000) - SUM(F2:F1000) -> 482
A2: =IFERROR(__xludf.DUMMYFUNCTION("QUERY(Pedidos!A2:E1000, ""SELECT A, D, (E/0) WHERE lower(B) CONTAINS 'ale ong'"", 0)"),"") | B2: =IFERROR(__xludf.DUMMYFUNCTION("""COMPUTED_VALUE"""),"") | C2: =IFERROR(__xludf.DUMMYFUNCTION("""COMPUTED_VALUE"""),"quotient(0())") -> quotient(0()) | D2: {=IF(B2:B1000="", "", B2:B1000 - C2:C1000)} | E2: 46023 | F2: 0
A3: =IFERROR(__xludf.DUMMYFUNCTION("""COMPUTED_VALUE"""),46085.38190596065) -> 46085.382 | B3: =IFERROR(__xludf.DUMMYFUNCTION("""COMPUTED_VALUE"""),1309.0) -> 1309 | D3: 1309 | E3: 46097 | F3: 842 | H3: 1200000 | I3: 1425
A4: =IFERROR(__xludf.DUMMYFUNCTION("""COMPUTED_VALUE"""),46085.387696423604) -> 46085.388 | B4: =IFERROR(__xludf.DUMMYFUNCTION("""COMPUTED_VALUE"""),37.0) -> 37 | D4: 37 | E4: 46099 | F4: 524 | H4: 752400 | I4: 1425
A5: =IFERROR(__xludf.DUMMYFUNCTION("""COMPUTED_VALUE"""),46124.94814658565) -> 46124.948 | B5: =IFERROR(__xludf.DUMMYFUNCTION("""COMPUTED_VALUE"""),1080.0) -> 1080 | D5: 1080 | E5: 46123 | F5: 251 | H5: 350000 | I5: 1390
A6: =IFERROR(__xludf.DUMMYFUNCTION("""COMPUTED_VALUE"""),46134.540712013884) -> 46134.541 | B6: =IFERROR(__xludf.DUMMYFUNCTION("""COMPUTED_VALUE"""),550.0) -> 550 | D6: 550 | E6: 46123 | F6: 302 | H6: 420000 | I6: 1390
A7: =IFERROR(__xludf.DUMMYFUNCTION("""COMPUTED_VALUE"""),46239.8355009838) -> 46239.836 | B7: =IFERROR(__xludf.DUMMYFUNCTION("""COMPUTED_VALUE"""),482.0) -> 482 | D7: 482 | E7: 46146 | F7: 1057 | H7: 1485085 | I7: 1390

Sheet Coco Salta
A1: Fecha | B1: Total de pedido | C1: Comision | D1: a Rendir | E1: Fecha Pago | F1: Pago | H1: SALDO ACTUAL: | I1: =SUM(D2:D1000) - SUM(F2:F1000) -> 2083.0266
A2: =IFERROR(__xludf.DUMMYFUNCTION("QUERY(Pedidos!A2:E1000, ""SELECT A, D, (E/2) WHERE lower(B) CONTAINS 'coco salta'"", 0)"),"") | B2: =IFERROR(__xludf.DUMMYFUNCTION("""COMPUTED_VALUE"""),"") | C2: =IFERROR(__xludf.DUMMYFUNCTION("""COMPUTED_VALUE"""),"quotient(2())") -> quotient(2()) | D2: {=IF(B2:B1000="", "", B2:B1000 - C2:C1000)} | E2: 46023 | F2: 0 | H2: TC
A3: =IFERROR(__xludf.DUMMYFUNCTION("""COMPUTED_VALUE"""),46065.572970092595) -> 46065.573 | B3: =IFERROR(__xludf.DUMMYFUNCTION("""COMPUTED_VALUE"""),440.0) -> 440 | C3: =IFERROR(__xludf.DUMMYFUNCTION("""COMPUTED_VALUE"""),52.58399999999999) -> 52.584 | D3: 387.416 | E3: 46121 | F3: 500 | G3: 710000 | H3: =G3/F3 -> 1420
A4: =IFERROR(__xludf.DUMMYFUNCTION("""COMPUTED_VALUE"""),46094.39509277778) -> 46094.395 | B4: =IFERROR(__xludf.DUMMYFUNCTION("""COMPUTED_VALUE"""),2868.0) -> 2868 | C4: =IFERROR(__xludf.DUMMYFUNCTION("""COMPUTED_VALUE"""),402.93408756199864) -> 402.93409 | D4: 2465.0659 | E4: 46122 | F4: 400 | G4: 568000 | H4: 1420
A5: =IFERROR(__xludf.DUMMYFUNCTION("""COMPUTED_VALUE"""),46099.63228344907) -> 46099.632 | B5: =IFERROR(__xludf.DUMMYFUNCTION("""COMPUTED_VALUE"""),920.0) -> 920 | C5: =IFERROR(__xludf.DUMMYFUNCTION("""COMPUTED_VALUE"""),112.43128999999998) -> 112.43129 | D5: 807.56871 | E5: 46150 | F5: 400
A6: =IFERROR(__xludf.DUMMYFUNCTION("""COMPUTED_VALUE"""),46100.455824467586) -> 46100.456 | B6: =IFERROR(__xludf.DUMMYFUNCTION("""COMPUTED_VALUE"""),75.0) -> 75 | C6: =IFERROR(__xludf.DUMMYFUNCTION("""COMPUTED_VALUE"""),8.527000000000001) -> 8.527 | D6: 66.473 | E6: 46154 | F6: 1800
A7: =IFERROR(__xludf.DUMMYFUNCTION("""COMPUTED_VALUE"""),46210.69943743056) -> 46210.699 | B7: =IFERROR(__xludf.DUMMYFUNCTION("""COMPUTED_VALUE"""),2016.0) -> 2016 | C7: =IFERROR(__xludf.DUMMYFUNCTION("""COMPUTED_VALUE"""),228.429) -> 228.429 | D7: 1787.571 | E7: 46213 | F7: 1200 | J7: eft a nachito, se agarro 300 dls para cubrir viajes hasta hoy.
A8: =IFERROR(__xludf.DUMMYFUNCTION("""COMPUTED_VALUE"""),46210.70009377315) -> 46210.7 | B8: =IFERROR(__xludf.DUMMYFUNCTION("""COMPUTED_VALUE"""),30.0) -> 30 | C8: =IFERROR(__xludf.DUMMYFUNCTION("""COMPUTED_VALUE"""),6.324999999999999) -> 6.325 | D8: 23.675 | E8: 46279 | F8: 1900 | J8: 3 depositos por banco al colo
A9: =IFERROR(__xludf.DUMMYFUNCTION("""COMPUTED_VALUE"""),46210.71191604167) -> 46210.712 | B9: =IFERROR(__xludf.DUMMYFUNCTION("""COMPUTED_VALUE"""),170.0) -> 170 | C9: =IFERROR(__xludf.DUMMYFUNCTION("""COMPUTED_VALUE"""),32.19) -> 32.19 | D9: 137.81 | E9: 46280 | F9: -843.42 | J9: ACOMODADO COMO DISTRIBUIDOR
A10: =IFERROR(__xludf.DUMMYFUNCTION("""COMPUTED_VALUE"""),46283.81863849537) -> 46283.819 | B10: =IFERROR(__xludf.DUMMYFUNCTION("""COMPUTED_VALUE"""),2012.0) -> 2012 | C10: =IFERROR(__xludf.DUMMYFUNCTION("""COMPUTED_VALUE"""),247.97300999999996) -> 247.97301 | D10: 1764.027

Sheet Nahu La comarca
A1: 1570+ | B1: Total de pedido | C1: Comision | D1: a Rendir | E1: Fecha Pago | F1: Pago | H1: SALDO ACTUAL: | I1: =SUM(D2:D1000) - SUM(F2:F1000) -> 733
A2: =IFERROR(__xludf.DUMMYFUNCTION("QUERY(Pedidos!A2:E1000, ""SELECT A, D, (E/0) WHERE lower(B) CONTAINS 'nahu la comarca'"", 0)"),"") | B2: =IFERROR(__xludf.DUMMYFUNCTION("""COMPUTED_VALUE"""),"") | C2: =IFERROR(__xludf.DUMMYFUNCTION("""COMPUTED_VALUE"""),"quotient(0())") -> quotient(0()) | D2: {=IF(B2:B1000="", "", B2:B1000 - C2:C1000)} | E2: 46023 | F2: 0
A3: =IFERROR(__xludf.DUMMYFUNCTION("""COMPUTED_VALUE"""),46080.84406765046) -> 46080.844 | B3: =IFERROR(__xludf.DUMMYFUNCTION("""COMPUTED_VALUE"""),1270.0) -> 1270 | D3: 1270 | E3: 46086 | F3: 500 | J3: Eft en mano luke
A4: =IFERROR(__xludf.DUMMYFUNCTION("""COMPUTED_VALUE"""),46080.84743357639) -> 46080.847 | B4: =IFERROR(__xludf.DUMMYFUNCTION("""COMPUTED_VALUE"""),172.0) -> 172 | D4: 172 | E4: 46114 | F4: 1000 | J4: eft en mano luke
A5: =IFERROR(__xludf.DUMMYFUNCTION("""COMPUTED_VALUE"""),46085.85309575232) -> 46085.853 | B5: =IFERROR(__xludf.DUMMYFUNCTION("""COMPUTED_VALUE"""),628.0) -> 628 | D5: 628 | E5: 46114 | F5: 342 | J5: eft en mano luke
A6: =IFERROR(__xludf.DUMMYFUNCTION("""COMPUTED_VALUE"""),46114.68181039352) -> 46114.682 | B6: =IFERROR(__xludf.DUMMYFUNCTION("""COMPUTED_VALUE"""),1040.0) -> 1040 | D6: 1040 | E6: 46163 | F6: 1000 | J6: eft en mano luke
A7: =IFERROR(__xludf.DUMMYFUNCTION("""COMPUTED_VALUE"""),46114.683501793974) -> 46114.683 | B7: =IFERROR(__xludf.DUMMYFUNCTION("""COMPUTED_VALUE"""),28.0) -> 28 | D7: 28 | E7: 46185 | F7: 1000 | J7: eft en mano luke al colo
A8: =IFERROR(__xludf.DUMMYFUNCTION("""COMPUTED_VALUE"""),46163.50088971065) -> 46163.501 | B8: =IFERROR(__xludf.DUMMYFUNCTION("""COMPUTED_VALUE"""),3001.0) -> 3001 | D8: 3001 | E8: 46185 | F8: 166 | J8: eft en mano luke al colo
A9: =IFERROR(__xludf.DUMMYFUNCTION("""COMPUTED_VALUE"""),46216.47186788195) -> 46216.472 | B9: =IFERROR(__xludf.DUMMYFUNCTION("""COMPUTED_VALUE"""),400.0) -> 400 | D9: 400 | E9: 46185 | F9: 190 | J9: devolucion de equipo roto
E10: 46216 | F10: 160
E11: 46216 | F11: 500 | J11: usar parte para alquiler 300 y quedan 200 para gastos o retiro de carga analizar
E12: 46253 | F12: 948 | J12: eft
E55: 4

Sheet Leloir ONG
A1: Fecha | B1: Total de pedido | C1: Comision | D1: a Rendir | E1: Fecha Pago | F1: Pago | H1: SALDO ACTUAL: | I1: =SUM(D2:D1000) - SUM(F2:F1000) -> 1315
A2: =IFERROR(__xludf.DUMMYFUNCTION("QUERY(Pedidos!A2:E1000, ""SELECT A, D, (E/0) WHERE lower(B) CONTAINS 'leloir ong'"", 0)"),"") | B2: =IFERROR(__xludf.DUMMYFUNCTION("""COMPUTED_VALUE"""),"") | C2: =IFERROR(__xludf.DUMMYFUNCTION("""COMPUTED_VALUE"""),"quotient(0())") -> quotient(0()) | D2: {=IF(B2:B1000="", "", B2:B1000 - C2:C1000)} | E2: 46023 | F2: 0
A3: =IFERROR(__xludf.DUMMYFUNCTION("""COMPUTED_VALUE"""),46065.55909001157) -> 46065.559 | B3: =IFERROR(__xludf.DUMMYFUNCTION("""COMPUTED_VALUE"""),1315.0) -> 1315 | D3: 1315 | E3: 46085 | F3: 480 | H3: 732720 | I3: =H3/F3 -> 1526.5
A4: =IFERROR(__xludf.DUMMYFUNCTION("""COMPUTED_VALUE"""),46080.81749991898) -> 46080.817 | B4: =IFERROR(__xludf.DUMMYFUNCTION("""COMPUTED_VALUE"""),450.0) -> 450 | D4: 450 | E4: 46132 | F4: 390 | H4: 552000 | I4: =H4/F4 -> 1415.3846
A5: =IFERROR(__xludf.DUMMYFUNCTION("""COMPUTED_VALUE"""),46084.519517002314) -> 46084.52 | B5: =IFERROR(__xludf.DUMMYFUNCTION("""COMPUTED_VALUE"""),30.0) -> 30 | D5: 30 | E5: 46263 | F5: 1100 | G5: 1710300 | H5: mhflia | I5: tranfer colo
A6: =IFERROR(__xludf.DUMMYFUNCTION("""COMPUTED_VALUE"""),46127.448699155095) -> 46127.449 | B6: =IFERROR(__xludf.DUMMYFUNCTION("""COMPUTED_VALUE"""),390.0) -> 390 | D6: 390
A7: =IFERROR(__xludf.DUMMYFUNCTION("""COMPUTED_VALUE"""),46263.39644988426) -> 46263.396 | B7: =IFERROR(__xludf.DUMMYFUNCTION("""COMPUTED_VALUE"""),1060.0) -> 1060 | D7: 1060
A8: =IFERROR(__xludf.DUMMYFUNCTION("""COMPUTED_VALUE"""),46263.403012222225) -> 46263.403 | B8: =IFERROR(__xludf.DUMMYFUNCTION("""COMPUTED_VALUE"""),40.0) -> 40 | D8: 40

Sheet Kanario
A1: Fecha | B1: Total de pedido | C1: Comision | D1: a Rendir | E1: Fecha Pago | F1: Pago | H1: SALDO ACTUAL: | I1: =SUM(D2:D1000) - SUM(F2:F1000) -> 2909.6785
A2: =IFERROR(__xludf.DUMMYFUNCTION("QUERY(Pedidos!A2:E1000, ""SELECT A, D, (E/2) WHERE lower(B) CONTAINS 'kanario'"", 0)"),"") | B2: =IFERROR(__xludf.DUMMYFUNCTION("""COMPUTED_VALUE"""),"") | C2: =IFERROR(__xludf.DUMMYFUNCTION("""COMPUTED_VALUE"""),"quotient(2())") -> quotient(2()) | D2: {=IF(B2:B1000="", "", B2:B1000 - C2:C1000)} | E2: 46023 | F2: 0
A3: =IFERROR(__xludf.DUMMYFUNCTION("""COMPUTED_VALUE"""),46083.91235726852) -> 46083.912 | B3: =IFERROR(__xludf.DUMMYFUNCTION("""COMPUTED_VALUE"""),4257.0) -> 4257 | C3: =IFERROR(__xludf.DUMMYFUNCTION("""COMPUTED_VALUE"""),625.859) -> 625.859 | D3: 3631.141 | E3: 46086 | F3: 214.18 | H3: 300000 | I3: =H3/F3 -> 1400.691
A4: =IFERROR(__xludf.DUMMYFUNCTION("""COMPUTED_VALUE"""),46100.81657142361) -> 46100.817 | B4: =IFERROR(__xludf.DUMMYFUNCTION("""COMPUTED_VALUE"""),1480.0) -> 1480 | C4: =IFERROR(__xludf.DUMMYFUNCTION("""COMPUTED_VALUE"""),183.69382631659857) -> 183.69383 | D4: 1296.3062 | E4: 46104 | F4: 210 | H4: 300000 | I4: =H4/F4 -> 1428.5714
A5: =IFERROR(__xludf.DUMMYFUNCTION("""COMPUTED_VALUE"""),46134.94462987268) -> 46134.945 | B5: =IFERROR(__xludf.DUMMYFUNCTION("""COMPUTED_VALUE"""),1485.0) -> 1485 | C5: =IFERROR(__xludf.DUMMYFUNCTION("""COMPUTED_VALUE"""),188.58864) -> 188.58864 | D5: 1296.4114 | E5: 46105 | F5: 245 | H5: 350000 | I5: =H5/F5 -> 1428.5714
E6: 46107 | F6: 52 | H6: 75000 | I6: =H6/F6 -> 1442.3077
E7: 46109 | F7: 70 | H7: 100000 | I7: =H7/F7 -> 1428.5714
E8: 46112 | F8: 99 | H8: 140000 | I8: =H8/F8 -> 1414.1414
E9: 46119 | F9: 104 | H9: 145000 | I9: =H9/F9 -> 1394.2308
E10: 46122 | F10: 302 | H10: 420000 | I10: =H10/F10 -> 1390.7285
E11: 46124 | F11: 50 | H11: 70000 | I11: =H11/F11 -> 1400
E12: 46127 | F12: 90 | H12: 127500 | I12: 1415
E13: 46139 | F13: 142 | H13: 200000 | I13: 1415
E14: 46141 | F14: 26
E15: 46147 | F15: 300 | H15: 426000
E16: 46150 | F16: 170 | H16: 240000
E17: 46192 | F17: 940 | J17: corresponde a devolucion de mercaderia 2 PEAK PRO 2 PRO LINK
E18: 46245 | F18: 300 | H18: 465000

Sheet Alan
A1: Fecha | B1: Total de pedido | C1: Comision | D1: a Rendir | E1: Fecha Pago | F1: Pago | H1: SALDO ACTUAL: | I1: =SUM(D2:D1000) - SUM(F2:F1000) -> 950.23259
A2: =IFERROR(__xludf.DUMMYFUNCTION("QUERY(Pedidos!A2:E1000, ""SELECT A, D, (E/2) WHERE lower(B) CONTAINS 'alan'"", 0)"),"") | B2: =IFERROR(__xludf.DUMMYFUNCTION("""COMPUTED_VALUE"""),"") | C2: =IFERROR(__xludf.DUMMYFUNCTION("""COMPUTED_VALUE"""),"quotient(2())") -> quotient(2()) | D2: {=IF(B2:B1000="", "", B2:B1000 - C2:C1000)} | E2: 46023 | F2: 0
A3: =IFERROR(__xludf.DUMMYFUNCTION("""COMPUTED_VALUE"""),46086.799596805555) -> 46086.8 | B3: =IFERROR(__xludf.DUMMYFUNCTION("""COMPUTED_VALUE"""),386.0) -> 386 | C3: =IFERROR(__xludf.DUMMYFUNCTION("""COMPUTED_VALUE"""),53.245999999999995) -> 53.246 | D3: 332.754 | E3: 46087 | F3: 339
A4: =IFERROR(__xludf.DUMMYFUNCTION("""COMPUTED_VALUE"""),46143.53343688657) -> 46143.533 | B4: =IFERROR(__xludf.DUMMYFUNCTION("""COMPUTED_VALUE"""),2527.0) -> 2527 | C4: =IFERROR(__xludf.DUMMYFUNCTION("""COMPUTED_VALUE"""),376.03511843899423) -> 376.03512 | D4: 2150.9649 | E4: 46142 | F4: 270 | G4: 360000
A5: =IFERROR(__xludf.DUMMYFUNCTION("""COMPUTED_VALUE"""),46144.4414979861) -> 46144.442 | B5: =IFERROR(__xludf.DUMMYFUNCTION("""COMPUTED_VALUE"""),900.0) -> 900 | C5: =IFERROR(__xludf.DUMMYFUNCTION("""COMPUTED_VALUE"""),91.262) -> 91.262 | D5: 808.738 | E5: 46151 | F5: 440 | G5: 616000
A6: =IFERROR(__xludf.DUMMYFUNCTION("""COMPUTED_VALUE"""),46163.51032546296) -> 46163.51 | B6: =IFERROR(__xludf.DUMMYFUNCTION("""COMPUTED_VALUE"""),2850.0) -> 2850 | C6: =IFERROR(__xludf.DUMMYFUNCTION("""COMPUTED_VALUE"""),467.22429) -> 467.22429 | D6: 2382.7757 | E6: 46152 | F6: 200 | G6: 240000
E7: 46164 | F7: 147 | G7: 210000
E8: 46164 | F8: 300 | G8: 426000 | K8: eft a nachito pago deuda con nachito
E9: 46164 | F9: 147 | G9: 210000
E10: 46165 | F10: 60 | G10: 85800
E11: 46165 | F11: 200 | G11: 285000
E12: 46165 | F12: 647 | G12: 921925
E13: 46176 | F13: 400 | G13: 574000
E14: 46181 | F14: 210 | G14: 302400
E15: 46183 | F15: 180 | G15: 257400
E16: 46192 | F16: 300 | G16: 438000
E17: 46200 | F17: 385 | G17: 583275
E18: 46256 | F18: 500

Sheet Guille naesa
A1: Fecha | B1: Total de pedido | C1: Comision | D1: a Rendir | E1: Fecha Pago | F1: Pago | H1: SALDO ACTUAL: | I1: =SUM(D2:D1000) - SUM(F2:F1000) -> 2912.7268
A2: =IFERROR(__xludf.DUMMYFUNCTION("QUERY(Pedidos!A2:E1000, ""SELECT A, D, (E/2) WHERE lower(B) CONTAINS 'guille naesa'"", 0)"),"") | B2: =IFERROR(__xludf.DUMMYFUNCTION("""COMPUTED_VALUE"""),"") | C2: =IFERROR(__xludf.DUMMYFUNCTION("""COMPUTED_VALUE"""),"quotient(2())") -> quotient(2()) | D2: {=IF(B2:B1000="", "", B2:B1000 - C2:C1000)} | E2: 46023 | F2: 0
A3: =IFERROR(__xludf.DUMMYFUNCTION("""COMPUTED_VALUE"""),46088.94043388889) -> 46088.94 | B3: =IFERROR(__xludf.DUMMYFUNCTION("""COMPUTED_VALUE"""),350.0) -> 350 | C3: =IFERROR(__xludf.DUMMYFUNCTION("""COMPUTED_VALUE"""),43.11600000000001) -> 43.116 | D3: 306.884 | E3: 46169 | F3: 306.88
A4: =IFERROR(__xludf.DUMMYFUNCTION("""COMPUTED_VALUE"""),46176.918002743056) -> 46176.918 | B4: =IFERROR(__xludf.DUMMYFUNCTION("""COMPUTED_VALUE"""),1170.0) -> 1170 | C4: =IFERROR(__xludf.DUMMYFUNCTION("""COMPUTED_VALUE"""),140.80300000000003) -> 140.803 | D4: 1029.197 | E4: 46183 | F4: 1000 | J4: a cuenta para Sixtar dos envios USD 1919 10-6 (retiros del 8-6 y 9-6)
A5: =IFERROR(__xludf.DUMMYFUNCTION("""COMPUTED_VALUE"""),46196.713611886575) -> 46196.714 | B5: =IFERROR(__xludf.DUMMYFUNCTION("""COMPUTED_VALUE"""),190.0) -> 190 | C5: =IFERROR(__xludf.DUMMYFUNCTION("""COMPUTED_VALUE"""),22.656000000000006) -> 22.656 | D5: 167.344 | E5: 46196 | F5: 168
A6: =IFERROR(__xludf.DUMMYFUNCTION("""COMPUTED_VALUE"""),46214.704208344905) -> 46214.704 | B6: =IFERROR(__xludf.DUMMYFUNCTION("""COMPUTED_VALUE"""),1200.0) -> 1200 | C6: =IFERROR(__xludf.DUMMYFUNCTION("""COMPUTED_VALUE"""),139.93) -> 139.93 | D6: 1060.07 | E6: 46214 | F6: 600 | J6: eft para pagar alquiler 900 (pagamos dos meses juntos)
A7: =IFERROR(__xludf.DUMMYFUNCTION("""COMPUTED_VALUE"""),46224.58329664352) -> 46224.583 | B7: =IFERROR(__xludf.DUMMYFUNCTION("""COMPUTED_VALUE"""),700.0) -> 700 | C7: =IFERROR(__xludf.DUMMYFUNCTION("""COMPUTED_VALUE"""),51.778700000000015) -> 51.7787 | D7: 648.2213 | E7: 46224 | F7: 400 | J7: eft para colo 23-7
A8: =IFERROR(__xludf.DUMMYFUNCTION("""COMPUTED_VALUE"""),46226.6697855324) -> 46226.67 | B8: =IFERROR(__xludf.DUMMYFUNCTION("""COMPUTED_VALUE"""),2050.0) -> 2050 | C8: =IFERROR(__xludf.DUMMYFUNCTION("""COMPUTED_VALUE"""),161.42675000000003) -> 161.42675 | D8: 1888.5732 | E8: 46226 | F8: 400 | J8: eft para ahorro 25-7 llevo nachito
A9: =IFERROR(__xludf.DUMMYFUNCTION("""COMPUTED_VALUE"""),46227.69139172454) -> 46227.691 | B9: =IFERROR(__xludf.DUMMYFUNCTION("""COMPUTED_VALUE"""),3240.0) -> 3240 | C9: =IFERROR(__xludf.DUMMYFUNCTION("""COMPUTED_VALUE"""),334.01444000000004) -> 334.01444 | D9: 2905.9856 | E9: 46227 | F9: 500 | J9: eft para ahorro 25-7 llevo nachito
A10: =IFERROR(__xludf.DUMMYFUNCTION("""COMPUTED_VALUE"""),46234.340746793976) -> 46234.341 | B10: =IFERROR(__xludf.DUMMYFUNCTION("""COMPUTED_VALUE"""),2960.0) -> 2960 | C10: =IFERROR(__xludf.DUMMYFUNCTION("""COMPUTED_VALUE"""),249.06943000000007) -> 249.06943 | D10: 2710.9306 | E10: 46227 | F10: 1545 | G10: 1545000 | J10: eft para colo 25-7 llevo nachito
A11: =IFERROR(__xludf.DUMMYFUNCTION("""COMPUTED_VALUE"""),46234.87849180555) -> 46234.878 | B11: =IFERROR(__xludf.DUMMYFUNCTION("""COMPUTED_VALUE"""),1470.0) -> 1470 | C11: =IFERROR(__xludf.DUMMYFUNCTION("""COMPUTED_VALUE"""),174.91063500000004) -> 174.91064 | D11: 1295.0894 | E11: 46232 | F11: 1000 | G11: 1550000 | J11: transfer 3-8
A12: =IFERROR(__xludf.DUMMYFUNCTION("""COMPUTED_VALUE"""),46237.52281260417) -> 46237.523 | B12: =IFERROR(__xludf.DUMMYFUNCTION("""COMPUTED_VALUE"""),1100.0) -> 1100 | C12: =IFERROR(__xludf.DUMMYFUNCTION("""COMPUTED_VALUE"""),89.75819000000001) -> 89.75819 | D12: 1010.2418 | E12: 46232 | F12: 500 | G12: 780000 | J12: eft para colo lunes 3 de agosto que vuelvo de viaje / entrego nachito
A13: =IFERROR(__xludf.DUMMYFUNCTION("""COMPUTED_VALUE"""),46246.82358787037) -> 46246.824 | B13: =IFERROR(__xludf.DUMMYFUNCTION("""COMPUTED_VALUE"""),9130.0) -> 9130 | C13: =IFERROR(__xludf.DUMMYFUNCTION("""COMPUTED_VALUE"""),919.9256000000001) -> 919.9256 | D13: 8210.0744 | E13: 46234 | F13: 750 | G13: 1162500 | J13: transfer 3-8
A14: =IFERROR(__xludf.DUMMYFUNCTION("""COMPUTED_VALUE"""),46274.597082291664) -> 46274.597 | B14: =IFERROR(__xludf.DUMMYFUNCTION("""COMPUTED_VALUE"""),360.0) -> 360 | C14: =IFERROR(__xludf.DUMMYFUNCTION("""COMPUTED_VALUE"""),40.059000000000026) -> 40.059 | D14: 319.941 | E14: 46234 | F14: 1250 | G14: 1943750 | J14: eft para colo lunes 3 de agosto que vuelvo de viaje / entrego nachito
A15: =IFERROR(__xludf.DUMMYFUNCTION("""COMPUTED_VALUE"""),46279.63716791666) -> 46279.637 | B15: =IFERROR(__xludf.DUMMYFUNCTION("""COMPUTED_VALUE"""),540.0) -> 540 | C15: =IFERROR(__xludf.DUMMYFUNCTION("""COMPUTED_VALUE"""),46.83564000000002) -> 46.83564 | D15: 493.16436 | E15: 46237 | F15: 1400 | J15: eft para colo martes 4 de agosto lleva nachito
A16: =IFERROR(__xludf.DUMMYFUNCTION("""COMPUTED_VALUE"""),46294.73021109954) -> 46294.73 | B16: =IFERROR(__xludf.DUMMYFUNCTION("""COMPUTED_VALUE"""),210.0) -> 210 | C16: =IFERROR(__xludf.DUMMYFUNCTION("""COMPUTED_VALUE"""),18.109845000000007) -> 18.109845 | D16: 191.89015 | E16: 46237 | F16: 600 | G16: 930000 | J16: eft para colo martes 4 de agosto lleva nachito
E17: 46246 | F17: 2000 | J17: eft para colo giro china
E18: 46262 | F18: 1000 | J18: eft para giro china
E19: 46273 | F19: 500 | J19: eft
E20: 46274 | F20: 1000 | J20: eft
E21: 46274 | F21: 2765 | I21: devolucion de 8 peak pro, 3 travel case
E22: 46283 | F22: 1140 | I22: devolucion de 2 peak pro, 1 pro link, 4 chamber peak pro 3DXL
E23: 46294 | F23: 500 | I23: eft para retiro Sixtar

Sheet Facu Pisando
A1: Fecha | B1: Total de pedido | C1: Comision | D1: a Rendir | E1: Fecha Pago | F1: Pago | G1: TC | H1: SALDO ACTUAL: | I1: =SUM(D2:D1000) - SUM(F2:F1000) -> 7052.3677
A2: =IFERROR(__xludf.DUMMYFUNCTION("QUERY(Pedidos!A2:E1000, ""SELECT A, D, (E/2) WHERE lower(B) CONTAINS 'facu pisando'"", 0)"),"") | B2: =IFERROR(__xludf.DUMMYFUNCTION("""COMPUTED_VALUE"""),"") | C2: =IFERROR(__xludf.DUMMYFUNCTION("""COMPUTED_VALUE"""),"quotient(2())") -> quotient(2()) | D2: {=IF(B2:B1000="", "", B2:B1000 - C2:C1000)} | E2: 46023 | F2: 0
A3: =IFERROR(__xludf.DUMMYFUNCTION("""COMPUTED_VALUE"""),46092.63492619213) -> 46092.635 | B3: =IFERROR(__xludf.DUMMYFUNCTION("""COMPUTED_VALUE"""),4334.0) -> 4334 | C3: =IFERROR(__xludf.DUMMYFUNCTION("""COMPUTED_VALUE"""),578.9518090003843) -> 578.95181 | D3: 3755.0482 | E3: 46092 | F3: 305 | G3: =H3/F3 -> 1401.6393 | H3: 427500
A4: =IFERROR(__xludf.DUMMYFUNCTION("""COMPUTED_VALUE"""),46099.42049445601) -> 46099.42 | B4: =IFERROR(__xludf.DUMMYFUNCTION("""COMPUTED_VALUE"""),1220.0) -> 1220 | C4: =IFERROR(__xludf.DUMMYFUNCTION("""COMPUTED_VALUE"""),139.68786) -> 139.68786 | D4: 1080.3121 | E4: 46092 | F4: 306 | G4: =H4/F4 -> 1401.9608 | H4: 429000
A5: =IFERROR(__xludf.DUMMYFUNCTION("""COMPUTED_VALUE"""),46100.91865572916) -> 46100.919 | B5: =IFERROR(__xludf.DUMMYFUNCTION("""COMPUTED_VALUE"""),380.0) -> 380 | C5: =IFERROR(__xludf.DUMMYFUNCTION("""COMPUTED_VALUE"""),45.31200000000001) -> 45.312 | D5: 334.688 | E5: 46098 | F5: 350 | G5: =H5/F5 -> 1428.5714 | H5: 500000
A6: =IFERROR(__xludf.DUMMYFUNCTION("""COMPUTED_VALUE"""),46108.623040659724) -> 46108.623 | B6: =IFERROR(__xludf.DUMMYFUNCTION("""COMPUTED_VALUE"""),282.0) -> 282 | C6: =IFERROR(__xludf.DUMMYFUNCTION("""COMPUTED_VALUE"""),47.266000000000005) -> 47.266 | D6: 234.734 | E6: 46100 | F6: 240 | G6: =H6/F6 -> 1425.8333 | H6: 342200
A7: =IFERROR(__xludf.DUMMYFUNCTION("""COMPUTED_VALUE"""),46128.83121408565) -> 46128.831 | B7: =IFERROR(__xludf.DUMMYFUNCTION("""COMPUTED_VALUE"""),1520.0) -> 1520 | C7: =IFERROR(__xludf.DUMMYFUNCTION("""COMPUTED_VALUE"""),177.77769956177434) -> 177.7777 | D7: 1342.2223 | E7: 46101 | F7: 559 | G7: =H7/F7 -> 1431.127 | H7: 800000
A8: =IFERROR(__xludf.DUMMYFUNCTION("""COMPUTED_VALUE"""),46199.7302580787) -> 46199.73 | B8: =IFERROR(__xludf.DUMMYFUNCTION("""COMPUTED_VALUE"""),3838.0) -> 3838 | C8: =IFERROR(__xludf.DUMMYFUNCTION("""COMPUTED_VALUE"""),823.8780399999998) -> 823.87804 | D8: 3014.122 | E8: 46104 | F8: 70 | G8: =H8/F8 -> 1428.5714 | H8: 100000
A9: =IFERROR(__xludf.DUMMYFUNCTION("""COMPUTED_VALUE"""),46224.64814820602) -> 46224.648 | B9: =IFERROR(__xludf.DUMMYFUNCTION("""COMPUTED_VALUE"""),6058.0) -> 6058 | C9: =IFERROR(__xludf.DUMMYFUNCTION("""COMPUTED_VALUE"""),750.1474200000002) -> 750.14742 | D9: 5307.8526 | E9: 46108 | F9: 340 | G9: =H9/F9 -> 1414.7059 | H9: 481000
A10: =IFERROR(__xludf.DUMMYFUNCTION("""COMPUTED_VALUE"""),46228.61995699074) -> 46228.62 | B10: =IFERROR(__xludf.DUMMYFUNCTION("""COMPUTED_VALUE"""),1620.0) -> 1620 | C10: =IFERROR(__xludf.DUMMYFUNCTION("""COMPUTED_VALUE"""),185.11745999999994) -> 185.11746 | D10: 1434.8825 | E10: 46108 | F10: 600 | G10: =H10/F10 -> 1416.6667 | H10: 850000
A11: =IFERROR(__xludf.DUMMYFUNCTION("""COMPUTED_VALUE"""),46298.65582460648) -> 46298.656 | B11: =IFERROR(__xludf.DUMMYFUNCTION("""COMPUTED_VALUE"""),897.0) -> 897 | C11: =IFERROR(__xludf.DUMMYFUNCTION("""COMPUTED_VALUE"""),94.49400000000001) -> 94.494 | D11: 802.506 | E11: 46130 | F11: 270 | G11: =H11/F11 -> 1407.4074 | H11: 380000
E12: 46136 | F12: 282 | G12: =H12/F12 -> 1418.4397 | H12: 400000
E13: 46197 | F13: 1570 | G13: =H13/F13 -> 0 | K13: eft a caja para puffco 12
E14: 46220 | F14: 320 | G14: =H14/F14 -> 1525 | H14: 488000
E15: 46224 | F15: 390 | G15: =H15/F15 -> 1538.4615 | H15: 600000
E16: 46226 | F16: 100 | G16: =H16/F16 -> 1550 | H16: 155000
E17: 46231 | F17: 100 | H17: 156500
E18: 46235 | F18: 173 | H18: 269500
E19: 46240 | F19: 447 | H19: 684000 | K19: russo GER
E20: 46247 | F20: 600 | H20: 920000
E21: 46247 | F21: 1290 | K21: eft
E22: 46248 | F22: 100 | H22: 154000
E23: 46255 | F23: 100 | H23: 154000
E24: 46263 | F24: 100 | H24: 154000
E25: 46264 | F25: 150 | H25: 233500
E26: 46266 | F26: 980 | H26: 1500000
E27: 46267 | F27: 190 | H27: 292000
E28: 46288 | F28: 322 | H28: 500000

Sheet Alfredo Indajaus
A1: Fecha | B1: Total de pedido | C1: Comision | D1: a Rendir | E1: Fecha Pago | F1: Pago | G1: TC | H1: SALDO ACTUAL: | I1: =SUM(D2:D1000) - SUM(F2:F1000) -> 2480 | K1: obs
A2: =IFERROR(__xludf.DUMMYFUNCTION("QUERY(Pedidos!A2:E1000, ""SELECT A, D, (E/0) WHERE lower(B) CONTAINS 'alfredo indajaus'"", 0)"),"") | B2: =IFERROR(__xludf.DUMMYFUNCTION("""COMPUTED_VALUE"""),"") | C2: =IFERROR(__xludf.DUMMYFUNCTION("""COMPUTED_VALUE"""),"quotient(0())") -> quotient(0()) | D2: {=IF(B2:B1000="", "", B2:B1000 - C2:C1000)} | E2: 46023 | F2: 0
A3: =IFERROR(__xludf.DUMMYFUNCTION("""COMPUTED_VALUE"""),46065.55580596065) -> 46065.556 | B3: =IFERROR(__xludf.DUMMYFUNCTION("""COMPUTED_VALUE"""),240.0) -> 240 | D3: 240 | E3: 46092 | F3: 240
A4: =IFERROR(__xludf.DUMMYFUNCTION("""COMPUTED_VALUE"""),46087.36523340278) -> 46087.365 | B4: =IFERROR(__xludf.DUMMYFUNCTION("""COMPUTED_VALUE"""),1180.0) -> 1180 | D4: 1180 | E4: 46092 | F4: 440
A5: =IFERROR(__xludf.DUMMYFUNCTION("""COMPUTED_VALUE"""),46164.65688746527) -> 46164.657 | B5: =IFERROR(__xludf.DUMMYFUNCTION("""COMPUTED_VALUE"""),595.0) -> 595 | D5: 595 | E5: 46150 | F5: 240
A6: =IFERROR(__xludf.DUMMYFUNCTION("""COMPUTED_VALUE"""),46185.52113927083) -> 46185.521 | B6: =IFERROR(__xludf.DUMMYFUNCTION("""COMPUTED_VALUE"""),330.0) -> 330 | D6: 330 | E6: 46163 | F6: 120
A7: =IFERROR(__xludf.DUMMYFUNCTION("""COMPUTED_VALUE"""),46204.93846574074) -> 46204.938 | B7: =IFERROR(__xludf.DUMMYFUNCTION("""COMPUTED_VALUE"""),330.0) -> 330 | D7: 330 | E7: 46199 | F7: 340
